Workbook

Sheet Summary All Corps
A1: Dates | B1: 1928 | C1: 1929 | D1: 1930 | E1: 1931 | F1: 1932 | G1: 1933 | H1: 1934 | I1: 1935 | J1: 1936 | K1: 1937 | L1: 1938 | M1: 1939 | N1: 1940 | O1: 1941 | P1: 1942 | Q1: 1943 | R1: 1944 | S1: 1945 | T1: 1946 | U1: 1947 | V1: 1948 | W1: 1949 | X1: 1950 | Y1: 1951 | Z1: 1952 | AA1: 1953 | AB1: 1954 | AC1: 1955 | AD1: 1956 | AE1: 1957 | AF1: 1958 | AG1: 1959 | AH1: 1960 | AI1: 1961 | AJ1: 1962 | AK1: 1963 | AL1: 1964 | AM1: 1965 | AN1: 1966 | AO1: 1967 | AP1: 1968 | AQ1: 1969 | AR1: 1970 | AS1: 1971 | AT1: 1972 | AU1: 1973 | AV1: 1974 | AW1: 1975 | AX1: 1976 | AY1: 1977 | AZ1: 1978 | BA1: 1979 | BB1: 1980 | BC1: 1981 | BD1: 1982 | BE1: 1983 | BF1: 1984 | BG1: 1985 | BH1: 1986 | BI1: 1987 | BJ1: 1988 | BK1: 1989 | BL1: 1990 | BM1: 1991 | BN1: 1992 | BO1: 1993 | BP1: 1994 | BQ1: 1995 | BR1: 1996 | BS1: 1997 | BT1: 1998 | BU1: 1999 | BV1: 2000 | BW1: 2001 | BX1: 2002 | BY1: 2003 | BZ1: 2004 | CA1: 2005 | CB1: 2006 | CC1: 2007 | CD1: 2008 | CE1: 2009 | CF1: 2010 | CG1: 2011 | CH1: 2012 | CI1: 2013 | CJ1: 2014 | CK1: 2015 | CL1: 2016 | CM1: 2017 | CN1: 2018 | CO1: 2019 | CP1: 2020 | CQ1: 2021 | CR1: 2022 | CS1: 2023 | CT1: 2024 | CU1: 2025
A2: GVA | B2: NaN | C2: ='NIPA 1.14'!C8 -> 54806 | D2: ='NIPA 1.14'!D8 -> 48178 | E2: ='NIPA 1.14'!E8 -> 37846 | F2: ='NIPA 1.14'!F8 -> 27861 | G2: ='NIPA 1.14'!G8 -> 26876 | H2: ='NIPA 1.14'!H8 -> 33500 | I2: ='NIPA 1.14'!I8 -> 37147 | J2: ='NIPA 1.14'!J8 -> 42724 | ... CT2: ='NIPA 1.14'!CT8 -> 16961079
A3: GFC | B3: NaN | C3: ='NIPA 1.14'!C9 -> 5228 | D3: ='NIPA 1.14'!D9 -> 5080 | E3: ='NIPA 1.14'!E9 -> 4752 | F3: ='NIPA 1.14'!F9 -> 4240 | G3: ='NIPA 1.14'!G9 -> 4008 | H3: ='NIPA 1.14'!H9 -> 4104 | I3: ='NIPA 1.14'!I9 -> 4184 | J3: ='NIPA 1.14'!J9 -> 4248 | ... CT3: ='NIPA 1.14'!CT9 -> 2583318
A4: Employee Compensation | B4: NaN | C4: ='NIPA 1.14'!C11 -> 34242 | D4: ='NIPA 1.14'!D11 -> 30808 | E4: ='NIPA 1.14'!E11 -> 25369 | F4: ='NIPA 1.14'!F11 -> 19013 | G4: ='NIPA 1.14'!G11 -> 18002 | H4: ='NIPA 1.14'!H11 -> 21045 | I4: ='NIPA 1.14'!I11 -> 23056 | J4: ='NIPA 1.14'!J11 -> 26274 | ... CT4: ='NIPA 1.14'!CT11 -> 9443321
A5: Indirect Business Taxes | B5: NaN | C5: ='NIPA 1.14'!C14 -> 2999 | D5: ='NIPA 1.14'!D14 -> 3037 | E5: ='NIPA 1.14'!E14 -> 2842 | F5: ='NIPA 1.14'!F14 -> 2942 | G5: ='NIPA 1.14'!G14 -> 3467 | H5: ='NIPA 1.14'!H14 -> 4090 | I5: ='NIPA 1.14'!I14 -> 4155 | J5: ='NIPA 1.14'!J14 -> 4364 | ... CT5: ='NIPA 1.14'!CT14 -> 1250767
A6: Net Operating Surplus | B6: NaN | C6: ='NIPA 1.14'!C15 -> 12337 | D6: ='NIPA 1.14'!D15 -> 9253 | E6: ='NIPA 1.14'!E15 -> 4883 | F6: ='NIPA 1.14'!F15 -> 1666 | G6: ='NIPA 1.14'!G15 -> 1399 | H6: ='NIPA 1.14'!H15 -> 4261 | I6: ='NIPA 1.14'!I15 -> 5752 | J6: ='NIPA 1.14'!J15 -> 7838 | ... CT6: ='NIPA 1.14'!CT15 -> 3683673
A7: Business Transfers | B7: NaN | C7: ='NIPA 1.14'!C17 -> 355 | D7: ='NIPA 1.14'!D17 -> 354 | E7: ='NIPA 1.14'!E17 -> 406 | F7: ='NIPA 1.14'!F17 -> 425 | G7: ='NIPA 1.14'!G17 -> 404 | H7: ='NIPA 1.14'!H17 -> 390 | I7: ='NIPA 1.14'!I17 -> 368 | J7: ='NIPA 1.14'!J17 -> 353 | ... CT7: ='NIPA 1.14'!CT17 -> 251287
A8: Taxes on Corporate Income | B8: NaN | C8: ='NIPA 1.14'!C19 -> 1365 | D8: ='NIPA 1.14'!D19 -> 842 | E8: ='NIPA 1.14'!E19 -> 498 | F8: ='NIPA 1.14'!F19 -> 383 | G8: ='NIPA 1.14'!G19 -> 521 | H8: ='NIPA 1.14'!H19 -> 744 | I8: ='NIPA 1.14'!I19 -> 951 | J8: ='NIPA 1.14'!J19 -> 1409 | ... CT8: ='NIPA 1.14'!CT19 -> 680341
A9: Investment | B9: NaN | C9: ='FA 6.7'!AE10 -> 8158 | D9: ='FA 6.7'!AF10 -> 6759 | E9: ='FA 6.7'!AG10 -> 4381 | F9: ='FA 6.7'!AH10 -> 2687 | G9: ='FA 6.7'!AI10 -> 2487 | H9: ='FA 6.7'!AJ10 -> 3085 | I9: ='FA 6.7'!AK10 -> 3574 | J9: ='FA 6.7'!AL10 -> 4598 | ... S9: ='FA 6.7'!AU10 -> 9152 | T9: ='CapitalDataL4+'!I20 -> 13908 | U9: ='CapitalDataL4+'!J20 -> 17936 | V9: ='CapitalDataL4+'!K20 -> 19821 | W9: ='CapitalDataL4+'!L20 -> 18033 | X9: ='CapitalDataL4+'!M20 -> 19819 | Y9: ='CapitalDataL4+'!N20 -> 23784 | Z9: ='CapitalDataL4+'!O20 -> 25310 | AA9: ='CapitalDataL4+'!P20 -> 28106 | ... CT9: ='CapitalDataL4+'!CI20 -> 3308281
A10: Free Cash Flow | B10: NaN | C10: =C2-C4-C5-C7-C8-C9 -> 7687 | D10: =D2-D4-D5-D7-D8-D9 -> 6378 | E10: =E2-E4-E5-E7-E8-E9 -> 4350 | F10: =F2-F4-F5-F7-F8-F9 -> 2411 | G10: =G2-G4-G5-G7-G8-G9 -> 1995 | H10: =H2-H4-H5-H7-H8-H9 -> 4146 | I10: =I2-I4-I5-I7-I8-I9 -> 5043 | J10: =J2-J4-J5-J7-J8-J9 -> 5726 | ... CT10: =CT2-CT4-CT5-CT7-CT8-CT9 -> 2027082
A11: Reproduction Value of Capital | B11: ='FA 6.1'!F10 -> 106916 | C11: ='FA 6.1'!G10 -> 106016 | D11: ='FA 6.1'!H10 -> 100962 | E11: ='FA 6.1'!I10 -> 90747 | F11: ='FA 6.1'!J10 -> 84747 | G11: ='FA 6.1'!K10 -> 85527 | H11: ='FA 6.1'!L10 -> 86754 | I11: ='FA 6.1'!M10 -> 86308 | ... R11: ='FA 6.1'!V10 -> 126747 | S11: ='CapitalDataL4+'!H19 -> 139208 | T11: ='CapitalDataL4+'!I19 -> 168356 | U11: ='CapitalDataL4+'!J19 -> 200698 | V11: ='CapitalDataL4+'!K19 -> 219642 | W11: ='CapitalDataL4+'!L19 -> 223678 | X11: ='CapitalDataL4+'!M19 -> 250857 | Y11: ='CapitalDataL4+'!N19 -> 272459 | Z11: ='CapitalDataL4+'!O19 -> 288532 | ... CT11: ='CapitalDataL4+'!CI19 -> 27603501
A12: Enterprise Value | B12: ='SOI 1945'!E16 -> 173056.56 | C12: ='SOI 1945'!F16 -> 164239.53 | D12: ='SOI 1945'!G16 -> 132259.85 | E12: ='SOI 1945'!H16 -> 85383.618 | F12: ='SOI 1945'!I16 -> 73446.334 | G12: ='SOI 1945'!J16 -> 96459.518 | H12: ='SOI 1945'!K16 -> 84167.436 | I12: ='SOI 1945'!L16 -> 111217.37 | ... R12: ='SOI 1945'!U16 -> 140989.25 | S12: ='B1'!G16+'B1'!G17 -> 152328 | T12: ='B1'!H16+'B1'!H17 -> 158831 | U12: ='B1'!I16+'B1'!I17 -> 161921 | V12: ='B1'!J16+'B1'!J17 -> 165216 | W12: ='B1'!K16+'B1'!K17 -> 170947 | X12: ='B1'!L16+'B1'!L17 -> 199319 | Y12: ='B1'!M16+'B1'!M17 -> 246419 | Z12: ='B1'!N16+'B1'!N17 -> 240284 | ... CT12: ='B1'!CH16+'B1'!CH17 -> 81137445
A13: Direct Capital Revaluations | B13: NaN | C13: NaN | D13: NaN | E13: NaN | F13: NaN | G13: NaN | H13: NaN | I13: NaN | J13: NaN | K13: NaN | L13: NaN | M13: NaN | N13: NaN | O13: NaN | P13: NaN | Q13: NaN | R13: NaN | S13: NaN | T13: ='CapitalDataL4+'!I22 -> 23297 | U13: ='CapitalDataL4+'!J22 -> 24275 | V13: ='CapitalDataL4+'!K22 -> 10695 | W13: ='CapitalDataL4+'!L22 -> -1493 | X13: ='CapitalDataL4+'!M22 -> 20749 | Y13: ='CapitalDataL4+'!N22 -> 13071 | Z13: ='CapitalDataL4+'!O22 -> 7006 | AA13: ='CapitalDataL4+'!P22 -> 4234 | ... CT13: ='CapitalDataL4+'!CI22 -> 192800
A14: Top Corp Tax Rate | B14: ='Top Corporate Tax Rate'!B5 -> 0.12 | C14: ='Top Corporate Tax Rate'!C5 -> 0.11 | D14: ='Top Corporate Tax Rate'!D5 -> 0.12 | E14: ='Top Corporate Tax Rate'!E5 -> 0.12 | F14: ='Top Corporate Tax Rate'!F5 -> 0.1375 | G14: ='Top Corporate Tax Rate'!G5 -> 0.1375 | H14: ='Top Corporate Tax Rate'!H5 -> 0.1375 | I14: ='Top Corporate Tax Rate'!I5 -> 0.1375 | ... CT14: ='Top Corporate Tax Rate'!CT5 -> 0.21
A15: Gravelle EMTR | B15: ='Gravelle Rates'!B5 -> NaN | C15: ='Gravelle Rates'!C5 -> NaN | D15: ='Gravelle Rates'!D5 -> NaN | E15: ='Gravelle Rates'!E5 -> NaN | F15: ='Gravelle Rates'!F5 -> NaN | G15: ='Gravelle Rates'!G5 -> NaN | H15: ='Gravelle Rates'!H5 -> NaN | I15: ='Gravelle Rates'!I5 -> NaN | ... CT15: ='Gravelle Rates'!CT5 -> NaN
A16: PCE Deflator | B16: NaN | C16: ='PCE Deflator'!C8 -> 8.787 | D16: ='PCE Deflator'!D8 -> 8.415 | E16: ='PCE Deflator'!E8 -> 7.514 | F16: ='PCE Deflator'!F8 -> 6.627 | G16: ='PCE Deflator'!G8 -> 6.391 | H16: ='PCE Deflator'!H8 -> 6.681 | I16: ='PCE Deflator'!I8 -> 6.846 | J16: ='PCE Deflator'!J8 -> 6.909 | ... CT16: ='PCE Deflator'!CT8 -> 123.666
A17: CRSP Rwd | B17: ='CRSP Data'!D2 -> 0.3913965 | C17: ='CRSP Data'!E2 -> -0.1509553 | D17: ='CRSP Data'!F2 -> -0.2890045 | E17: ='CRSP Data'!G2 -> -0.4438795 | F17: ='CRSP Data'!H2 -> -0.07944798 | G17: ='CRSP Data'!I2 -> 0.5741313 | H17: ='CRSP Data'!J2 -> 0.03184588 | I17: ='CRSP Data'!K2 -> 0.454487 | ... CT17: ='CRSP Data'!CV2 -> 0.228557
A18: One Year Nominal Rate | B18: NaN | C18: NaN | D18: NaN | E18: NaN | F18: NaN | G18: NaN | H18: NaN | I18: NaN | J18: NaN | K18: NaN | L18: NaN | M18: NaN | N18: NaN | O18: NaN | P18: NaN | Q18: NaN | R18: NaN | S18: NaN | T18: NaN | U18: NaN | V18: NaN | W18: NaN | X18: NaN | Y18: NaN | Z18: NaN | AA18: NaN | AB18: ='Interest Rates'!B33 -> 1.21 | AC18: ='Interest Rates'!C33 -> 2.73 | AD18: ='Interest Rates'!D33 -> 3.68 | AE18: ='Interest Rates'!E33 -> 3.18 | AF18: ='Interest Rates'!F33 -> 3.29 | AG18: ='Interest Rates'!G33 -> 5.14 | AH18: ='Interest Rates'!H33 -> 2.86 | AI18: ='Interest Rates'!I33 -> 3.18 | ... CT18: ='Interest Rates'!BT33 -> 4.23
A19: Ten Year Nominal Rate | B19: ='Interest Rates'!E10 -> 3.45 | C19: ='Interest Rates'!F10 -> 3.36 | D19: ='Interest Rates'!G10 -> 3.22 | E19: ='Interest Rates'!H10 -> 3.93 | F19: ='Interest Rates'!I10 -> 3.35 | G19: ='Interest Rates'!J10 -> 3.53 | H19: ='Interest Rates'!K10 -> 3.01 | I19: ='Interest Rates'!L10 -> 2.84 | ... AA19: ='Interest Rates'!AD10 -> 2.79 | AB19: ='Interest Rates'!B21 -> 2.51 | AC19: ='Interest Rates'!C21 -> 2.96 | AD19: ='Interest Rates'!D21 -> 3.59 | AE19: ='Interest Rates'!E21 -> 3.21 | AF19: ='Interest Rates'!F21 -> 3.86 | AG19: ='Interest Rates'!G21 -> 4.69 | AH19: ='Interest Rates'!H21 -> 3.84 | AI19: ='Interest Rates'!I21 -> 4.06 | ... CT19: ='Interest Rates'!BT21 -> 4.39
A20: Cleveland Ten Year Real Rate | B20: NaN | C20: NaN | D20: NaN | E20: NaN | F20: NaN | G20: NaN | H20: NaN | I20: NaN | J20: NaN | K20: NaN | L20: NaN | M20: NaN | N20: NaN | O20: NaN | P20: NaN | Q20: NaN | R20: NaN | S20: NaN | T20: NaN | U20: NaN | V20: NaN | W20: NaN | X20: NaN | Y20: NaN | Z20: NaN | AA20: NaN | AB20: NaN | AC20: NaN | AD20: NaN | AE20: NaN | AF20: NaN | AG20: NaN | AH20: NaN | AI20: NaN | AJ20: NaN | AK20: NaN | AL20: NaN | AM20: NaN | AN20: NaN | AO20: NaN | AP20: NaN | AQ20: NaN | AR20: NaN | AS20: NaN | AT20: NaN | AU20: NaN | AV20: NaN | AW20: NaN | AX20: NaN | AY20: NaN | AZ20: NaN | BA20: NaN | BB20: NaN | BC20: NaN | BD20: ='Interest Rates'!B46 -> 5.8817314 | BE20: ='Interest Rates'!C46 -> 6.1484245 | BF20: ='Interest Rates'!D46 -> 6.0756251 | BG20: ='Interest Rates'!E46 -> 5.0807695 | BH20: ='Interest Rates'!F46 -> 3.5437344 | BI20: ='Interest Rates'!G46 -> 4.5792755 | BJ20: ='Interest Rates'!H46 -> 4.6179387 | BK20: ='Interest Rates'!I46 -> 4.0296658 | ... CT20: ='Interest Rates'!AR46 -> 1.8243688
A21: One Year Inflation Expectations | B21: NaN | C21: NaN | D21: NaN | E21: NaN | F21: NaN | G21: NaN | H21: NaN | I21: NaN | J21: NaN | K21: NaN | L21: NaN | M21: NaN | N21: NaN | O21: NaN | P21: NaN | Q21: NaN | R21: NaN | S21: NaN | T21: NaN | U21: NaN | V21: NaN | W21: NaN | X21: NaN | Y21: NaN | Z21: NaN | AA21: NaN | AB21: NaN | AC21: NaN | AD21: NaN | AE21: NaN | AF21: NaN | AG21: NaN | AH21: NaN | AI21: NaN | AJ21: NaN | AK21: NaN | AL21: NaN | AM21: NaN | AN21: NaN | AO21: NaN | AP21: NaN | AQ21: NaN | AR21: ='Inflation Forecasts'!B6 -> 3.5414 | AS21: ='Inflation Forecasts'!C6 -> 3.4194 | AT21: ='Inflation Forecasts'!D6 -> 3.6999 | AU21: ='Inflation Forecasts'!E6 -> 5.3651 | AV21: ='Inflation Forecasts'!F6 -> 7.6814 | AW21: ='Inflation Forecasts'!G6 -> 6.2087 | AX21: ='Inflation Forecasts'!H6 -> 5.729 | AY21: ='Inflation Forecasts'!I6 -> 5.9557 | ... BQ21: ='Inflation Forecasts'!AA6 -> 2.3505 | BR21: NaN | BS21: NaN | BT21: NaN | BU21: NaN | BV21: NaN | BW21: NaN | BX21: NaN | BY21: NaN | BZ21: NaN | CA21: NaN | CB21: NaN | CC21: NaN | CD21: NaN | CE21: NaN | CF21: NaN | CG21: NaN | CH21: NaN | CI21: NaN | CJ21: NaN | CK21: NaN | CL21: NaN | CM21: NaN | CN21: NaN | CO21: NaN | CP21: NaN | CQ21: NaN | CR21: NaN | CS21: NaN | CT21: NaN
A22: Ten Year Inflation Expectations | B22: NaN | C22: NaN | D22: NaN | E22: NaN | F22: NaN | G22: NaN | H22: NaN | I22: NaN | J22: NaN | K22: NaN | L22: NaN | M22: NaN | N22: NaN | O22: NaN | P22: NaN | Q22: NaN | R22: NaN | S22: NaN | T22: NaN | U22: NaN | V22: NaN | W22: NaN | X22: NaN | Y22: NaN | Z22: NaN | AA22: NaN | AB22: NaN | AC22: NaN | AD22: NaN | AE22: NaN | AF22: NaN | AG22: NaN | AH22: NaN | AI22: NaN | AJ22: NaN | AK22: NaN | AL22: NaN | AM22: NaN | AN22: NaN | AO22: NaN | AP22: NaN | AQ22: NaN | AR22: NaN | AS22: NaN | AT22: NaN | AU22: NaN | AV22: NaN | AW22: NaN | AX22: NaN | AY22: NaN | AZ22: NaN | BA22: ='Inflation Forecasts'!K7 -> 6.9 | BB22: ='Inflation Forecasts'!L7 -> 8.25 | BC22: ='Inflation Forecasts'!M7 -> 7.05 | BD22: ='Inflation Forecasts'!N7 -> 5.65 | BE22: ='Inflation Forecasts'!O7 -> 5.2 | BF22: ='Inflation Forecasts'!P7 -> 5.2 | BG22: ='Inflation Forecasts'!Q7 -> 4.55 | BH22: ='Inflation Forecasts'!R7 -> 4 | ... BQ22: ='Inflation Forecasts'!AA7 -> 3 | BR22: NaN | BS22: NaN | BT22: NaN | BU22: NaN | BV22: NaN | BW22: NaN | BX22: NaN | BY22: NaN | BZ22: NaN | CA22: NaN | CB22: NaN | CC22: NaN | CD22: NaN | CE22: NaN | CF22: NaN | CG22: NaN | CH22: NaN | CI22: NaN | CJ22: NaN | CK22: NaN | CL22: NaN | CM22: NaN | CN22: NaN | CO22: NaN | CP22: NaN | CQ22: NaN | CR22: NaN | CS22: NaN | CT22: NaN
A23: Ten Year Real Rate Extended | B23: NaN | C23: NaN | D23: NaN | E23: NaN | F23: NaN | G23: NaN | H23: NaN | I23: NaN | J23: NaN | K23: NaN | L23: NaN | M23: NaN | N23: NaN | O23: NaN | P23: NaN | Q23: NaN | R23: NaN | S23: NaN | T23: NaN | U23: NaN | V23: NaN | W23: NaN | X23: NaN | Y23: NaN | Z23: NaN | AA23: NaN | AB23: NaN | AC23: NaN | AD23: NaN | AE23: NaN | AF23: NaN | AG23: NaN | AH23: NaN | AI23: NaN | AJ23: NaN | AK23: NaN | AL23: NaN | AM23: NaN | AN23: NaN | AO23: NaN | AP23: NaN | AQ23: NaN | AR23: =AR19-AR21 -> 2.8486 | AS23: =AS19-AS21 -> 2.5106 | AT23: =AT19-AT21 -> 2.6601 | AU23: =AU19-AU21 -> 1.3749 | AV23: =AV19-AV21 -> -0.2514 | AW23: =AW19-AW21 -> 1.7913 | AX23: =AX19-AX21 -> 1.141 | AY23: =AY19-AY21 -> 1.7343 | AZ23: =AZ19-AZ21 -> 1.9173 | BA23: =BA19-BA22 -> 3.49 | BB23: =BB19-BB22 -> 4.59 | BC23: =BC19-BC22 -> 6.67 | BD23: =BD19-BD22 -> 4.89 | BE23: =BE19-BE22 -> 6.63 | BF23: =BF19-BF22 -> 6.3 | BG23: =BG19-BG22 -> 4.71 | BH23: =BH19-BH22 -> 3.11 | ... BQ23: =BQ19-BQ22 -> 2.71 | BR23: NaN | BS23: NaN | BT23: NaN | BU23: NaN | BV23: NaN | BW23: NaN | BX23: NaN | BY23: NaN | BZ23: NaN | CA23: NaN | CB23: NaN | CC23: NaN | CD23: NaN | CE23: NaN | CF23: NaN | CG23: NaN | CH23: NaN | CI23: NaN | CJ23: NaN | CK23: NaN | CL23: NaN | CM23: NaN | CN23: NaN | CO23: NaN | CP23: NaN | CQ23: NaN | CR23: NaN | CS23: NaN | CT23: NaN
A24: rstar LW | B24: NaN | C24: NaN | D24: NaN | E24: NaN | F24: NaN | G24: NaN | H24: NaN | I24: NaN | J24: NaN | K24: NaN | L24: NaN | M24: NaN | N24: NaN | O24: NaN | P24: NaN | Q24: NaN | R24: NaN | S24: NaN | T24: NaN | U24: NaN | V24: NaN | W24: NaN | X24: NaN | Y24: NaN | Z24: NaN | AA24: NaN | AB24: NaN | AC24: NaN | AD24: NaN | AE24: NaN | AF24: NaN | AG24: NaN | AH24: NaN | AI24: ='rstar estimates'!B17 -> 4.3229116 | AJ24: ='rstar estimates'!C17 -> 4.2908936 | AK24: ='rstar estimates'!D17 -> 4.310704 | AL24: ='rstar estimates'!E17 -> 4.313279 | AM24: ='rstar estimates'!F17 -> 4.2307805 | AN24: ='rstar estimates'!G17 -> 4.0618104 | AO24: ='rstar estimates'!H17 -> 3.9081264 | AP24: ='rstar estimates'!I17 -> 3.6876784 | ... CT24: ='rstar estimates'!BM17 -> 1.5445383
A25: rstar HLW | B25: NaN | C25: NaN | D25: NaN | E25: NaN | F25: NaN | G25: NaN | H25: NaN | I25: NaN | J25: NaN | K25: NaN | L25: NaN | M25: NaN | N25: NaN | O25: NaN | P25: NaN | Q25: NaN | R25: NaN | S25: NaN | T25: NaN | U25: NaN | V25: NaN | W25: NaN | X25: NaN | Y25: NaN | Z25: NaN | AA25: NaN | AB25: NaN | AC25: NaN | AD25: NaN | AE25: NaN | AF25: NaN | AG25: NaN | AH25: NaN | AI25: ='rstar estimates'!B21 -> 5.5022072 | AJ25: ='rstar estimates'!C21 -> 4.223001 | AK25: ='rstar estimates'!D21 -> 4.2365271 | AL25: ='rstar estimates'!E21 -> 4.3053377 | AM25: ='rstar estimates'!F21 -> 5.1099439 | AN25: ='rstar estimates'!G21 -> 5.0467335 | AO25: ='rstar estimates'!H21 -> 4.7519318 | AP25: ='rstar estimates'!I21 -> 4.7482959 | ... CT25: ='rstar estimates'!BM21 -> 0.91973286
A26: rstar DelNegro | B26: ='rstar estimates'!B29 -> 1.7683695 | C26: ='rstar estimates'!C29 -> 1.7253975 | D26: ='rstar estimates'!D29 -> 1.6538956 | E26: ='rstar estimates'!E29 -> 1.6858968 | F26: ='rstar estimates'!F29 -> 1.668671 | G26: ='rstar estimates'!G29 -> 1.6165772 | H26: ='rstar estimates'!H29 -> 1.5381355 | I26: ='rstar estimates'!I29 -> 1.4950429 | ... CT26: ='rstar estimates'!CT29 -> NaN
A27: SP Earnings Yield | B27: 0.054078396 | C27: 0.070465325 | D27: 0.078361586 | E27: 0.087915662 | F27: 0.070476148 | G27: 0.043638643 | H27: 0.050496877 | I27: 0.057240047 | J27: 0.052391368 | K27: 0.10429037 | L27: 0.061875003 | M27: 0.06291684 | N27: 0.09821052 | O27: 0.13404121 | P27: 0.10973215 | Q27: 0.092395006 | R27: 0.07113386 | S27: 0.056911023 | T27: 0.066662007 | U27: 0.098943277 | V27: 0.12696587 | W27: 0.14203692 | X27: 0.1352645 | Y27: 0.11600427 | Z27: 0.091855623 | AA27: 0.10080819 | AB27: 0.074530637 | AC27: 0.071447211 | AD27: 0.077809928 | AE27: 0.085695527 | AF27: 0.056177462 | AG27: 0.056186575 | AH27: 0.058679526 | AI27: 0.043321962 | AJ27: 0.055663702 | AK27: 0.052412501 | AL27: 0.051971369 | AM27: 0.05356292 | AN27: 0.067730958 | AO27: 0.057284553 | AP27: 0.053387816 | AQ27: 0.065789246 | AR27: 0.062249744 | AS27: 0.054953032 | AT27: 0.05210128 | AU27: 0.08032695 | AV27: 0.1367668 | AW27: 0.094396568 | AX27: 0.089612378 | AY27: 0.11402825 | AZ27: 0.12298138 | BA27: 0.137001 | BB27: 0.11722883 | BC27: 0.12537116 | BD27: 0.10183552 | BE27: 0.080208812 | BF27: 0.098231724 | BG27: 0.076650231 | BH27: 0.059414084 | BI27: 0.065157415 | BJ27: 0.077909969 | BK27: 0.07082455 | BL27: 0.067413357 | BM27: 0.049456582 | BN27: 0.040221902 | BO27: 0.043602568 | BP27: 0.057053113 | BQ27: 0.055309154 | BR27: 0.048314613 | BS27: 0.041981009 | BT27: 0.032739088 | BU27: 0.029693351 | BV27: 0.039089335 | BW27: 0.031331619 | BX27: 0.030216033 | BY27: 0.033622266 | BZ27: 0.046441183 | CA27: 0.051082618 | CB27: 0.053588777 | CC27: 0.054468453 | CD27: 0.052738091 | CE27: 0.014875349 | CF27: 0.05431698 | CG27: 0.067749783 | CH27: 0.061458309 | CI27: 0.050997599 | CJ27: 0.049674204 | CK27: 0.045752124 | CL27: 0.039659361 | CM27: 0.039266118 | CN27: 0.048038174 | CO27: 0.042689134 | CP27: 0.028812774 | CQ27: 0.034314364 | CR27: 0.049204095 | CS27: 0.039009574 | CT27: 0.0331661
A28: SPDividend Yield | B28: 0.035014354 | C28: 0.042854404 | D28: 0.060650873 | E28: 0.10154612 | F28: 0.090781216 | G28: 0.047905616 | H28: 0.048162084 | I28: 0.034568752 | J28: 0.033949156 | K28: 0.071154794 | L28: 0.054516129 | M28: 0.044611844 | N28: 0.062210142 | O28: 0.083159772 | P28: 0.07077026 | Q28: 0.052181169 | R28: 0.048658645 | S28: 0.038136488 | T28: 0.050082834 | U28: 0.053430378 | V28: 0.05725022 | W28: 0.061589404 | X28: 0.066449389 | Y28: 0.065759298 | Z28: 0.055323115 | AA28: 0.057541079 | AB28: 0.041945151 | AC28: 0.035057885 | AD28: 0.038676383 | AE28: 0.043826912 | AF28: 0.03273433 | AG28: 0.030623874 | AH28: 0.034369728 | AI28: 0.027407677 | AJ28: 0.033181777 | AK28: 0.029891819 | AL28: 0.02868186 | AM28: 0.028786714 | AN28: 0.035267714 | AO28: 0.030988368 | AP28: 0.028724853 | AQ28: 0.035283628 | AR28: 0.036114812 | AS28: 0.031717314 | AT28: 0.026692613 | AU28: 0.035584017 | AV28: 0.055175216 | AW28: 0.042867437 | AX28: 0.037175364 | AY28: 0.047796594 | AZ28: 0.053094908 | BA28: 0.052719862 | BB28: 0.04668245 | BC28: 0.053583431 | BD28: 0.049286422 | BE28: 0.043101838 | BF28: 0.045061495 | BG28: 0.038007281 | BH28: 0.03295133 | BI28: 0.035979123 | BJ28: 0.034144668 | BK28: 0.030349713 | BL28: 0.036261301 | BM28: 0.031740537 | BN28: 0.028645197 | BO28: 0.027094784 | BP28: 0.028539574 | BQ28: 0.022007553 | BR28: 0.01957471 | BS28: 0.015884026 | BT28: 0.013456479 | BU28: 0.011680604 | BV28: 0.01257103 | BW28: 0.013797816 | BX28: 0.017764303 | BY28: 0.015280196 | BZ28: 0.015652142 | CA28: 0.016748239 | CB28: 0.016662036 | CC28: 0.018044666 | CD28: 0.031722842 | CE28: 0.022938307 | CF28: 0.017995999 | CG28: 0.019794714 | CH28: 0.020194486 | CI28: 0.018470772 | CJ28: 0.018112579 | CK28: 0.02029807 | CL28: 0.019957695 | CM28: 0.017893296 | CN28: 0.02001691 | CO28: 0.017794762 | CP28: 0.016095453 | CQ28: 0.012901998 | CR28: 0.016590731 | CS28: 0.014794483 | CT28: 0.012114331
A29: trend g HLW | B29: NaN | C29: NaN | D29: NaN | E29: NaN | F29: NaN | G29: NaN | H29: NaN | I29: NaN | J29: NaN | K29: NaN | L29: NaN | M29: NaN | N29: NaN | O29: NaN | P29: NaN | Q29: NaN | R29: NaN | S29: NaN | T29: NaN | U29: NaN | V29: NaN | W29: NaN | X29: NaN | Y29: NaN | Z29: NaN | AA29: NaN | AB29: NaN | AC29: NaN | AD29: NaN | AE29: NaN | AF29: NaN | AG29: NaN | AH29: NaN | AI29: ='rstar estimates'!B22 -> 5.0535728 | AJ29: ='rstar estimates'!C22 -> 3.895209 | AK29: ='rstar estimates'!D22 -> 3.887629 | AL29: ='rstar estimates'!E22 -> 3.9847854 | AM29: ='rstar estimates'!F22 -> 4.7193122 | AN29: ='rstar estimates'!G22 -> 4.5944173 | AO29: ='rstar estimates'!H22 -> 4.3377748 | AP29: ='rstar estimates'!I22 -> 4.3117097 | ... CT29: ='rstar estimates'!BM22 -> 2.4565514
A30: Bauer Rudebusch rstar (end of year) | B30: NaN | C30: NaN | D30: NaN | E30: NaN | F30: NaN | G30: NaN | H30: NaN | I30: NaN | J30: NaN | K30: NaN | L30: NaN | M30: NaN | N30: NaN | O30: NaN | P30: NaN | Q30: NaN | R30: NaN | S30: NaN | T30: NaN | U30: NaN | V30: NaN | W30: NaN | X30: NaN | Y30: NaN | Z30: NaN | AA30: NaN | AB30: NaN | AC30: NaN | AD30: NaN | AE30: NaN | AF30: NaN | AG30: NaN | AH30: NaN | AI30: NaN | AJ30: NaN | AK30: NaN | AL30: NaN | AM30: NaN | AN30: NaN | AO30: NaN | AP30: NaN | AQ30: NaN | AR30: NaN | AS30: 2.1150066 | AT30: 2.1349668 | AU30: 2.1929508 | AV30: 1.7969603 | AW30: 1.7611073 | AX30: 1.6244953 | AY30: 1.5726897 | AZ30: 1.7944572 | BA30: 1.8939945 | BB30: 2.02581 | BC30: 2.0749039 | BD30: 1.9782419 | BE30: 2.2455671 | BF30: 2.4474308 | BG30: 2.4583929 | BH30: 2.379612 | BI30: 2.4438086 | BJ30: 2.6063283 | BK30: 2.6222987 | BL30: 2.492771 | BM30: 2.3812134 | BN30: 2.1966115 | BO30: 2.048737 | BP30: 2.1657986 | BQ30: 2.1921596 | BR30: 2.26921 | BS30: 2.3776836 | BT30: 2.5032879 | BU30: 2.6051738 | BV30: 2.692727 | BW30: 2.4086588 | BX30: 2.1730293 | BY30: 2.0319014 | BZ30: 1.8900346 | CA30: 1.9121786 | CB30: 1.9892265 | CC30: 1.8565944 | CD30: 1.1940393 | CE30: 1.1300649 | CF30: 0.91496597 | CG30: 0.84017309 | CH30: 0.68972432 | CI30: 0.68480369 | CJ30: 0.62333976 | CK30: 0.59253781 | CL30: 0.52135301 | CM30: 0.53593275 | CN30: NaN | CO30: NaN | CP30: NaN | CQ30: NaN | CR30: NaN | CS30: NaN | CT30: NaN
C34: =+C1 -> 1929 | D34: =+D1 -> 1930 | E34: =+E1 -> 1931 | F34: =+F1 -> 1932 | G34: =+G1 -> 1933 | H34: =+H1 -> 1934 | I34: =+I1 -> 1935 | J34: =+J1 -> 1936 | ... CT34: =+CT1 -> 2024
B35: tax/NOS | C35: =+C8/C6 -> 0.11064278 | D35: =+D8/D6 -> 0.090997514 | E35: =+E8/E6 -> 0.10198648 | F35: =+F8/F6 -> 0.22989196 | G35: =+G8/G6 -> 0.37240886 | H35: =+H8/H6 -> 0.1746069 | I35: =+I8/I6 -> 0.1653338 | J35: =+J8/J6 -> 0.17976525 | ... CT35: =+CT8/CT6 -> 0.18469093
B36: max rate | C36: =+C14 -> 0.11 | D36: =+D14 -> 0.12 | E36: =+E14 -> 0.12 | F36: =+F14 -> 0.1375 | G36: =+G14 -> 0.1375 | H36: =+H14 -> 0.1375 | I36: =+I14 -> 0.1375 | J36: =+J14 -> 0.15 | ... CT36: =+CT14 -> 0.21
B37: (tax+transfers)/NOS | C37: =+(C7+C8)/C6 -> 0.13941801 | D37: =+(D7+D8)/D6 -> 0.12925538 | E37: =+(E7+E8)/E6 -> 0.18513209 | F37: =+(F7+F8)/F6 -> 0.484994 | G37: =+(G7+G8)/G6 -> 0.66118656 | H37: =+(H7+H8)/H6 -> 0.26613471 | I37: =+(I7+I8)/I6 -> 0.22931154 | J37: =+(J7+J8)/J6 -> 0.22480225 | ... CT37: =+(CT7+CT8)/CT6 -> 0.25290736
B38: IBT+bt/gva | C38: =+(C5+C7)/C2 -> 0.061197679 | D38: =+(D5+D7)/D2 -> 0.070384823 | E38: =+(E5+E7)/E2 -> 0.085821487 | F38: =+(F5+F7)/F2 -> 0.12084993 | G38: =+(G5+G7)/G2 -> 0.14403185 | H38: =+(H5+H7)/H2 -> 0.13373134 | I38: =+(I5+I7)/I2 -> 0.1217595 | J38: =+(J5+J7)/J2 -> 0.11040633 | ... CT38: =+(CT5+CT7)/CT2 -> 0.088558871
B41: Net Invest/QK | C41: =(C9-C3)/C11 -> 0.027637338 | D41: =(D9-D3)/D11 -> 0.016630019 | E41: =(E9-E3)/E11 -> -0.0040882894 | F41: =(F9-F3)/F11 -> -0.018325132 | G41: =(G9-G3)/G11 -> -0.017783858 | H41: =(H9-H3)/H11 -> -0.011745856 | I41: =(I9-I3)/I11 -> -0.007067711 | J41: =(J9-J3)/J11 -> 0.0036870437 | ... CT41: =(CT9-CT3)/CT11 -> 0.026263444
B42: Tobins Q | C42: =C12/C11 - 1 -> 0.54919569 | D42: =D12/D11 - 1 -> 0.30999636 | E42: =E12/E11 - 1 -> -0.059102579 | F42: =F12/F11 - 1 -> -0.13334591 | G42: =G12/G11 - 1 -> 0.12782535 | H42: =H12/H11 - 1 -> -0.029814928 | I42: =I12/I11 - 1 -> 0.28861021 | J42: =J12/J11 - 1 -> 0.49244023 | ... CT42: =CT12/CT11 - 1 -> 1.9393896
B44: QK3 | C44: =3*C41+1 -> 1.082912 | D44: =3*D41+1 -> 1.0498901 | E44: =3*E41+1 -> 0.98773513 | F44: =3*F41+1 -> 0.9450246 | G44: =3*G41+1 -> 0.94664843 | H44: =3*H41+1 -> 0.96476243 | I44: =3*I41+1 -> 0.97879687 | J44: =3*J41+1 -> 1.0110611 | ... CT44: =3*CT41+1 -> 1.0787903
B45: QK8 | C45: =8*C41+1 -> 1.2210987 | D45: =8*D41+1 -> 1.1330402 | E45: =8*E41+1 -> 0.96729368 | F45: =8*F41+1 -> 0.85339894 | G45: =8*G41+1 -> 0.85772914 | H45: =8*H41+1 -> 0.90603315 | I45: =8*I41+1 -> 0.94345831 | J45: =8*J41+1 -> 1.0294963 | ... CT45: =8*CT41+1 -> 1.2101076
B47: VPi0 | C47: =C12/C2-C11/C2 -> 1.0623569 | D47: =D12/D2-D11/D2 -> 0.64962955 | E47: =E12/E2-E11/E2 -> -0.14171595 | F47: =F12/F2-F11/F2 -> -0.40560878 | G47: =G12/G2-G11/G2 -> 0.40677624 | H47: =H12/H2-H11/H2 -> -0.077210874 | I47: =I12/I2-I11/I2 -> 0.6705621 | J47: =J12/J2-J11/J2 -> 1.0941362 | ... CT47: =CT12/CT2-CT11/CT2 -> 3.1562817
B48: VPi3 | C48: =C12/C2-C44*C11/C2 -> 0.90197297 | D48: =D12/D2-D44*D11/D2 -> 0.54507976 | E48: =E12/E2-E44*E11/E2 -> -0.11230729 | F48: =F12/F2-F44*F11/F2 -> -0.23838578 | G48: =G12/G2-G44*G11/G2 -> 0.57655597 | H48: =H12/H2-H44*H11/H2 -> 0.014042857 | I48: =I12/I2-I44*I11/I2 -> 0.71982584 | J48: =J12/J2-J44*J11/J2 -> 1.0695598 | ... CT48: =CT12/CT2-CT44*CT11/CT2 -> 3.0280535
B49: VPi8 | C49: =C12/C2-C45*C11/C2 -> 0.63466647 | D49: =D12/D2-D45*D11/D2 -> 0.3708301 | E49: =E12/E2-E45*E11/E2 -> -0.063292864 | F49: =F12/F2-F45*F11/F2 -> 0.040319222 | G49: =G12/G2-G45*G11/G2 -> 0.85952219 | H49: =H12/H2-H45*H11/H2 -> 0.16613241 | I49: =I12/I2-I45*I11/I2 -> 0.80193206 | J49: =J12/J2-J45*J11/J2 -> 1.0285992 | ... CT49: =CT12/CT2-CT45*CT11/CT2 -> 2.8143398

Sheet B1
A1: Download Page | F1: Z.1 Statistical Release for Jan 09, 2026
A2: Descriptions: | B2: Unit: | C2: Multiplier: | D2: Currency: | E2: Unique Identifier: | F2: Series Name: | G2: 1945 | H2: 1946 | I2: 1947 | J2: 1948 | K2: 1949 | L2: 1950 | M2: 1951 | N2: 1952 | O2: 1953 | P2: 1954 | Q2: 1955 | R2: 1956 | S2: 1957 | T2: 1958 | U2: 1959 | V2: 1960 | W2: 1961 | X2: 1962 | Y2: 1963 | Z2: 1964 | AA2: 1965 | AB2: 1966 | AC2: 1967 | AD2: 1968 | AE2: 1969 | AF2: 1970 | AG2: 1971 | AH2: 1972 | AI2: 1973 | AJ2: 1974 | AK2: 1975 | AL2: 1976 | AM2: 1977 | AN2: 1978 | AO2: 1979 | AP2: 1980 | AQ2: 1981 | AR2: 1982 | AS2: 1983 | AT2: 1984 | AU2: 1985 | AV2: 1986 | AW2: 1987 | AX2: 1988 | AY2: 1989 | AZ2: 1990 | BA2: 1991 | BB2: 1992 | BC2: 1993 | BD2: 1994 | BE2: 1995 | BF2: 1996 | BG2: 1997 | BH2: 1998 | BI2: 1999 | BJ2: 2000 | BK2: 2001 | BL2: 2002 | BM2: 2003 | BN2: 2004 | BO2: 2005 | BP2: 2006 | BQ2: 2007 | BR2: 2008 | BS2: 2009 | BT2: 2010 | BU2: 2011 | BV2: 2012 | BW2: 2013 | BX2: 2014 | BY2: 2015 | BZ2: 2016 | CA2: 2017 | CB2: 2018 | CC2: 2019 | CD2: 2020 | CE2: 2021 | CF2: 2022 | CG2: 2023 | CH2: 2024
A3: All sectors; U.S. wealth | B3: Currency | C3: 1000000 | D3: USD | E3: Z1/Z1/FL892090005.A | F3: FL892090005.A | G3: 733273 | H3: 817833 | I3: 934935 | J3: 991725 | K3: 1013747 | L3: 1120186 | M3: 1269077 | N3: 1317785 | O3: 1351999 | P3: 1497113 | Q3: 1679481 | R3: 1832498 | S3: 1866771 | T3: 2080972 | U3: 2210496 | V3: 2287245 | W3: 2521742 | X3: 2598968 | Y3: 2726472 | Z3: 2911977 | AA3: 3124583 | AB3: 3243599 | AC3: 3557415 | AD3: 3974923 | AE3: 4088663 | AF3: 4322288 | AG3: 4718697 | AH3: 5294069 | AI3: 5599547 | AJ3: 5835321 | AK3: 6602817 | AL3: 7288342 | AM3: 7903176 | AN3: 8888113 | AO3: 10272149 | AP3: 11792350 | AQ3: 12769304 | AR3: 13335352 | AS3: 14148311 | AT3: 15109572 | AU3: 16485542 | AV3: 17875263 | AW3: 19004781 | AX3: 20533955 | AY3: 22293729 | AZ3: 22775596 | BA3: 24130502 | BB3: 25093678 | BC3: 26414440 | BD3: 27452078 | BE3: 29810038 | BF3: 31995017 | BG3: 35684048 | BH3: 39569603 | BI3: 45125576 | BJ3: 45817440 | BK3: 46537331 | BL3: 45990464 | BM3: 51334751 | BN3: 57772107 | BO3: 63513873 | BP3: 68590785 | BQ3: 69637948 | BR3: 59655182 | BS3: 58484178 | BT3: 63014150 | BU3: 61929247 | BV3: 65945859 | BW3: 75557851 | BX3: 80021752 | BY3: 82238878 | BZ3: 87161969 | CA3: 95332022 | CB3: 94848037 | CC3: 103033483 | CD3: 113914917 | CE3: 136205372 | CF3: 135285879 | CG3: 144557112 | CH3: 156707266
A4: Households and nonprofit organizations; nonfinancial assets | B4: Currency | C4: 1000000 | D4: USD | E4: Z1/Z1/LM152010005.A | F4: LM152010005.A | G4: 189327 | H4: 220716 | I4: 280815 | J4: 313686 | K4: 340071 | L4: 387297 | M4: 430932 | N4: 463998 | O4: 493418 | P4: 520894 | Q4: 565453 | R4: 608073 | S4: 643776 | T4: 670313 | U4: 706020 | V4: 737552 | W4: 769614 | X4: 803569 | Y4: 839163 | Z4: 884104 | AA4: 930933 | AB4: 1005985 | AC4: 1074444 | AD4: 1200814 | AE4: 1308558 | AF4: 1390677 | AG4: 1517841 | AH4: 1714199 | AI4: 1943148 | AJ4: 2064417 | AK4: 2286518 | AL4: 2543119 | AM4: 2947334 | AN4: 3407984 | AO4: 3961948 | AP4: 4451130 | AQ4: 4916768 | AR4: 5148139 | AS4: 5444411 | AT4: 6150304 | AU4: 6937161 | AV4: 7644160 | AW4: 8330141 | AX4: 9094409 | AY4: 9817681 | AZ4: 10083770 | BA4: 10308657 | BB4: 10665051 | BC4: 11136594 | BD4: 11662709 | BE4: 11929586 | BF4: 12484792 | BG4: 13201651 | BH4: 14292512 | BI4: 15542198 | BJ4: 17549453 | BK4: 19536847 | BL4: 21309764 | BM4: 23178254 | BN4: 26438362 | BO4: 29769560 | BP4: 31090978 | BQ4: 30587677 | BR4: 28105337 | BS4: 26046008 | BT4: 25650841 | BU4: 25220683 | BV4: 25840518 | BW4: 27969505 | BX4: 29654637 | BY4: 31556587 | BZ4: 33665006 | CA4: 35879789 | CB4: 37209025 | CC4: 38517398 | CD4: 42808158 | CE4: 51375030 | CF4: 54832175 | CG4: 57680864 | CH4: 60080508
A5: Households and nonprofit organizations; real estate at market value | B5: Currency | C5: 1000000 | D5: USD | E5: Z1/Z1/LM155035005.A | F5: LM155035005.A | G5: 134635 | H5: 158074 | I5: 206381 | J5: 229359 | K5: 246931 | L5: 278126 | M5: 308963 | N5: 334895 | O5: 355919 | P5: 379599 | Q5: 414487 | R5: 445773 | S5: 471674 | T5: 493819 | U5: 521544 | V5: 547589 | W5: 576368 | X5: 603604 | Y5: 628622 | Z5: 662499 | AA5: 696286 | AB5: 748935 | AC5: 794221 | AD5: 889605 | AE5: 968674 | AF5: 1025204 | AG5: 1127739 | AH5: 1290675 | AI5: 1472632 | AJ5: 1517696 | AK5: 1684206 | AL5: 1880025 | AM5: 2211304 | AN5: 2577511 | AO5: 3025997 | AP5: 3413722 | AQ5: 3803851 | AR5: 3989640 | AS5: 4209413 | AT5: 4816923 | AU5: 5492906 | AV5: 6049418 | AW5: 6598723 | AX5: 7207766 | AY5: 7797521 | AZ5: 7941478 | BA5: 8080372 | BB5: 8353177 | BC5: 8711537 | BD5: 9110695 | BE5: 9267737 | BF5: 9721072 | BG5: 10341382 | BH5: 11303625 | BI5: 12381006 | BJ5: 14160428 | BK5: 15970953 | BL5: 17564511 | BM5: 19264275 | BN5: 22283537 | BO5: 25388489 | BP5: 26497066 | BQ5: 25795258 | BR5: 23190081 | BS5: 21115293 | BT5: 20719405 | BU5: 20146017 | BV5: 20652228 | BW5: 22690165 | BX5: 24266395 | BY5: 25995204 | BZ5: 27920752 | CA5: 29972160 | CB5: 31057948 | CC5: 32126419 | CD5: 36020399 | CE5: 43564200 | CF5: 46325329 | CG5: 48912521 | CH5: 51011988
A6: Nonprofit organizations; equipment, current cost basis | B6: Currency | C6: 1000000 | D6: USD | E6: Z1/Z1/LM165015205.A | F6: LM165015205.A | G6: 436 | H6: 590 | I6: 768 | J6: 944 | K6: 1043 | L6: 1346 | M6: 1592 | N6: 1728 | O6: 1980 | P6: 2160 | Q6: 2412 | R6: 2726 | S6: 3050 | T6: 3263 | U6: 3550 | V6: 3760 | W6: 3989 | X6: 4245 | Y6: 4529 | Z6: 4873 | AA6: 5257 | AB6: 5795 | AC6: 6317 | AD6: 6876 | AE6: 7605 | AF6: 8354 | AG6: 9063 | AH6: 10558 | AI6: 12517 | AJ6: 16435 | AK6: 19180 | AL6: 21838 | AM6: 24480 | AN6: 27912 | AO6: 31525 | AP6: 36150 | AQ6: 40085 | AR6: 42670 | AS6: 45262 | AT6: 48100 | AU6: 50419 | AV6: 54289 | AW6: 58601 | AX6: 63306 | AY6: 68558 | AZ6: 74319 | BA6: 78767 | BB6: 82840 | BC6: 85114 | BD6: 87566 | BE6: 90118 | BF6: 91444 | BG6: 94611 | BH6: 103614 | BI6: 114288 | BJ6: 127343 | BK6: 140201 | BL6: 154827 | BM6: 167565 | BN6: 183824 | BO6: 197724 | BP6: 215065 | BQ6: 231681 | BR6: 255136 | BS6: 268585 | BT6: 284802 | BU6: 307356 | BV6: 326848 | BW6: 354638 | BX6: 380723 | BY6: 407721 | BZ6: 434808 | CA6: 457951 | CB6: 485525 | CC6: 514573 | CD6: 543747 | CE6: 581703 | CF6: 622277 | CG6: 653471 | CH6: 681682
A7: Nonprofit organizations; nonresidential intellectual property products, current cost basis | B7: Currency | C7: 1000000 | D7: USD | E7: Z1/Z1/LM165013765.A | F7: LM165013765.A | G7: 257 | H7: 292 | I7: 310 | J7: 310 | K7: 315 | L7: 345 | M7: 366 | N7: 375 | O7: 394 | P7: 417 | Q7: 455 | R7: 502 | S7: 555 | T7: 628 | U7: 710 | V7: 784 | W7: 882 | X7: 1011 | Y7: 1168 | Z7: 1334 | AA7: 1522 | AB7: 1738 | AC7: 1984 | AD7: 2274 | AE7: 2568 | AF7: 2862 | AG7: 3143 | AH7: 3458 | AI7: 3967 | AJ7: 4615 | AK7: 5136 | AL7: 5735 | AM7: 6434 | AN7: 7463 | AO7: 8850 | AP7: 10389 | AQ7: 12053 | AR7: 13405 | AS7: 14644 | AT7: 15698 | AU7: 16706 | AV7: 18069 | AW7: 20155 | AX7: 23011 | AY7: 26019 | AZ7: 28931 | BA7: 32071 | BB7: 35566 | BC7: 37695 | BD7: 40312 | BE7: 42425 | BF7: 44347 | BG7: 47697 | BH7: 51510 | BI7: 55811 | BJ7: 59926 | BK7: 61393 | BL7: 64242 | BM7: 68813 | BN7: 72782 | BO7: 77077 | BP7: 80588 | BQ7: 85949 | BR7: 93873 | BS7: 101997 | BT7: 111132 | BU7: 122656 | BV7: 134002 | BW7: 147368 | BX7: 155759 | BY7: 163037 | BZ7: 172718 | CA7: 182042 | CB7: 193947 | CC7: 205063 | CD7: 221738 | CE7: 233171 | CF7: 245254 | CG7: 258301 | CH7: 275648
A8: Households and nonprofit organizations; consumer durable goods, current cost basis | B8: Currency | C8: 1000000 | D8: USD | E8: Z1/Z1/LM155111005.A | F8: LM155111005.A | G8: 53999 | H8: 61760 | I8: 73356 | J8: 83073 | K8: 91782 | L8: 107480 | M8: 120011 | N8: 127000 | O8: 135125 | P8: 138718 | Q8: 148099 | R8: 159072 | S8: 168497 | T8: 172603 | U8: 180216 | V8: 185419 | W8: 188375 | X8: 194709 | Y8: 204844 | Z8: 215398 | AA8: 227868 | AB8: 249517 | AC8: 271922 | AD8: 302059 | AE8: 329711 | AF8: 354257 | AG8: 377896 | AH8: 409508 | AI8: 454032 | AJ8: 525671 | AK8: 577996 | AL8: 635521 | AM8: 705116 | AN8: 795098 | AO8: 895576 | AP8: 990869 | AQ8: 1060779 | AR8: 1102424 | AS8: 1175092 | AT8: 1269583 | AU8: 1377130 | AV8: 1522384 | AW8: 1652662 | AX8: 1800326 | AY8: 1925583 | AZ8: 2039042 | BA8: 2117447 | BB8: 2193468 | BC8: 2302248 | BD8: 2424136 | BE8: 2529306 | BF8: 2627929 | BG8: 2717961 | BH8: 2833763 | BI8: 2991093 | BJ8: 3201756 | BK8: 3364300 | BL8: 3526184 | BM8: 3677601 | BN8: 3898219 | BO8: 4106270 | BP8: 4298259 | BQ8: 4474789 | BR8: 4566247 | BS8: 4560133 | BT8: 4535502 | BU8: 4644654 | BV8: 4727440 | BW8: 4777334 | BX8: 4851760 | BY8: 4990625 | BZ8: 5136728 | CA8: 5267636 | CB8: 5471605 | CC8: 5671343 | CD8: 6022274 | CE8: 6995956 | CF8: 7639315 | CG8: 7856571 | CH8: 8111190
A9: Nonfinancial noncorporate business; nonfinancial assets | B9: Currency | C9: 1000000 | D9: USD | E9: Z1/Z1/LM112010005.A | F9: LM112010005.A | G9: 188688 | H9: 227819 | I9: 262959 | J9: 281246 | K9: 284459 | L9: 304098 | M9: 333808 | N9: 336953 | O9: 337207 | P9: 344489 | Q9: 359453 | R9: 378823 | S9: 393645 | T9: 409859 | U9: 419022 | V9: 434722 | W9: 457533 | X9: 482177 | Y9: 495124 | Z9: 521651 | AA9: 556908 | AB9: 597837 | AC9: 631468 | AD9: 685644 | AE9: 734613 | AF9: 778637 | AG9: 861877 | AH9: 969757 | AI9: 1137615 | AJ9: 1292563 | AK9: 1413727 | AL9: 1568517 | AM9: 1762657 | AN9: 2038862 | AO9: 2378693 | AP9: 2689173 | AQ9: 2883132 | AR9: 3005164 | AS9: 3120880 | AT9: 3221698 | AU9: 3353925 | AV9: 3498188 | AW9: 3669597 | AX9: 3877704 | AY9: 4070053 | AZ9: 4158524 | BA9: 4084665 | BB9: 4031762 | BC9: 4147907 | BD9: 4349727 | BE9: 4528496 | BF9: 4760461 | BG9: 5203809 | BH9: 5510571 | BI9: 5909950 | BJ9: 6393538 | BK9: 6634585 | BL9: 7078073 | BM9: 7562615 | BN9: 8602156 | BO9: 9734904 | BP9: 10511942 | BQ9: 10699790 | BR9: 9807562 | BS9: 8552329 | BT9: 9021884 | BU9: 9197054 | BV9: 9733116 | BW9: 10604929 | BX9: 11335238 | BY9: 11957273 | BZ9: 12599108 | CA9: 13363327 | CB9: 13874943 | CC9: 14670219 | CD9: 15673569 | CE9: 18261928 | CF9: 19102278 | CG9: 18758406 | CH9: 19036293
A10: Nonfinancial noncorporate business; real estate at market value | B10: Currency | C10: 1000000 | D10: USD | E10: Z1/Z1/LM115035005.A | F10: LM115035005.A | G10: 151676 | H10: 179671 | I10: 206256 | J10: 218473 | K10: 223629 | L10: 236563 | M10: 255779 | N10: 262603 | O10: 264204 | P10: 271288 | Q10: 287208 | R10: 302998 | S10: 313203 | T10: 323570 | U10: 334803 | V10: 349081 | W10: 370084 | X10: 391707 | Y10: 405397 | Z10: 430762 | AA10: 458451 | AB10: 493570 | AC10: 522958 | AD10: 569262 | AE10: 609003 | AF10: 648063 | AG10: 719630 | AH10: 812021 | AI10: 952736 | AJ10: 1092686 | AK10: 1196958 | AL10: 1341057 | AM10: 1512676 | AN10: 1742627 | AO10: 2033457 | AP10: 2313816 | AQ10: 2485585 | AR10: 2589754 | AS10: 2704845 | AT10: 2789414 | AU10: 2912260 | AV10: 3054746 | AW10: 3208385 | AX10: 3388668 | AY10: 3557102 | AZ10: 3627015 | BA10: 3558666 | BB10: 3491595 | BC10: 3598151 | BD10: 3775833 | BE10: 3938765 | BF10: 4118650 | BG10: 4544029 | BH10: 4844518 | BI10: 5209030 | BJ10: 5648078 | BK10: 5875493 | BL10: 6287628 | BM10: 6736988 | BN10: 7724369 | BO10: 8800140 | BP10: 9518182 | BQ10: 9635008 | BR10: 8706511 | BS10: 7476211 | BT10: 7903416 | BU10: 8019481 | BV10: 8528165 | BW10: 9340514 | BX10: 10018388 | BY10: 10641128 | BZ10: 11275644 | CA10: 11987975 | CB10: 12451733 | CC10: 13198031 | CD10: 14164755 | CE10: 16605068 | CF10: 17293612 | CG10: 16866688 | CH10: 17050499
A11: Nonfinancial noncorporate business; equipment, current cost basis | B11: Currency | C11: 1000000 | D11: USD | E11: Z1/Z1/LM115015205.A | F11: LM115015205.A | G11: 10964 | H11: 13074 | I11: 17090 | J11: 21750 | K11: 23749 | L11: 28420 | M11: 31385 | N11: 32717 | O11: 34704 | P11: 35044 | Q11: 38014 | R11: 40430 | S11: 42761 | T11: 43678 | U11: 45090 | V11: 45487 | W11: 45398 | X11: 46183 | Y11: 47571 | Z11: 49566 | AA11: 52385 | AB11: 56839 | AC11: 60640 | AD11: 64814 | AE11: 69951 | AF11: 75670 | AG11: 80391 | AH11: 85049 | AI11: 94515 | AJ11: 114461 | AK11: 127379 | AL11: 139076 | AM11: 153768 | AN11: 173992 | AO11: 202086 | AP11: 227609 | AQ11: 253944 | AR11: 265258 | AS11: 268073 | AT11: 275474 | AU11: 283730 | AV11: 294536 | AW11: 303632 | AX11: 319657 | AY11: 333525 | AZ11: 340708 | BA11: 341091 | BB11: 341468 | BC11: 347761 | BD11: 359958 | BE11: 373811 | BF11: 384648 | BG11: 394954 | BH11: 407455 | BI11: 424173 | BJ11: 446601 | BK11: 463398 | BL11: 478900 | BM11: 492373 | BN11: 527455 | BO11: 562305 | BP11: 607005 | BQ11: 642030 | BR11: 678964 | BS11: 671933 | BT11: 682617 | BU11: 707028 | BV11: 731801 | BW11: 768848 | BX11: 795061 | BY11: 811007 | BZ11: 819333 | CA11: 839201 | CB11: 868464 | CC11: 894903 | CD11: 920830 | CE11: 998940 | CF11: 1084767 | CG11: 1124436 | CH11: 1161744
A12: Nonfinancial noncorporate business; nonresidential intellectual property products, current cost basis | B12: Currency | C12: 1000000 | D12: USD | E12: Z1/Z1/LM115013765.A | F12: LM115013765.A | G12: 1942 | H12: 2162 | I12: 2507 | J12: 2667 | K12: 2777 | L12: 3009 | M12: 3103 | N12: 3221 | O12: 3430 | P12: 3603 | Q12: 3850 | R12: 4110 | S12: 4392 | T12: 4596 | U12: 4964 | V12: 5154 | W12: 5480 | X12: 5680 | Y12: 5958 | Z12: 6186 | AA12: 6463 | AB12: 6690 | AC12: 7023 | AD12: 7321 | AE12: 7756 | AF12: 8142 | AG12: 8216 | AH12: 8279 | AI12: 8450 | AJ12: 8953 | AK12: 9264 | AL12: 9686 | AM12: 10008 | AN12: 10959 | AO12: 12202 | AP12: 13666 | AQ12: 15311 | AR12: 16566 | AS12: 17915 | AT12: 19855 | AU12: 22012 | AV12: 24417 | AW12: 28105 | AX12: 33847 | AY12: 39929 | AZ12: 46014 | BA12: 51818 | BB12: 57225 | BC12: 62097 | BD12: 67201 | BE12: 72484 | BF12: 77023 | BG12: 82819 | BH12: 90612 | BI12: 101839 | BJ12: 114050 | BK12: 121009 | BL12: 128475 | BM12: 136837 | BN12: 143903 | BO12: 154293 | BP12: 164458 | BQ12: 175832 | BR12: 183941 | BS12: 186573 | BT12: 191485 | BU12: 196795 | BV12: 202243 | BW12: 217714 | BX12: 229951 | BY12: 243405 | BZ12: 252310 | CA12: 276603 | CB12: 293623 | CC12: 319054 | CD12: 347515 | CE12: 372475 | CF12: 412860 | CG12: 449464 | CH12: 484930
A13: Nonfinancial noncorporate business; inventories | B13: Currency | C13: 1000000 | D13: USD | E13: Z1/Z1/LM115020005.A | F13: LM115020005.A | G13: 24106 | H13: 32912 | I13: 37106 | J13: 38356 | K13: 34304 | L13: 36106 | M13: 43541 | N13: 38412 | O13: 34869 | P13: 34554 | Q13: 30381 | R13: 31285 | S13: 33289 | T13: 38015 | U13: 34165 | V13: 35000 | W13: 36571 | X13: 38607 | Y13: 36198 | Z13: 35137 | AA13: 39609 | AB13: 40738 | AC13: 40847 | AD13: 44247 | AE13: 47903 | AF13: 46762 | AG13: 53640 | AH13: 64408 | AI13: 81914 | AJ13: 76463 | AK13: 80126 | AL13: 78698 | AM13: 86205 | AN13: 111284 | AO13: 130948 | AP13: 134082 | AQ13: 128292 | AR13: 133586 | AS13: 130047 | AT13: 136955 | AU13: 135923 | AV13: 124489 | AW13: 129475 | AX13: 135532 | AY13: 139497 | AZ13: 144787 | BA13: 133090 | BB13: 141474 | BC13: 139898 | BD13: 146735 | BE13: 143436 | BF13: 180140 | BG13: 182007 | BH13: 167986 | BI13: 174908 | BJ13: 184809 | BK13: 174685 | BL13: 183070 | BM13: 196417 | BN13: 206429 | BO13: 218166 | BP13: 222297 | BQ13: 246920 | BR13: 238146 | BS13: 217612 | BT13: 244366 | BU13: 273750 | BV13: 270907 | BW13: 277853 | BX13: 291838 | BY13: 261733 | BZ13: 251821 | CA13: 259548 | CB13: 261123 | CC13: 258231 | CD13: 240469 | CE13: 285445 | CF13: 311039 | CG13: 317818 | CH13: 339120
A14: Security brokers and dealers; proprietors' equity in noncorporate business | B14: Currency | C14: 1000000 | D14: USD | E14: Z1/Z1/LM662090003.A | F14: LM662090003.A | G14: 0 | H14: 0 | I14: 0 | J14: 0 | K14: 0 | L14: 0 | M14: 0 | N14: 0 | O14: 0 | P14: 0 | Q14: 0 | R14: 0 | S14: 0 | T14: 0 | U14: 0 | V14: 0 | W14: 0 | X14: 0 | Y14: 0 | Z14: 0 | AA14: 0 | AB14: 0 | AC14: 0 | AD14: 0 | AE14: 0 | AF14: 0 | AG14: 0 | AH14: 0 | AI14: 950 | AJ14: 1706 | AK14: 2135 | AL14: 1943 | AM14: 1711 | AN14: 1973 | AO14: 2694 | AP14: 2172 | AQ14: 2191 | AR14: 2994 | AS14: 3642 | AT14: 3966 | AU14: 4718 | AV14: 6398 | AW14: 5877 | AX14: 6578 | AY14: 5788 | AZ14: 4524 | BA14: 5680 | BB14: 5889 | BC14: 6966 | BD14: 5868 | BE14: 7005 | BF14: 7837 | BG14: 10911 | BH14: 11257 | BI14: 13774 | BJ14: 14609 | BK14: 19232 | BL14: 18595 | BM14: 19076 | BN14: 18810 | BO14: 18965 | BP14: 16977 | BQ14: 22230 | BR14: 21785 | BS14: 23035 | BT14: 29197 | BU14: 27446 | BV14: 37886 | BW14: 40794 | BX14: 45121 | BY14: 50404 | BZ14: 67741 | CA14: 68693 | CB14: 78230 | CC14: 83475 | CD14: 90334 | CE14: 106104 | CF14: 109761 | CG14: 123829 | CH14: 140600
... A33: All sectors; U.S. wealth | B33: Currency | C33: 1000000 | D33: USD | E33: Z1/Z1/FL892090005.A | F33: FL892090005.A | G33: 733273 | H33: 817833 | I33: 934935 | J33: 991725 | K33: 1013747 | L33: 1120186 | M33: 1269077 | N33: 1317785 | O33: 1351999 | P33: 1497113 | Q33: 1679481 | R33: 1832498 | S33: 1866771 | T33: 2080972 | U33: 2210496 | V33: 2287245 | W33: 2521742 | X33: 2598968 | Y33: 2726472 | Z33: 2911977 | AA33: 3124583 | AB33: 3243599 | AC33: 3557415 | AD33: 3974923 | AE33: 4088663 | AF33: 4322288 | AG33: 4718697 | AH33: 5294069 | AI33: 5599547 | AJ33: 5835321 | AK33: 6602817 | AL33: 7288342 | AM33: 7903176 | AN33: 8888113 | AO33: 10272149 | AP33: 11792350 | AQ33: 12769304 | AR33: 13335352 | AS33: 14148311 | AT33: 15109572 | AU33: 16485542 | AV33: 17875263 | AW33: 19004781 | AX33: 20533955 | AY33: 22293729 | AZ33: 22775596 | BA33: 24130502 | BB33: 25093678 | BC33: 26414440 | BD33: 27452078 | BE33: 29810038 | BF33: 31995017 | BG33: 35684048 | BH33: 39569603 | BI33: 45125576 | BJ33: 45817440 | BK33: 46537331 | BL33: 45990464 | BM33: 51334751 | BN33: 57772107 | BO33: 63513873 | BP33: 68590785 | BQ33: 69637948 | BR33: 59655182 | BS33: 58484178 | BT33: 63014150 | BU33: 61929247 | BV33: 65945859 | BW33: 75557851 | BX33: 80021752 | BY33: 82238878 | BZ33: 87161969 | CA33: 95332022 | CB33: 94848037 | CC33: 103033483 | CD33: 113914917 | CE33: 136205372 | CF33: 135285879 | CG33: 144557112 | CH33: 156707266
A34: All sectors; U.S. wealth | B34: Currency | C34: 1000000 | D34: USD | E34: Z1/Z1/FC892090005.A | F34: FC892090005.A | H34: 84560 | I34: 117102 | J34: 56791 | K34: 22022 | L34: 106439 | M34: 148891 | N34: 48708 | O34: 34214 | P34: 145114 | Q34: 182368 | R34: 153017 | S34: 34273 | T34: 214201 | U34: 129524 | V34: 76749 | W34: 234497 | X34: 77226 | Y34: 127504 | Z34: 185505 | AA34: 212606 | AB34: 119016 | AC34: 313816 | AD34: 417508 | AE34: 113740 | AF34: 233625 | AG34: 396409 | AH34: 575372 | AI34: 305478 | AJ34: 235774 | AK34: 767496 | AL34: 685525 | AM34: 614834 | AN34: 984937 | AO34: 1384036 | AP34: 1520201 | AQ34: 976954 | AR34: 566048 | AS34: 812959 | AT34: 961261 | AU34: 1375970 | AV34: 1389721 | AW34: 1129518 | AX34: 1529174 | AY34: 1759774 | AZ34: 481867 | BA34: 1354906 | BB34: 963176 | BC34: 1320762 | BD34: 1037638 | BE34: 2357960 | BF34: 2184979 | BG34: 3689031 | BH34: 3885555 | BI34: 5555972 | BJ34: 691865 | BK34: 719891 | BL34: -546867 | BM34: 5344287 | BN34: 6437356 | BO34: 5741766 | BP34: 5076912 | BQ34: 1047163 | BR34: -9982766 | BS34: -1171004 | BT34: 4529971 | BU34: -1084902 | BV34: 4016611 | BW34: 9611992 | BX34: 4463901 | BY34: 2217126 | BZ34: 4923091 | CA34: 8170053 | CB34: -483985 | CC34: 8185446 | CD34: 10881434 | CE34: 22290455 | CF34: -919493 | CG34: 9271233 | CH34: 12150153
A35: All sectors; U.S. wealth | B35: Percent | C35: 1000000 | D35: USD | E35: Z1/Z1/PC892090005.A | F35: PC892090005.A | H35: 11.531812 | I35: 14.31851 | J35: 6.0743025 | K35: 2.2205495 | L35: 10.499587 | M35: 13.291607 | N35: 3.838065 | O35: 2.5963264 | P35: 10.733292 | Q35: 12.181312 | R35: 9.1109694 | S35: 1.8702885 | T35: 11.474412 | U35: 6.2242068 | V35: 3.4720262 | W35: 10.252378 | X35: 3.0624069 | Y35: 4.9059473 | Z35: 6.8038476 | AA35: 7.3010879 | AB35: 3.8090203 | AC35: 9.6749321 | AD35: 11.736275 | AE35: 2.8614391 | AF35: 5.7139706 | AG35: 9.1712769 | AH35: 12.193451 | AI35: 5.770193 | AJ35: 4.2105906 | AK35: 13.152593 | AL35: 10.382311 | AM35: 8.4358555 | AN35: 12.462547 | AO35: 15.571764 | AP35: 14.79925 | AQ35: 8.2846422 | AR35: 4.4328806 | AS35: 6.0962695 | AT35: 6.7941749 | AU35: 9.1066114 | AV35: 8.4299382 | AW35: 6.3188888 | AX35: 8.0462595 | AY35: 8.5700685 | AZ35: 2.1614464 | BA35: 5.9489376 | BB35: 3.9915291 | BC35: 5.2633257 | BD35: 3.9282983 | BE35: 8.589368 | BF35: 7.3296753 | BG35: 11.530017 | BH35: 10.888774 | BI35: 14.041011 | BJ35: 1.5331987 | BK35: 1.5712154 | BL35: -1.1751154 | BM35: 11.620425 | BN35: 12.539958 | BO35: 9.9386466 | BP35: 7.9933911 | BQ35: 1.5266819 | BR35: -14.335238 | BS35: -1.9629539 | BT35: 7.7456356 | BU35: -1.7216801 | BV35: 6.4858067 | BW35: 14.575581 | BX35: 5.9079247 | BY35: 2.7706545 | BZ35: 5.9863308 | CA35: 9.3734144 | CB35: -0.5076834 | CC35: 8.6300637 | CD35: 10.561066 | CE35: 19.567634 | CF35: -0.67507815 | CG35: 6.8530679 | CH35: 8.4050886
A36: Households and nonprofit organizations; net worth | B36: Currency | C36: 1000000 | D36: USD | E36: Z1/Z1/FL152090005.A | F36: FL152090005.A | G36: 806616 | H36: 885216 | I36: 984199 | J36: 1037019 | K36: 1079425 | L36: 1171443 | M36: 1280523 | N36: 1338242 | O36: 1386232 | P36: 1484120 | Q36: 1600734 | R36: 1710651 | S36: 1776003 | T36: 1921081 | U36: 2016085 | V36: 2091056 | W36: 2256719 | X36: 2319203 | Y36: 2422670 | Z36: 2604188 | AA36: 2803145 | AB36: 2902437 | AC36: 3204063 | AD36: 3595704 | AE36: 3660323 | AF36: 3875609 | AG36: 4294415 | AH36: 4889778 | AI36: 5101037 | AJ36: 5213063 | AK36: 5861925 | AL36: 6522666 | AM36: 7107581 | AN36: 7955603 | AO36: 9096396 | AP36: 10359452 | AQ36: 11258954 | AR36: 12084247 | AS36: 12980987 | AT36: 14097490 | AU36: 15549012 | AV36: 17180357 | AW36: 18436338 | AX36: 20181251 | AY36: 21976312 | AZ36: 22629587 | BA36: 24128374 | BB36: 25237606 | BC36: 26745508 | BD36: 27723515 | BE36: 30075730 | BF36: 32171612 | BG36: 35539480 | BH36: 39314914 | BI36: 43267374 | BJ36: 44488148 | BK36: 46021409 | BL36: 45935157 | BM36: 50913954 | BN36: 57782223 | BO36: 63340513 | BP36: 68263388 | BQ36: 69895699 | BR36: 61058258 | BS36: 61492801 | BT36: 65941998 | BU36: 67005103 | BV36: 72020139 | BW36: 80843597 | BX36: 86979596 | BY36: 89947002 | BZ36: 95192405 | CA36: 104026218 | CB36: 103933714 | CC36: 115663941 | CD36: 130673319 | CE36: 151701072 | CF36: 143858225 | CG36: 156064345 | CH36: 169427418
A37: Households and nonprofit organizations; net worth | B37: Currency | C37: 1000000 | D37: USD | E37: Z1/Z1/FC152090005.A | F37: FC152090005.A | H37: 78600 | I37: 98982 | J37: 52821 | K37: 42406 | L37: 92018 | M37: 109080 | N37: 57719 | O37: 47990 | P37: 97888 | Q37: 116614 | R37: 109918 | S37: 65352 | T37: 145078 | U37: 95004 | V37: 74971 | W37: 165663 | X37: 62484 | Y37: 103468 | Z37: 181518 | AA37: 198957 | AB37: 99293 | AC37: 301626 | AD37: 391641 | AE37: 64619 | AF37: 215286 | AG37: 418807 | AH37: 595363 | AI37: 211259 | AJ37: 112026 | AK37: 648862 | AL37: 660741 | AM37: 584915 | AN37: 848022 | AO37: 1140793 | AP37: 1263056 | AQ37: 899502 | AR37: 825293 | AS37: 896740 | AT37: 1116503 | AU37: 1451522 | AV37: 1631345 | AW37: 1255981 | AX37: 1744913 | AY37: 1795061 | AZ37: 653275 | BA37: 1498787 | BB37: 1109232 | BC37: 1507902 | BD37: 978007 | BE37: 2352214 | BF37: 2095882 | BG37: 3367868 | BH37: 3775435 | BI37: 3952460 | BJ37: 1220774 | BK37: 1533262 | BL37: -86252 | BM37: 4978796 | BN37: 6868269 | BO37: 5558289 | BP37: 4922876 | BQ37: 1632311 | BR37: -8837441 | BS37: 434543 | BT37: 4449198 | BU37: 1063105 | BV37: 5015036 | BW37: 8823458 | BX37: 6135999 | BY37: 2967406 | BZ37: 5245403 | CA37: 8833813 | CB37: -92505 | CC37: 11730228 | CD37: 15009378 | CE37: 21027753 | CF37: -7842847 | CG37: 12206120 | CH37: 13363073
A38: Households and nonprofit organizations; net worth | B38: Percent | C38: 1000000 | D38: USD | E38: Z1/Z1/PC152090005.A | F38: PC152090005.A | H38: 9.7444089 | I38: 11.181695 | J38: 5.3668792 | K38: 4.0892246 | L38: 8.5246882 | M38: 9.3116221 | N38: 4.5074459 | O38: 3.5860098 | P38: 7.0614741 | Q38: 7.8574229 | R38: 6.8667008 | S38: 3.8202757 | T38: 8.1687981 | U38: 4.94533 | V38: 3.7186529 | W38: 7.9224417 | X38: 2.7687987 | Y38: 4.461339 | Z38: 7.4924764 | AA38: 7.6398661 | AB38: 3.5421859 | AC38: 10.392159 | AD38: 12.223251 | AE38: 1.7971196 | AF38: 5.881601 | AG38: 10.806215 | AH38: 13.863645 | AI38: 4.3204172 | AJ38: 2.1961438 | AK38: 12.446854 | AL38: 11.271741 | AM38: 8.9674268 | AN38: 11.931226 | AO38: 14.339494 | AP38: 13.885239 | AQ38: 8.6829068 | AR38: 7.3301001 | AS38: 7.4207382 | AT38: 8.6010648 | AU38: 10.296315 | AV38: 10.491631 | AW38: 7.3105641 | AX38: 9.4645304 | AY38: 8.8946985 | AZ38: 2.972633 | BA38: 6.6231292 | BB38: 4.5972103 | BC38: 5.9748226 | BD38: 3.6567153 | BE38: 8.4845452 | BF38: 6.9686828 | BG38: 10.468446 | BH38: 10.623213 | BI38: 10.053334 | BJ38: 2.8214649 | BK38: 3.4464496 | BL38: -0.18741658 | BM38: 10.838749 | BN38: 13.489955 | BO38: 9.6193761 | BP38: 7.7720809 | BQ38: 2.391195 | BR38: -12.643756 | BS38: 0.7116858 | BT38: 7.2353148 | BU38: 1.6121815 | BV38: 7.4845584 | BW38: 12.251376 | BX38: 7.5899627 | BY38: 3.4116112 | BZ38: 5.8316601 | CA38: 9.2799558 | CB38: -0.088924262 | CC38: 11.286259 | CD38: 12.976713 | CE38: 16.091848 | CF38: -5.1699351 | CG38: 8.4848262 | CH38: 8.5625405

Sheet L4
A1: Download Page | F1: Z.1 Statistical Release for Jan 09, 2026
A2: Descriptions: | B2: Unit: | C2: Multiplier: | D2: Currency: | E2: Unique Identifier: | F2: Series Name: | G2: 1945 | H2: 1946 | I2: 1947 | J2: 1948 | K2: 1949 | L2: 1950 | M2: 1951 | N2: 1952 | O2: 1953 | P2: 1954 | Q2: 1955 | R2: 1956 | S2: 1957 | T2: 1958 | U2: 1959 | V2: 1960 | W2: 1961 | X2: 1962 | Y2: 1963 | Z2: 1964 | AA2: 1965 | AB2: 1966 | AC2: 1967 | AD2: 1968 | AE2: 1969 | AF2: 1970 | AG2: 1971 | AH2: 1972 | AI2: 1973 | AJ2: 1974 | AK2: 1975 | AL2: 1976 | AM2: 1977 | AN2: 1978 | AO2: 1979 | AP2: 1980 | AQ2: 1981 | AR2: 1982 | AS2: 1983 | AT2: 1984 | AU2: 1985 | AV2: 1986 | AW2: 1987 | AX2: 1988 | AY2: 1989 | AZ2: 1990 | BA2: 1991 | BB2: 1992 | BC2: 1993 | BD2: 1994 | BE2: 1995 | BF2: 1996 | BG2: 1997 | BH2: 1998 | BI2: 1999 | BJ2: 2000 | BK2: 2001 | BL2: 2002 | BM2: 2003 | BN2: 2004 | BO2: 2005 | BP2: 2006 | BQ2: 2007 | BR2: 2008 | BS2: 2009 | BT2: 2010 | BU2: 2011 | BV2: 2012 | BW2: 2013 | BX2: 2014 | BY2: 2015 | BZ2: 2016 | CA2: 2017 | CB2: 2018 | CC2: 2019 | CD2: 2020 | CE2: 2021 | CF2: 2022 | CG2: 2023 | CH2: 2024
A3: All domestic sectors; gross fixed investment, current cost basis | B3: Currency | C3: 1000000 | D3: USD | E3: Z1/Z1/FL885019865.A | F3: FL885019865.A | G3: 554840 | H3: 639557 | I3: 734155 | J3: 779995 | K3: 785039 | L3: 871996 | M3: 957305 | N3: 1012970 | O3: 1051269 | P3: 1099956 | Q3: 1197093 | R3: 1301496 | S3: 1369440 | T3: 1415027 | U3: 1471124 | V3: 1520449 | W3: 1580092 | X3: 1652675 | Y3: 1717352 | Z3: 1829486 | AA3: 1954131 | AB3: 2119630 | AC3: 2285122 | AD3: 2511156 | AE3: 2743748 | AF3: 2990474 | AG3: 3294294 | AH3: 3621510 | AI3: 4110445 | AJ3: 4887525 | AK3: 5276582 | AL3: 5747011 | AM3: 6415098 | AN3: 7259791 | AO3: 8359565 | AP3: 9511476 | AQ3: 10489750 | AR3: 11083259 | AS3: 11467860 | AT3: 12138928 | AU3: 12757908 | AV3: 13547111 | AW3: 14341072 | AX3: 15226770 | AY3: 16092388 | AZ3: 16854534 | BA3: 17271370 | BB3: 17998077 | BC3: 18899579 | BD3: 20025720 | BE3: 20998211 | BF3: 21999462 | BG3: 23167721 | BH3: 24470593 | BI3: 26040669 | BJ3: 27757018 | BK3: 29308485 | BL3: 30735473 | BM3: 32394949 | BN3: 35710996 | BO3: 39290344 | BP3: 42505719 | BQ3: 44406957 | BR3: 45918921 | BS3: 45079011 | BT3: 45978958 | BU3: 47571642 | BV3: 49070496 | BW3: 51481571 | BX3: 53583348 | BY3: 54904898 | BZ3: 57232242 | CA3: 59662646 | CB3: 62780152 | CC3: 65316427 | CD3: 68156365 | CE3: 77384510 | CF3: 86358882 | CG3: 88606168 | CH3: 91548536
A4: All domestic sectors; gross fixed investment, structures, current cost basis | B4: Currency | C4: 1000000 | D4: USD | E4: Z1/Z1/FL885019665.A | F4: FL885019665.A | G4: 419286 | H4: 500717 | I4: 591591 | J4: 630942 | K4: 638466 | L4: 712794 | M4: 781948 | N4: 823187 | O4: 842237 | P4: 877884 | Q4: 952845 | R4: 1030647 | S4: 1076324 | T4: 1110097 | U4: 1147648 | V4: 1182474 | W4: 1228684 | X4: 1280576 | Y4: 1326105 | Z4: 1414608 | AA4: 1510035 | AB4: 1632462 | AC4: 1752389 | AD4: 1928902 | AE4: 2106358 | AF4: 2295588 | AG4: 2558114 | AH4: 2833280 | AI4: 3238581 | AJ4: 3853875 | AK4: 4115062 | AL4: 4469960 | AM4: 4994166 | AN4: 5653512 | AO4: 6527060 | AP4: 7410543 | AQ4: 8141430 | AR4: 8560882 | AS4: 8810123 | AT4: 9274517 | AU4: 9739326 | AV4: 10352404 | AW4: 10963233 | AX4: 11614122 | AY4: 12248721 | AZ4: 12774773 | BA4: 13037333 | BB4: 13610492 | BC4: 14332017 | BD4: 15215953 | BE4: 15931972 | BF4: 16726793 | BG4: 17674932 | BH4: 18714826 | BI4: 19922932 | BJ4: 21266407 | BK4: 22640384 | BL4: 23935312 | BM4: 25419933 | BN4: 28377666 | BO4: 31586635 | BP4: 34322145 | BQ4: 35785649 | BR4: 36854807 | BS4: 35982272 | BT4: 36597055 | BU4: 37775222 | BV4: 38895067 | BW4: 40905869 | BX4: 42600653 | BY4: 43636925 | BZ4: 45572307 | CA4: 47468929 | CB4: 49966039 | CC4: 51988666 | CD4: 54235283 | CE4: 62396934 | CF4: 70186705 | CG4: 71592596 | CH4: 73687068
A5: All domestic sectors; gross fixed investment, equipment, current cost basis | B5: Currency | C5: 1000000 | D5: USD | E5: Z1/Z1/FL885019265.A | F5: FL885019265.A | G5: 123201 | H5: 124673 | I5: 126427 | J5: 131562 | K5: 128154 | L5: 138649 | M5: 152960 | N5: 165512 | O5: 182254 | P5: 192749 | Q5: 211346 | R5: 232880 | S5: 249722 | T5: 256476 | U5: 269549 | V5: 278747 | W5: 286183 | X5: 300896 | Y5: 311742 | Z5: 326652 | AA5: 346059 | AB5: 377580 | AC5: 409830 | AD5: 444342 | AE5: 482034 | AF5: 522686 | AG5: 551018 | AH5: 588714 | AI5: 649650 | AJ5: 782835 | AK5: 890403 | AL5: 983282 | AM5: 1101024 | AN5: 1252534 | AO5: 1432317 | AP5: 1646139 | AQ5: 1833217 | AR5: 1954497 | AS5: 2036340 | AT5: 2184837 | AU5: 2281134 | AV5: 2402655 | AW5: 2512802 | AX5: 2672774 | AY5: 2829172 | AZ5: 2989287 | BA5: 3072810 | BB5: 3161902 | BC5: 3284486 | BD5: 3453797 | BE5: 3636012 | BF5: 3774128 | BG5: 3900520 | BH5: 4060519 | BI5: 4276780 | BJ5: 4499225 | BK5: 4604355 | BL5: 4667015 | BM5: 4727182 | BN5: 4980135 | BO5: 5204911 | BP5: 5547022 | BQ5: 5806818 | BR5: 6108187 | BS5: 6055930 | BT5: 6197481 | BU5: 6467262 | BV5: 6718880 | BW5: 6938128 | BX5: 7202300 | BY5: 7389895 | BZ5: 7576968 | CA5: 7842334 | CB5: 8202312 | CC5: 8462825 | CD5: 8637503 | CE5: 9309444 | CF5: 9974341 | CG5: 10371215 | CH5: 10729364
A6: All domestic sectors; nonresidential intellectual property products, current cost basis | B6: Currency | C6: 1000000 | D6: USD | E6: Z1/Z1/FL885013765.A | F6: FL885013765.A | G6: 12353 | H6: 14167 | I6: 16137 | J6: 17491 | K6: 18419 | L6: 20553 | M6: 22397 | N6: 24271 | O6: 26778 | P6: 29323 | Q6: 32902 | R6: 37969 | S6: 43394 | T6: 48454 | U6: 53927 | V6: 59228 | W6: 65225 | X6: 71203 | Y6: 79505 | Z6: 88226 | AA6: 98037 | AB6: 109588 | AC6: 122903 | AD6: 137912 | AE6: 155356 | AF6: 172200 | AG6: 185162 | AH6: 199516 | AI6: 222214 | AJ6: 250815 | AK6: 271117 | AL6: 293769 | AM6: 319908 | AN6: 353745 | AO6: 400188 | AP6: 454794 | AQ6: 515103 | AR6: 567880 | AS6: 621397 | AT6: 679574 | AU6: 737448 | AV6: 792052 | AW6: 865037 | AX6: 939874 | AY6: 1014495 | AZ6: 1090474 | BA6: 1161227 | BB6: 1225683 | BC6: 1283076 | BD6: 1355970 | BE6: 1430227 | BF6: 1498541 | BG6: 1592269 | BH6: 1695248 | BI6: 1840957 | BJ6: 1991386 | BK6: 2063746 | BL6: 2133146 | BM6: 2247834 | BN6: 2353195 | BO6: 2498798 | BP6: 2636552 | BQ6: 2814490 | BR6: 2955927 | BS6: 3040809 | BT6: 3184422 | BU6: 3329158 | BV6: 3456549 | BW6: 3637574 | BX6: 3780395 | BY6: 3878078 | BZ6: 4082967 | CA6: 4351383 | CB6: 4611801 | CC6: 4864936 | CD6: 5283579 | CE6: 5678132 | CF6: 6197836 | CG6: 6642357 | CH6: 7132104
A7: All domestic sectors; nonresidential software, current cost basis | B7: Currency | C7: 1000000 | D7: USD | E7: Z1/Z1/FL885013365.A | F7: FL885013365.A | G7: 0 | H7: 0 | I7: 0 | J7: 0 | K7: 0 | L7: 0 | M7: 0 | N7: 0 | O7: 0 | P7: 0 | Q7: 0 | R7: 0 | S7: 0 | T7: 0 | U7: 13 | V7: 143 | W7: 276 | X7: 413 | Y7: 730 | Z7: 1057 | AA7: 1387 | AB7: 1973 | AC7: 2570 | AD7: 3176 | AE7: 4152 | AF7: 5362 | AG7: 6209 | AH7: 7288 | AI7: 8704 | AJ7: 10902 | AK7: 12923 | AL7: 14800 | AM7: 16206 | AN7: 18448 | AO7: 22522 | AP7: 27304 | AQ7: 33168 | AR7: 38683 | AS7: 44262 | AT7: 52415 | AU7: 60560 | AV7: 68323 | AW7: 77871 | AX7: 88016 | AY7: 100832 | AZ7: 116864 | BA7: 125564 | BB7: 134848 | BC7: 147349 | BD7: 156556 | BE7: 167936 | BF7: 178273 | BG7: 200364 | BH7: 230700 | BI7: 276063 | BJ7: 323314 | BK7: 344516 | BL7: 347925 | BM7: 348727 | BN7: 364112 | BO7: 387190 | BP7: 413355 | BQ7: 443973 | BR7: 481308 | BS7: 493420 | BT7: 510703 | BU7: 546240 | BV7: 582208 | BW7: 621812 | BX7: 660054 | BY7: 694015 | BZ7: 741107 | CA7: 801189 | CB7: 869362 | CC7: 926420 | CD7: 984547 | CE7: 1067325 | CF7: 1197965 | CG7: 1298439 | CH7: 1433440
A8: All domestic sectors; nonresidential research and development, current cost basis | B8: Currency | C8: 1000000 | D8: USD | E8: Z1/Z1/FL885013465.A | F8: FL885013465.A | G8: 7056 | H8: 8274 | I8: 9381 | J8: 10389 | K8: 11080 | L8: 12686 | M8: 14289 | N8: 15854 | O8: 17805 | P8: 19864 | Q8: 22754 | R8: 27073 | S8: 31597 | T8: 36087 | U8: 40444 | V8: 44975 | W8: 49808 | X8: 54970 | Y8: 61797 | Z8: 69064 | AA8: 76848 | AB8: 86091 | AC8: 96393 | AD8: 108592 | AE8: 122543 | AF8: 136142 | AG8: 147435 | AH8: 159403 | AI8: 179540 | AJ8: 203107 | AK8: 219124 | AL8: 236710 | AM8: 257438 | AN8: 284296 | AO8: 321328 | AP8: 366160 | AQ8: 414134 | AR8: 455024 | AS8: 495864 | AT8: 536363 | AU8: 577850 | AV8: 615324 | AW8: 668065 | AX8: 723747 | AY8: 772926 | AZ8: 820163 | BA8: 871585 | BB8: 918347 | BC8: 953141 | BD8: 1004564 | BE8: 1051183 | BF8: 1093464 | BG8: 1150860 | BH8: 1212522 | BI8: 1291727 | BJ8: 1375426 | BK8: 1416155 | BL8: 1466436 | BM8: 1563265 | BN8: 1638260 | BO8: 1741960 | BP8: 1829618 | BQ8: 1965451 | BR8: 2059773 | BS8: 2131212 | BT8: 2248550 | BU8: 2352420 | BV8: 2431766 | BW8: 2566447 | BX8: 2659473 | BY8: 2704569 | BZ8: 2846151 | CA8: 3034315 | CB8: 3210017 | CC8: 3385581 | CD8: 3733117 | CE8: 4012474 | CF8: 4354341 | CG8: 4654251 | CH8: 4986446
A9: Private domestic sectors; nonresidential entertainment, literary, and artistic originals, current cost basis | B9: Currency | C9: 1000000 | D9: USD | E9: Z1/Z1/FL835013565.A | F9: FL835013565.A | G9: 5297 | H9: 5893 | I9: 6756 | J9: 7102 | K9: 7339 | L9: 7867 | M9: 8108 | N9: 8417 | O9: 8973 | P9: 9459 | Q9: 10148 | R9: 10896 | S9: 11797 | T9: 12367 | U9: 13470 | V9: 14110 | W9: 15141 | X9: 15820 | Y9: 16978 | Z9: 18105 | AA9: 19802 | AB9: 21524 | AC9: 23940 | AD9: 26144 | AE9: 28661 | AF9: 30696 | AG9: 31518 | AH9: 32825 | AI9: 33970 | AJ9: 36806 | AK9: 39070 | AL9: 42259 | AM9: 46264 | AN9: 51001 | AO9: 56338 | AP9: 61330 | AQ9: 67801 | AR9: 74173 | AS9: 81271 | AT9: 90796 | AU9: 99038 | AV9: 108405 | AW9: 119101 | AX9: 128111 | AY9: 140737 | AZ9: 153447 | BA9: 164078 | BB9: 172488 | BC9: 182586 | BD9: 194850 | BE9: 211108 | BF9: 226804 | BG9: 241045 | BH9: 252026 | BI9: 273167 | BJ9: 292646 | BK9: 303075 | BL9: 318785 | BM9: 335842 | BN9: 350823 | BO9: 369648 | BP9: 393579 | BQ9: 405066 | BR9: 414846 | BS9: 416177 | BT9: 425169 | BU9: 430498 | BV9: 442575 | BW9: 449315 | BX9: 460868 | BY9: 479494 | BZ9: 495709 | CA9: 515879 | CB9: 532422 | CC9: 552935 | CD9: 565915 | CE9: 598333 | CF9: 645530 | CG9: 689667 | CH9: 712218
A10: All domestic sectors; gross fixed investment, current cost basis | B10: Currency | C10: 1000000 | D10: USD | E10: Z1/Z1/FL885019865.A | F10: FL885019865.A | G10: 554840 | H10: 639557 | I10: 734155 | J10: 779995 | K10: 785039 | L10: 871996 | M10: 957305 | N10: 1012970 | O10: 1051269 | P10: 1099956 | Q10: 1197093 | R10: 1301496 | S10: 1369440 | T10: 1415027 | U10: 1471124 | V10: 1520449 | W10: 1580092 | X10: 1652675 | Y10: 1717352 | Z10: 1829486 | AA10: 1954131 | AB10: 2119630 | AC10: 2285122 | AD10: 2511156 | AE10: 2743748 | AF10: 2990474 | AG10: 3294294 | AH10: 3621510 | AI10: 4110445 | AJ10: 4887525 | AK10: 5276582 | AL10: 5747011 | AM10: 6415098 | AN10: 7259791 | AO10: 8359565 | AP10: 9511476 | AQ10: 10489750 | AR10: 11083259 | AS10: 11467860 | AT10: 12138928 | AU10: 12757908 | AV10: 13547111 | AW10: 14341072 | AX10: 15226770 | AY10: 16092388 | AZ10: 16854534 | BA10: 17271370 | BB10: 17998077 | BC10: 18899579 | BD10: 20025720 | BE10: 20998211 | BF10: 21999462 | BG10: 23167721 | BH10: 24470593 | BI10: 26040669 | BJ10: 27757018 | BK10: 29308485 | BL10: 30735473 | BM10: 32394949 | BN10: 35710996 | BO10: 39290344 | BP10: 42505719 | BQ10: 44406957 | BR10: 45918921 | BS10: 45079011 | BT10: 45978958 | BU10: 47571642 | BV10: 49070496 | BW10: 51481571 | BX10: 53583348 | BY10: 54904898 | BZ10: 57232242 | CA10: 59662646 | CB10: 62780152 | CC10: 65316427 | CD10: 68156365 | CE10: 77384510 | CF10: 86358882 | CG10: 88606168 | CH10: 91548536
A11: Households and nonprofit organizations; structures, equipment, and intellectual property products, current cost basis (Fixed assets basis) | B11: Currency | C11: 1000000 | D11: USD | E11: Z1/Z1/FL155015015.A | F11: FL155015015.A | G11: 118330 | H11: 149143 | I11: 179022 | J11: 195613 | K11: 207311 | L11: 237976 | M11: 262749 | N11: 279736 | O11: 293214 | P11: 312398 | Q11: 342242 | R11: 364380 | S11: 380726 | T11: 394216 | U11: 414618 | V11: 425533 | W11: 436417 | X11: 447857 | Y11: 463789 | Z11: 502626 | AA11: 536864 | AB11: 578944 | AC11: 620318 | AD11: 687440 | AE11: 738110 | AF11: 784272 | AG11: 879578 | AH11: 980457 | AI11: 1121114 | AJ11: 1274197 | AK11: 1376257 | AL11: 1533065 | AM11: 1787475 | AN11: 2071087 | AO11: 2408177 | AP11: 2712998 | AQ11: 2916614 | AR11: 3041916 | AS11: 3175101 | AT11: 3368015 | AU11: 3551264 | AV11: 3835364 | AW11: 4105574 | AX11: 4385882 | AY11: 4659584 | AZ11: 4859234 | BA11: 4978175 | BB11: 5265672 | BC11: 5612765 | BD11: 6038841 | BE11: 6316183 | BF11: 6667186 | BG11: 7046438 | BH11: 7529437 | BI11: 8124482 | BJ11: 8727350 | BK11: 9394813 | BL11: 10054459 | BM11: 10929524 | BN11: 12254392 | BO11: 13700007 | BP11: 14711656 | BQ11: 14973839 | BR11: 14796707 | BS11: 14472824 | BT11: 14542517 | BU11: 14737265 | BV11: 15194474 | BW11: 16315278 | BX11: 17075410 | BY11: 17640634 | BZ11: 18813149 | CA11: 19694807 | CB11: 20864375 | CC11: 21722190 | CD11: 23279585 | CE11: 27265038 | CF11: 30637552 | CG11: 31207265 | CH11: 32262867
A12: Nonfinancial corporate business; structures, equipment, and intellectual property products, current cost basis (includes used car premium and REITs residential structures) | B12: Currency | C12: 1000000 | D12: USD | E12: Z1/Z1/FL105015085.A | F12: FL105015085.A | G12: 134003 | H12: 161715 | I12: 192728 | J12: 211039 | K12: 215670 | L12: 241922 | M12: 262117 | N12: 277786 | O12: 292501 | P12: 301966 | Q12: 332305 | R12: 368852 | S12: 396425 | T12: 404909 | U12: 422056 | V12: 431681 | W12: 443253 | X12: 457910 | Y12: 473397 | Z12: 499569 | AA12: 534604 | AB12: 582404 | AC12: 632740 | AD12: 696067 | AE12: 767095 | AF12: 843414 | AG12: 921543 | AH12: 998402 | AI12: 1124922 | AJ12: 1372197 | AK12: 1518806 | AL12: 1666379 | AM12: 1850996 | AN12: 2097947 | AO12: 2414174 | AP12: 2766412 | AQ12: 3125662 | AR12: 3320753 | AS12: 3415779 | AT12: 3613436 | AU12: 3801706 | AV12: 3959550 | AW12: 4154782 | AX12: 4404530 | AY12: 4650305 | AZ12: 4905710 | BA12: 5028761 | BB12: 5205412 | BC12: 5454731 | BD12: 5759417 | BE12: 6106994 | BF12: 6431220 | BG12: 6811806 | BH12: 7180238 | BI12: 7599121 | BJ12: 8137294 | BK12: 8540555 | BL12: 8810698 | BM12: 9081233 | BN12: 9838424 | BO12: 10724500 | BP12: 11601576 | BQ12: 12248969 | BR12: 13060202 | BS12: 12692474 | BT12: 13078840 | BU12: 13738373 | BV12: 14229170 | BW12: 14783467 | BX12: 15515241 | BY12: 15792585 | BZ12: 16251521 | CA12: 16888542 | CB12: 17670680 | CC12: 18471301 | CD12: 18843166 | CE12: 20906670 | CF12: 23313721 | CG12: 24166378 | CH12: 24954909
A13: Nonfinancial noncorporate business; structures, equipment, and intellectual property products, current cost basis (NIPA basis) | B13: Currency | C13: 1000000 | D13: USD | E13: Z1/Z1/FL115015005.A | F13: FL115015005.A | G13: 95477 | H13: 116492 | I13: 136916 | J13: 146901 | K13: 150119 | L13: 166958 | M13: 178696 | N13: 183665 | O13: 186609 | P13: 189979 | Q13: 202176 | R13: 211433 | S13: 217070 | T13: 219780 | U13: 225631 | V13: 237390 | W13: 250699 | X13: 266191 | Y13: 272087 | Z13: 290340 | AA13: 307941 | AB13: 334844 | AC13: 354993 | AD13: 388516 | AE13: 420437 | AF13: 451479 | AG13: 503891 | AH13: 561565 | AI13: 639062 | AJ13: 744967 | AK13: 804139 | AL13: 871928 | AM13: 986513 | AN13: 1114531 | AO13: 1286193 | AP13: 1451349 | AQ13: 1598716 | AR13: 1685858 | AS13: 1734619 | AT13: 1822175 | AU13: 1917813 | AV13: 2042003 | AW13: 2146171 | AX13: 2260141 | AY13: 2356227 | AZ13: 2426893 | BA13: 2448646 | BB13: 2509920 | BC13: 2591047 | BD13: 2697101 | BE13: 2787377 | BF13: 2892140 | BG13: 3024830 | BH13: 3182096 | BI13: 3348826 | BJ13: 3534338 | BK13: 3712386 | BL13: 3881640 | BM13: 4069397 | BN13: 4435967 | BO13: 4858157 | BP13: 5199448 | BQ13: 5379404 | BR13: 5503855 | BS13: 5368975 | BT13: 5394471 | BU13: 5477039 | BV13: 5612151 | BW13: 5876039 | BX13: 6141055 | BY13: 6377636 | BZ13: 6627647 | CA13: 6915355 | CB13: 7241062 | CC13: 7495197 | CD13: 7794043 | CE13: 8834932 | CF13: 9847438 | CG13: 10083027 | CH13: 10410153
A14: Federal government; nonfinancial assets (does not include land) | B14: Currency | C14: 1000000 | D14: USD | E14: Z1/Z1/FL315015005.A | F14: FL315015005.A | G14: 135721 | H14: 132686 | I14: 124219 | J14: 116197 | K14: 106730 | L14: 106631 | M14: 120256 | N14: 130505 | O14: 138681 | P14: 149640 | Q14: 158331 | R14: 173094 | S14: 182371 | T14: 191377 | U14: 198000 | V14: 205213 | W14: 215738 | X14: 230254 | Y14: 240733 | Z14: 250987 | AA14: 262979 | AB14: 278893 | AC14: 299817 | AD14: 319583 | AE14: 343047 | AF14: 370168 | AG14: 391164 | AH14: 424729 | AI14: 470809 | AJ14: 539642 | AK14: 572069 | AL14: 619507 | AM14: 655972 | AN14: 721488 | AO14: 799572 | AP14: 888284 | AQ14: 959787 | AR14: 1024194 | AS14: 1084225 | AT14: 1181793 | AU14: 1210016 | AV14: 1259625 | AW14: 1317674 | AX14: 1405285 | AY14: 1477370 | AZ14: 1540287 | BA14: 1592104 | BB14: 1651570 | BC14: 1704204 | BD14: 1769893 | BE14: 1810541 | BF14: 1833376 | BG14: 1863751 | BH14: 1902223 | BI14: 1966997 | BJ14: 2003531 | BK14: 2026168 | BL14: 2077426 | BM14: 2149632 | BN14: 2288989 | BO14: 2432816 | BP14: 2579409 | BQ14: 2709774 | BR14: 2828666 | BS14: 2838363 | BT14: 2955727 | BU14: 3061248 | BV14: 3126659 | BW14: 3209295 | BX14: 3253273 | BY14: 3255708 | BZ14: 3325197 | CA14: 3422677 | CB14: 3547247 | CC14: 3626715 | CD14: 3766500 | CE14: 4107083 | CF14: 4442124 | CG14: 4570236 | CH14: 4710067
... A33: Nonfinancial business; inventories | B33: Currency | C33: 1000000 | D33: USD | E33: Z1/Z1/FL145020005.A | F33: FL145020005.A | G33: 60394 | H33: 72600 | I33: 81200 | J33: 88050 | K33: 82750 | L33: 87650 | M33: 108025 | N33: 105100 | O33: 103500 | P33: 101800 | Q33: 104300 | R33: 112200 | S33: 116200 | T33: 119700 | U33: 121400 | V33: 124900 | W33: 128200 | X33: 135400 | Y33: 137700 | Z33: 143000 | AA33: 157200 | AB33: 173700 | AC33: 184100 | AD33: 197400 | AE33: 215800 | AF33: 222900 | AG33: 240700 | AH33: 266800 | AI33: 322800 | AJ33: 382300 | AK33: 387300 | AL33: 419300 | AM33: 462700 | AN33: 546800 | AO33: 644700 | AP33: 710800 | AQ33: 754900 | AR33: 752100 | AS33: 769600 | AT33: 845600 | AU33: 856500 | AV33: 839400 | AW33: 901000 | AX33: 968800 | AY33: 1016300 | AZ33: 1054600 | BA33: 1028000 | BB33: 1051900 | BC33: 1082800 | BD33: 1162900 | BE33: 1222400 | BF33: 1284650 | BG33: 1329795 | BH33: 1342316 | BI33: 1433438 | BJ33: 1524806 | BK33: 1447653 | BL33: 1495772 | BM33: 1560315 | BN33: 1700028 | BO33: 1836852 | BP33: 1942323 | BQ33: 2102808 | BR33: 2044108 | BS33: 1919715 | BT33: 2104760 | BU33: 2274572 | BV33: 2370153 | BW33: 2482735 | BX33: 2551676 | BY33: 2532214 | BZ33: 2609034 | CA33: 2711026 | CB33: 2840634 | CC33: 2907955 | CD33: 2915314 | CE33: 3462033 | CF33: 3828554 | CG33: 3813695 | CH33: 3913313

Sheet CapitalDataL4+
A1: Nonfinfancial Corporate | B1: Descriptions: | C1: Unit: | D1: Multiplier: | E1: Currency: | F1: Unique Identifier: | G1: Series Name: | H1: 1945 | I1: 1946 | J1: 1947 | K1: 1948 | L1: 1949 | M1: 1950 | N1: 1951 | O1: 1952 | P1: 1953 | Q1: 1954 | R1: 1955 | S1: 1956 | T1: 1957 | U1: 1958 | V1: 1959 | W1: 1960 | X1: 1961 | Y1: 1962 | Z1: 1963 | AA1: 1964 | AB1: 1965 | AC1: 1966 | AD1: 1967 | AE1: 1968 | AF1: 1969 | AG1: 1970 | AH1: 1971 | AI1: 1972 | AJ1: 1973 | AK1: 1974 | AL1: 1975 | AM1: 1976 | AN1: 1977 | AO1: 1978 | AP1: 1979 | AQ1: 1980 | AR1: 1981 | AS1: 1982 | AT1: 1983 | AU1: 1984 | AV1: 1985 | AW1: 1986 | AX1: 1987 | AY1: 1988 | AZ1: 1989 | BA1: 1990 | BB1: 1991 | BC1: 1992 | BD1: 1993 | BE1: 1994 | BF1: 1995 | BG1: 1996 | BH1: 1997 | BI1: 1998 | BJ1: 1999 | BK1: 2000 | BL1: 2001 | BM1: 2002 | BN1: 2003 | BO1: 2004 | BP1: 2005 | BQ1: 2006 | BR1: 2007 | BS1: 2008 | BT1: 2009 | BU1: 2010 | BV1: 2011 | BW1: 2012 | BX1: 2013 | BY1: 2014 | BZ1: 2015 | CA1: 2016 | CB1: 2017 | CC1: 2018 | CD1: 2019 | CE1: 2020 | CF1: 2021 | CG1: 2022 | CH1: 2023 | CI1: 2024
A2: Capital | B2: Nonfinancial corporate business; structures, equipment, and intellectual property products, current cost basis (includes used car premium and REITs residential structures) | C2: Currency | D2: 1000000 | E2: USD | F2: Z1/Z1/FL105015085.A | G2: FL105015085.A | H2: 134003 | I2: 161715 | J2: 192728 | K2: 211039 | L2: 215670 | M2: 241922 | N2: 262117 | O2: 277786 | P2: 292501 | Q2: 301966 | R2: 332305 | S2: 368852 | T2: 396425 | U2: 404909 | V2: 422056 | W2: 431681 | X2: 443253 | Y2: 457910 | Z2: 473397 | AA2: 499569 | AB2: 534604 | AC2: 582404 | AD2: 632740 | AE2: 696067 | AF2: 767095 | AG2: 843414 | AH2: 921543 | AI2: 998402 | AJ2: 1124922 | AK2: 1372197 | AL2: 1518806 | AM2: 1666379 | AN2: 1850996 | AO2: 2097947 | AP2: 2414174 | AQ2: 2766412 | AR2: 3125662 | AS2: 3320753 | AT2: 3415779 | AU2: 3613436 | AV2: 3801706 | AW2: 3959550 | AX2: 4154782 | AY2: 4404530 | AZ2: 4650305 | BA2: 4905710 | BB2: 5028761 | BC2: 5205412 | BD2: 5454731 | BE2: 5759417 | BF2: 6106994 | BG2: 6431220 | BH2: 6811806 | BI2: 7180238 | BJ2: 7599121 | BK2: 8137294 | BL2: 8540555 | BM2: 8810698 | BN2: 9081233 | BO2: 9838424 | BP2: 10724500 | BQ2: 11601576 | BR2: 12248969 | BS2: 13060202 | BT2: 12692474 | BU2: 13078840 | BV2: 13738373 | BW2: 14229170 | BX2: 14783467 | BY2: 15515241 | BZ2: 15792585 | CA2: 16251521 | CB2: 16888542 | CC2: 17670680 | CD2: 18471301 | CE2: 18843166 | CF2: 20906670 | CG2: 23313721 | CH2: 24166378 | CI2: 24954909
A3: Investment | B3: Nonfinancial corporate business; gross fixed capital formation with equity REIT residential structures (IMA) | C3: Currency | D3: 1000000 | E3: USD | F3: Z1/Z1/FU105019085.A | G3: FU105019085.A | I3: 13361 | J3: 17296 | K3: 19102 | L3: 17269 | M3: 18961 | N3: 22779 | O3: 24384 | P3: 26910 | Q3: 26662 | R3: 29403 | S3: 35688 | T3: 38576 | U3: 33721 | V3: 37278 | W3: 40431 | X3: 40444 | Y3: 43578 | Z3: 46438 | AA3: 51851 | AB3: 61704 | AC3: 71952 | AD3: 73874 | AE3: 80346 | AF3: 89281 | AG3: 92336 | AH3: 95421 | AI3: 107865 | AJ3: 125804 | AK3: 141538 | AL3: 144183 | AM3: 161805 | AN3: 193035 | AO3: 233472 | AP3: 274491 | AQ3: 299969 | AR3: 343054 | AS3: 349908 | AT3: 348271 | AU3: 405891 | AV3: 431584 | AW3: 426903 | AX3: 422235 | AY3: 450558 | AZ3: 489804 | BA3: 524972 | BB3: 522908 | BC3: 543625 | BD3: 582993 | BE3: 636979 | BF3: 719057 | BG3: 779768 | BH3: 858482 | BI3: 915633 | BJ3: 994652 | BK3: 1101403 | BL3: 1065402 | BM3: 956646 | BN3: 976342 | BO3: 1029817 | BP3: 1156258 | BQ3: 1287718 | BR3: 1384599 | BS3: 1422603 | BT3: 1201475 | BU3: 1251054 | BV3: 1390984 | BW3: 1543068 | BX3: 1590872 | BY3: 1767580 | BZ3: 1801861 | CA3: 1826792 | CB3: 1919803 | CC3: 2080197 | CD3: 2127035 | CE3: 2051296 | CF3: 2236870 | CG3: 2548806 | CH3: 2810202 | CI3: 2914282
A4: Depreciation | B4: Nonfinancial corporate business; consumption of fixed capital, structures, equipment, and intellectual property products, including equity REITs for all periods (adjusted NIPA basis) | C4: Currency | D4: 1000000 | E4: USD | F4: Z1/Z1/FU106300011.A | G4: FU106300011.A | I4: 7759 | J4: 9485 | K4: 11130 | L4: 12019 | M4: 12861 | N4: 14653 | O4: 15598 | P4: 16749 | Q4: 17748 | R4: 18937 | S4: 21385 | T4: 23788 | U4: 25529 | V4: 26722 | W4: 27597 | X4: 28603 | Y4: 29863 | Z4: 31380 | AA4: 33298 | AB4: 35882 | AC4: 39454 | AD4: 43526 | AE4: 48177 | AF4: 53585 | AG4: 59376 | AH4: 64871 | AI4: 70349 | AJ4: 78370 | AK4: 91609 | AL4: 107974 | AM4: 118530 | AN4: 132826 | AO4: 150435 | AP4: 172753 | AQ4: 199206 | AR4: 229468 | AS4: 254302 | AT4: 265069 | AU4: 279453 | AV4: 299499 | AW4: 318424 | AX4: 335309 | AY4: 358874 | AZ4: 380877 | BA4: 403383 | BB4: 424348 | BC4: 437048 | BD4: 456668 | BE4: 483213 | BF4: 521779 | BG4: 555194 | BH4: 595775 | BI4: 635467 | BJ4: 680702 | BK4: 739330 | BL4: 783516 | BM4: 805023 | BN4: 818192 | BO4: 851953 | BP4: 913611 | BQ4: 984446 | BR4: 1047220 | BS4: 1108750 | BT4: 1114627 | BU4: 1123496 | BV4: 1173464 | BW4: 1234809 | BX4: 1282796 | BY4: 1352680 | BZ4: 1408264 | CA4: 1441019 | CB4: 1509413 | CC4: 1582147 | CD4: 1664697 | CE4: 1728115 | CF4: 1815454 | CG4: 2010486 | CH4: 2154291 | CI4: 2274356
A5: Revaluation | B5: Nonfinancial corporate business; structures, equipment, and intellectual property products, current cost basis (includes used car premium and REITs residential structures) | C5: Currency | D5: 1000000 | E5: USD | F5: Z1/Z1/FR105015085.A | G5: FR105015085.A | I5: 22110 | J5: 23202 | K5: 10339 | L5: -619 | M5: 20152 | N5: 12069 | O5: 6883 | P5: 4554 | Q5: 551 | R5: 19873 | S5: 22244 | T5: 12785 | U5: 292 | V5: 6591 | W5: -3209 | X5: -269 | Y5: 942 | Z5: 429 | AA5: 7619 | AB5: 9213 | AC5: 15302 | AD5: 19988 | AE5: 31158 | AF5: 35332 | AG5: 43359 | AH5: 47579 | AI5: 39464 | AJ5: 79124 | AK5: 197359 | AL5: 110400 | AM5: 104319 | AN5: 124459 | AO5: 163914 | AP5: 214568 | AQ5: 251475 | AR5: 245664 | AS5: 99487 | AT5: 11843 | AU5: 71219 | AV5: 56186 | AW5: 49365 | AX5: 108306 | AY5: 158064 | AZ5: 138104 | BA5: 133816 | BB5: 24491 | BC5: 72449 | BD5: 124101 | BE5: 152522 | BF5: 150467 | BG5: 99652 | BH5: 117879 | BI5: 88266 | BJ5: 105337 | BK5: 176100 | BL5: 124959 | BM5: 118520 | BN5: 112385 | BO5: 583692 | BP5: 652245 | BQ5: 573804 | BR5: 310014 | BS5: 498794 | BT5: -454576 | BU5: 258808 | BV5: 442013 | BW5: 184938 | BX5: 246221 | BY5: 316874 | BZ5: -116253 | CA5: 73163 | CB5: 232187 | CC5: 286130 | CD5: 338284 | CE5: 48684 | CF5: 1649262 | CG5: 1872865 | CH5: 196746 | CI5: 150559
A6: Other Volume Changes | B6: Computed | I6: =I2-H2-I3+I4-I5 -> 0 | J6: =J2-I2-J3+J4-J5 -> 0 | K6: =K2-J2-K3+K4-K5 -> 0 | L6: =L2-K2-L3+L4-L5 -> 0 | M6: =M2-L2-M3+M4-M5 -> 0 | N6: =N2-M2-N3+N4-N5 -> 0 | O6: =O2-N2-O3+O4-O5 -> 0 | P6: =P2-O2-P3+P4-P5 -> 0 | ... CI6: =CI2-CH2-CI3+CI4-CI5 -> -1954
A8: Domestic Financial Sectors
A9: Capital | B9: Domestic financial sectors; capital formation, net (IMA) | C9: Currency | D9: 1000000 | E9: USD | F9: Z1/Z1/FL795015085.A | G9: FL795015085.A | H9: 5205 | I9: 6641 | J9: 7970 | K9: 8603 | L9: 8008 | M9: 8935 | N9: 10342 | O9: 10746 | P9: 10935 | Q9: 10875 | R9: 12073 | S9: 13814 | T9: 14681 | U9: 15095 | V9: 15761 | W9: 16371 | X9: 17273 | Y9: 18427 | Z9: 19459 | AA9: 21404 | AB9: 23477 | AC9: 25888 | AD9: 28481 | AE9: 32723 | AF9: 37259 | AG9: 41806 | AH9: 47679 | AI9: 53508 | AJ9: 61981 | AK9: 77140 | AL9: 86925 | AM9: 97592 | AN9: 110826 | AO9: 129100 | AP9: 155934 | AQ9: 187104 | AR9: 219440 | AS9: 248677 | AT9: 274071 | AU9: 308847 | AV9: 348253 | AW9: 393843 | AX9: 436939 | AY9: 485612 | AZ9: 536959 | BA9: 581721 | BB9: 603264 | BC9: 628236 | BD9: 663261 | BE9: 707646 | BF9: 740958 | BG9: 777003 | BH9: 820370 | BI9: 883585 | BJ9: 954468 | BK9: 1019061 | BL9: 1058635 | BM9: 1091918 | BN9: 1119061 | BO9: 1208042 | BP9: 1297166 | BQ9: 1386483 | BR9: 1452616 | BS9: 1522931 | BT9: 1457558 | BU9: 1448900 | BV9: 1489432 | BW9: 1518382 | BX9: 1560628 | BY9: 1604327 | BZ9: 1651594 | CA9: 1702631 | CB9: 1756682 | CC9: 1845520 | CD9: 1936763 | CE9: 1984392 | CF9: 2232998 | CG9: 2512840 | CH9: 2557957 | CI9: 2648592
A10: Investment NIPA | B10: Domestic financial sectors; gross fixed investment, nonresidential structures, equipment, and intellectual property products | C10: Currency | D10: 1000000 | E10: USD | F10: Z1/Z1/FU795013005.A | G10: FU795013005.A | I10: 540 | J10: 621 | K10: 705 | L10: 747 | M10: 835 | N10: 979 | O10: 910 | P10: 1178 | Q10: 1203 | R10: 1537 | S10: 1666 | T10: 1706 | U10: 1631 | V10: 1815 | W10: 2045 | X10: 2038 | Y10: 2293 | Z10: 2263 | AA10: 2943 | AB10: 3474 | AC10: 3626 | AD10: 3978 | AE10: 5126 | AF10: 5534 | AG10: 5786 | AH10: 6842 | AI10: 7309 | AJ10: 9612 | AK10: 11950 | AL10: 12923 | AM10: 14105 | AN10: 15736 | AO10: 20435 | AP10: 26002 | AQ10: 31633 | AR10: 37510 | AS10: 41342 | AT10: 45815 | AU10: 55850 | AV10: 64130 | AW10: 69944 | AX10: 72912 | AY10: 80344 | AZ10: 89580 | BA10: 87889 | BB10: 80576 | BC10: 80613 | BD10: 88380 | BE10: 96119 | BF10: 98229 | BG10: 109546 | BH10: 116162 | BI10: 139972 | BJ10: 153838 | BK10: 156857 | BL10: 151426 | BM10: 144412 | BN10: 143295 | BO10: 164517 | BP10: 169291 | BQ10: 175965 | BR10: 198114 | BS10: 181022 | BT10: 147686 | BU10: 153492 | BV10: 168104 | BW10: 193222 | BX10: 194426 | BY10: 207539 | BZ10: 228690 | CA10: 244084 | CB10: 247513 | CC10: 266701 | CD10: 301336 | CE10: 284977 | CF10: 302552 | CG10: 318288 | CH10: 359300 | CI10: 394000
A11: Investment NIPA-Fixed Assets | B11: Domestic financial sectors; structures, equipment, and intellectual property products, current cost basis (residual difference between NIPA and fixed asset accounts) | C11: Currency | D11: 1000000 | E11: USD | F11: Z1/Z1/FU795015095.A | G11: FU795015095.A | I11: -7 | J11: -19 | K11: -14 | L11: -17 | M11: -23 | N11: -26 | O11: -16 | P11: -18 | Q11: -16 | R11: -15 | S11: -15 | T11: -20 | U11: -23 | V11: -28 | W11: -31 | X11: -33 | Y11: -24 | Z11: -27 | AA11: -42 | AB11: -49 | AC11: -54 | AD11: -65 | AE11: -75 | AF11: -92 | AG11: -103 | AH11: -119 | AI11: -138 | AJ11: -167 | AK11: -204 | AL11: -228 | AM11: -239 | AN11: -257 | AO11: -271 | AP11: -286 | AQ11: -333 | AR11: -363 | AS11: -403 | AT11: -439 | AU11: -483 | AV11: -507 | AW11: -532 | AX11: -600 | AY11: -652 | AZ11: -691 | BA11: -729 | BB11: -762 | BC11: -769 | BD11: -799 | BE11: -843 | BF11: -917 | BG11: -999 | BH11: -1138 | BI11: -1349 | BJ11: -1612 | BK11: -1848 | BL11: -2026 | BM11: 27 | BN11: 31 | BO11: 26 | BP11: 27 | BQ11: 30 | BR11: 19 | BS11: 20 | BT11: 32 | BU11: 26 | BV11: 20 | BW11: 26 | BX11: 28 | BY11: 20 | BZ11: 29 | CA11: -1 | CB11: -1 | CC11: 0 | CD11: -2 | CE11: 0 | CF11: -2 | CG11: 1 | CH11: 1 | CI11: 1
A12: Investment Computed | B12: Computed | I12: =I10-I11 -> 547 | J12: =J10-J11 -> 640 | K12: =K10-K11 -> 719 | L12: =L10-L11 -> 764 | M12: =M10-M11 -> 858 | N12: =N10-N11 -> 1005 | O12: =O10-O11 -> 926 | P12: =P10-P11 -> 1196 | ... CI12: =CI10-CI11 -> 393999
A13: Depreciation | B13: Domestic financial sectors; consumption of fixed capital, nonresidential structures, equipment, and intellectual property products, including noncorporate financial, current cost basis (IMA) | C13: Currency | D13: 1000000 | E13: USD | F13: Z1/Z1/FA796330081.A | G13: FA796330081.A | I13: 298 | J13: 384 | K13: 442 | L13: 485 | M13: 528 | N13: 600 | O13: 645 | P13: 687 | Q13: 740 | R13: 778 | S13: 878 | T13: 970 | U13: 1080 | V13: 1184 | W13: 1145 | X13: 1182 | Y13: 1235 | Z13: 1302 | AA13: 1392 | AB13: 1561 | AC13: 1735 | AD13: 1930 | AE13: 2211 | AF13: 2570 | AG13: 2940 | AH13: 3341 | AI13: 3756 | AJ13: 4370 | AK13: 5300 | AL13: 6511 | AM13: 7518 | AN13: 8717 | AO13: 10007 | AP13: 11922 | AQ13: 14449 | AR13: 17262 | AS13: 20359 | AT13: 23156 | AU13: 26248 | AV13: 30060 | AW13: 34300 | AX13: 39184 | AY13: 44502 | AZ13: 49994 | BA13: 55143 | BB13: 59174 | BC13: 61104 | BD13: 64383 | BE13: 68449 | BF13: 73008 | BG13: 75730 | BH13: 79216 | BI13: 85037 | BJ13: 95258 | BK13: 106474 | BL13: 112757 | BM13: 115315 | BN13: 120244 | BO13: 127299 | BP13: 135160 | BQ13: 142043 | BR13: 149569 | BS13: 156506 | BT13: 157958 | BU13: 156443 | BV13: 160953 | BW13: 167837 | BX13: 176478 | BY13: 184121 | BZ13: 192444 | CA13: 203220 | CB13: 214439 | CC13: 226122 | CD13: 242836 | CE13: 257539 | CF13: 274459 | CG13: 302232 | CH13: 324065 | CI13: 344821
A14: Revaluation | B14: Domestic financial sectors; capital formation, net (IMA) | C14: Currency | D14: 1000000 | E14: USD | F14: Z1/Z1/FR795015085.A | G14: FR795015085.A | I14: 1187 | J14: 1073 | K14: 356 | L14: -874 | M14: 597 | N14: 1002 | O14: 123 | P14: -320 | Q14: -539 | R14: 424 | S14: 938 | T14: 111 | U14: -160 | V14: 7 | W14: -321 | X14: 13 | Y14: 72 | Z14: 44 | AA14: 352 | AB14: 111 | AC14: 466 | AD14: 480 | AE14: 1252 | AF14: 1480 | AG14: 1598 | AH14: 2256 | AI14: 2204 | AJ14: 3082 | AK14: 8306 | AL14: 3145 | AM14: 3846 | AN14: 5968 | AO14: 7575 | AP14: 12504 | AQ14: 13673 | AR14: 11725 | AS14: 7873 | AT14: 2325 | AU14: 4691 | AV14: 4835 | AW14: 9414 | AX14: 8768 | AY14: 12179 | AZ14: 11256 | BA14: 10074 | BB14: -621 | BC14: 4946 | BD14: 10327 | BE14: 16037 | BF14: 7213 | BG14: 1230 | BH14: 5283 | BI14: 6931 | BJ14: 10735 | BK14: 12362 | BL14: 2648 | BM14: 4213 | BN14: 4123 | BO14: 53453 | BP14: 56697 | BQ14: 55425 | BR14: 17607 | BS14: 46418 | BT14: -55069 | BU14: -3584 | BV14: 33401 | BW14: 5358 | BX14: 24326 | BY14: 20301 | BZ14: 11050 | CA14: 10173 | CB14: 22824 | CC14: 50654 | CD14: 32742 | CE14: 20192 | CF14: 220942 | CG14: 265304 | CH14: 9883 | CI14: 42241
A15: Other Volume Changes | B15: Computed | I15: =I9-H9-I12+I13-I14 -> 0 | J15: =J9-I9-J12+J13-J14 -> 0 | K15: =K9-J9-K12+K13-K14 -> 0 | L15: =L9-K9-L12+L13-L14 -> 0 | M15: =M9-L9-M12+M13-M14 -> 0 | N15: =N9-M9-N12+N13-N14 -> 0 | O15: =O9-N9-O12+O13-O14 -> 0 | P15: =P9-O9-P12+P13-P14 -> 0 | ... CI15: =CI9-CH9-CI12+CI13-CI14 -> -784
A18: Totals
A19: Capital | B19: Computed | H19: =H2+H9 -> 139208 | I19: =I2+I9 -> 168356 | J19: =J2+J9 -> 200698 | K19: =K2+K9 -> 219642 | L19: =L2+L9 -> 223678 | M19: =M2+M9 -> 250857 | N19: =N2+N9 -> 272459 | O19: =O2+O9 -> 288532 | ... CI19: =CI2+CI9 -> 27603501
A20: Investment | B20: Computed | I20: =I3+I12 -> 13908 | J20: =J3+J12 -> 17936 | K20: =K3+K12 -> 19821 | L20: =L3+L12 -> 18033 | M20: =M3+M12 -> 19819 | N20: =N3+N12 -> 23784 | O20: =O3+O12 -> 25310 | P20: =P3+P12 -> 28106 | ... CI20: =CI3+CI12 -> 3308281
A21: Depreciation | B21: Computed | I21: =I4+I13 -> 8057 | J21: =J4+J13 -> 9869 | K21: =K4+K13 -> 11572 | L21: =L4+L13 -> 12504 | M21: =M4+M13 -> 13389 | N21: =N4+N13 -> 15253 | O21: =O4+O13 -> 16243 | P21: =P4+P13 -> 17436 | ... CI21: =CI4+CI13 -> 2619177
A22: Revaluation | B22: Computed | I22: =I5+I14 -> 23297 | J22: =J5+J14 -> 24275 | K22: =K5+K14 -> 10695 | L22: =L5+L14 -> -1493 | M22: =M5+M14 -> 20749 | N22: =N5+N14 -> 13071 | O22: =O5+O14 -> 7006 | P22: =P5+P14 -> 4234 | ... CI22: =CI5+CI14 -> 192800
A23: Other Volume Changes | B23: Computed | I23: =I6+I15 -> 0 | J23: =J6+J15 -> 0 | K23: =K6+K15 -> 0 | L23: =L6+L15 -> 0 | M23: =M6+M15 -> 0 | N23: =N6+N15 -> 0 | O23: =O6+O15 -> 0 | P23: =P6+P15 -> 0 | ... CI23: =CI6+CI15 -> -2738

Sheet L224
A1: Download Page | F1: Z.1 Statistical Release for Jan 09, 2026
A2: Descriptions: | B2: Unit: | C2: Multiplier: | D2: Currency: | E2: Unique Identifier: | F2: Series Name: | G2: 1945 | H2: 1946 | I2: 1947 | J2: 1948 | K2: 1949 | L2: 1950 | M2: 1951 | N2: 1952 | O2: 1953 | P2: 1954 | Q2: 1955 | R2: 1956 | S2: 1957 | T2: 1958 | U2: 1959 | V2: 1960 | W2: 1961 | X2: 1962 | Y2: 1963 | Z2: 1964 | AA2: 1965 | AB2: 1966 | AC2: 1967 | AD2: 1968 | AE2: 1969 | AF2: 1970 | AG2: 1971 | AH2: 1972 | AI2: 1973 | AJ2: 1974 | AK2: 1975 | AL2: 1976 | AM2: 1977 | AN2: 1978 | AO2: 1979 | AP2: 1980 | AQ2: 1981 | AR2: 1982 | AS2: 1983 | AT2: 1984 | AU2: 1985 | AV2: 1986 | AW2: 1987 | AX2: 1988 | AY2: 1989 | AZ2: 1990 | BA2: 1991 | BB2: 1992 | BC2: 1993 | BD2: 1994 | BE2: 1995 | BF2: 1996 | BG2: 1997 | BH2: 1998 | BI2: 1999 | BJ2: 2000 | BK2: 2001 | BL2: 2002 | BM2: 2003 | BN2: 2004 | BO2: 2005 | BP2: 2006 | BQ2: 2007 | BR2: 2008 | BS2: 2009 | BT2: 2010 | BU2: 2011 | BV2: 2012 | BW2: 2013 | BX2: 2014 | BY2: 2015 | BZ2: 2016 | CA2: 2017 | CB2: 2018 | CC2: 2019 | CD2: 2020 | CE2: 2021 | CF2: 2022 | CG2: 2023 | CH2: 2024
A3: All sectors; corporate equities; asset | B3: Currency | C3: 1000000 | D3: USD | E3: Z1/Z1/LM893064105.A | F3: LM893064105.A | G3: 152852 | H3: 146656 | I3: 144829 | J3: 144008 | K3: 153784 | L3: 177528 | M3: 199082 | N3: 198678 | O3: 196403 | P3: 248357 | Q3: 298673 | R3: 323618 | S3: 301375 | T3: 382051 | U3: 420820 | V3: 425058 | W3: 521094 | X3: 503823 | Y3: 558475 | Z3: 647246 | AA3: 734923 | AB3: 660424 | AC3: 835107 | AD3: 996085 | AE3: 840609 | AF3: 831233 | AG3: 974871 | AH3: 1203281 | AI3: 938338 | AJ3: 632492 | AK3: 839378 | AL3: 1034228 | AM3: 922579 | AN3: 969619 | AO3: 1147253 | AP3: 1494924 | AQ3: 1382028 | AR3: 1562485 | AS3: 1855966 | AT3: 1789165 | AU3: 2270405 | AV3: 2682199 | AW3: 2710300 | AX3: 3075619 | AY3: 3812955 | AZ3: 3531306 | BA3: 4847773 | BB3: 5421969 | BC3: 6296866 | BD3: 6317493 | BE3: 8481326 | BF3: 10061049 | BG3: 12994553 | BH3: 15913534 | BI3: 19973394 | BJ3: 18244390 | BK3: 16388532 | BL3: 13194274 | BM3: 17330352 | BN3: 19800437 | BO3: 21515809 | BP3: 24973843 | BQ3: 26300070 | BR3: 16482304 | BS3: 21008142 | BT3: 24428137 | BU3: 23655389 | BV3: 27064003 | BW3: 34766495 | BX3: 38422608 | BY3: 37357372 | BZ3: 40313791 | CA3: 48133249 | CB3: 44014308 | CC3: 54708167 | CD3: 65517579 | CE3: 81253224 | CF3: 65308604 | CG3: 78220902 | CH3: 93815167
A4: Nonfinancial corporate business; corporate equities; liability | B4: Currency | C4: 1000000 | D4: USD | E4: Z1/Z1/LM103164105.A | F4: LM103164105.A | G4: 103694 | H4: 97302 | I4: 95116 | J4: 94141 | K4: 103822 | L4: 126681 | M4: 147629 | N4: 146628 | O4: 144082 | P4: 194840 | Q4: 244222 | R4: 268373 | S4: 245747 | T4: 324670 | U4: 362157 | V4: 365166 | W4: 437674 | X4: 424314 | Y4: 465779 | Z4: 545955 | AA4: 623812 | AB4: 547891 | AC4: 712221 | AD4: 843150 | AE4: 705075 | AF4: 702482 | AG4: 824038 | AH4: 1032948 | AI4: 809566 | AJ4: 557656 | AK4: 754897 | AL4: 927412 | AM4: 819176 | AN4: 856335 | AO4: 1014783 | AP4: 1346523 | AQ4: 1225637 | AR4: 1386479 | AS4: 1630514 | AT4: 1553653 | AU4: 1917631 | AV4: 2241896 | AW4: 2287678 | AX4: 2559333 | AY4: 3140008 | AZ4: 2956992 | BA4: 4000417 | BB4: 4369261 | BC4: 4865339 | BD4: 4831577 | BE4: 6449974 | BF4: 7403482 | BG4: 9429717 | BH4: 11881725 | BI4: 15381893 | BJ4: 13361037 | BK4: 11944574 | BL4: 9269952 | BM4: 11931885 | BN4: 13516322 | BO4: 14216036 | BP4: 16022269 | BQ4: 16913376 | BR4: 11039201 | BS4: 13674425 | BT4: 15565512 | BU4: 15598527 | BV4: 17485958 | BW4: 22684806 | BX4: 25320711 | BY4: 24335330 | BZ4: 25843298 | CA4: 30023624 | CB4: 27922692 | CC4: 35063233 | CD4: 43783375 | CE4: 54262122 | CF4: 42065026 | CG4: 51743045 | CH4: 62728651
A5: Nonfinancial corporate business; public corporate equities; liability (includes closely held before 1996q4) | B5: Currency | C5: 1000000 | D5: USD | E5: Z1/Z1/LM103164115.A | F5: LM103164115.A | G5: 103694 | H5: 97302 | I5: 95116 | J5: 94141 | K5: 103822 | L5: 126681 | M5: 147629 | N5: 146628 | O5: 144082 | P5: 194840 | Q5: 244222 | R5: 268373 | S5: 245747 | T5: 324670 | U5: 362157 | V5: 365166 | W5: 437674 | X5: 424314 | Y5: 465779 | Z5: 545955 | AA5: 623812 | AB5: 547891 | AC5: 712221 | AD5: 843150 | AE5: 705075 | AF5: 702482 | AG5: 824038 | AH5: 1032948 | AI5: 809566 | AJ5: 557656 | AK5: 754897 | AL5: 927412 | AM5: 819176 | AN5: 856335 | AO5: 1014783 | AP5: 1346523 | AQ5: 1225637 | AR5: 1386479 | AS5: 1630514 | AT5: 1553653 | AU5: 1917631 | AV5: 2241896 | AW5: 2287678 | AX5: 2559333 | AY5: 3140008 | AZ5: 2956992 | BA5: 4000417 | BB5: 4369261 | BC5: 4865339 | BD5: 4831577 | BE5: 6449974 | BF5: 6452650 | BG5: 8173484 | BH5: 10310699 | BI5: 13687036 | BJ5: 11865829 | BK5: 10431925 | BL5: 7957785 | BM5: 10386711 | BN5: 11644860 | BO5: 12062909 | BP5: 13420745 | BQ5: 14030865 | BR5: 8821591 | BS5: 11188489 | BT5: 12978719 | BU5: 13023982 | BV5: 14496468 | BW5: 18672464 | BX5: 20495535 | BY5: 19567299 | BZ5: 20741195 | CA5: 24356405 | CB5: 22485665 | CC5: 28530744 | CD5: 36091357 | CE5: 44798142 | CF5: 34091709 | CG5: 42480113 | CH5: 51870336
A6: Nonfinancial corporate business; closely held corporate equities; liability | B6: Currency | C6: 1000000 | D6: USD | E6: Z1/Z1/LM103164125.A | F6: LM103164125.A | G6: 0 | H6: 0 | I6: 0 | J6: 0 | K6: 0 | L6: 0 | M6: 0 | N6: 0 | O6: 0 | P6: 0 | Q6: 0 | R6: 0 | S6: 0 | T6: 0 | U6: 0 | V6: 0 | W6: 0 | X6: 0 | Y6: 0 | Z6: 0 | AA6: 0 | AB6: 0 | AC6: 0 | AD6: 0 | AE6: 0 | AF6: 0 | AG6: 0 | AH6: 0 | AI6: 0 | AJ6: 0 | AK6: 0 | AL6: 0 | AM6: 0 | AN6: 0 | AO6: 0 | AP6: 0 | AQ6: 0 | AR6: 0 | AS6: 0 | AT6: 0 | AU6: 0 | AV6: 0 | AW6: 0 | AX6: 0 | AY6: 0 | AZ6: 0 | BA6: 0 | BB6: 0 | BC6: 0 | BD6: 0 | BE6: 0 | BF6: 950832 | BG6: 1256233 | BH6: 1571026 | BI6: 1694857 | BJ6: 1495208 | BK6: 1512649 | BL6: 1312167 | BM6: 1545174 | BN6: 1871462 | BO6: 2153127 | BP6: 2601524 | BQ6: 2882511 | BR6: 2217610 | BS6: 2485936 | BT6: 2586793 | BU6: 2574545 | BV6: 2989490 | BW6: 4012342 | BX6: 4825176 | BY6: 4768031 | BZ6: 5102103 | CA6: 5667219 | CB6: 5437027 | CC6: 6532489 | CD6: 7692018 | CE6: 9463980 | CF6: 7973317 | CG6: 9262932 | CH6: 10858315
A7: Domestic financial sectors; corporate equities; liability | B7: Currency | C7: 1000000 | D7: USD | E7: Z1/Z1/LM793164105.A | F7: LM793164105.A | G7: 48216 | H7: 48353 | I7: 48741 | J7: 48923 | K7: 49254 | L7: 49672 | M7: 50063 | N7: 50591 | O7: 50992 | P7: 51649 | Q7: 52012 | R7: 52620 | S7: 53395 | T7: 54286 | U7: 54974 | V7: 55908 | W7: 78518 | X7: 74795 | Y7: 87551 | Z7: 96021 | AA7: 106063 | AB7: 108209 | AC7: 117648 | AD7: 146483 | AE7: 128581 | AF7: 122178 | AG7: 143192 | AH7: 159796 | AI7: 118746 | AJ7: 65825 | AK7: 74896 | AL7: 97363 | AM7: 93293 | AN7: 102048 | AO7: 117667 | AP7: 129471 | AQ7: 139924 | AR7: 158564 | AS7: 199298 | AT7: 209518 | AU7: 308391 | AV7: 367904 | AW7: 327922 | AX7: 387624 | AY7: 475602 | AZ7: 376718 | BA7: 568380 | BB7: 738442 | BC7: 887665 | BD7: 859154 | BE7: 1240737 | BF7: 1651432 | BG7: 2357049 | BH7: 2556826 | BI7: 2587785 | BJ7: 3030511 | BK7: 2831285 | BL7: 2550342 | BM7: 3319045 | BN7: 3723697 | BO7: 3982068 | BP7: 4622614 | BQ7: 4138704 | BR7: 2694675 | BS7: 3338422 | BT7: 3962379 | BU7: 3555424 | BV7: 4256188 | BW7: 5608812 | BX7: 6331268 | BY7: 6265879 | BZ7: 7324173 | CA7: 8991487 | CB7: 8192053 | CC7: 10166920 | CD7: 11119188 | CE7: 14929808 | CF7: 13111550 | CG7: 15210823 | CH7: 19090227
A8: U.S.-chartered depository institutions; corporate equities; liability | B8: Currency | C8: 1000000 | D8: USD | E8: Z1/Z1/LM763164105.A | F8: LM763164105.A | G8: 1811 | H8: 2333 | I8: 2890 | J8: 2444 | K8: 2599 | L8: 2077 | M8: 2184 | N8: 2155 | O8: 2723 | P8: 2600 | Q8: 2333 | R8: 2210 | S8: 2797 | T8: 2805 | U8: 2293 | V8: 2672 | W8: 3694 | X8: 3357 | Y8: 4302 | Z8: 4136 | AA8: 5165 | AB8: 5215 | AC8: 5190 | AD8: 4547 | AE8: 3511 | AF8: 4819 | AG8: 5250 | AH8: 5501 | AI8: 2928 | AJ8: 1597 | AK8: 1745 | AL8: 2722 | AM8: 2645 | AN8: 2977 | AO8: 3383 | AP8: 3380 | AQ8: 3870 | AR8: 3428 | AS8: 4395 | AT8: 3851 | AU8: 5739 | AV8: 9789 | AW8: 8185 | AX8: 12172 | AY8: 10651 | AZ8: 5826 | BA8: 10970 | BB8: 14827 | BC8: 22532 | BD8: 24924 | BE8: 36915 | BF8: 52174 | BG8: 75872 | BH8: 78727 | BI8: 82826 | BJ8: 116815 | BK8: 117090 | BL8: 117969 | BM8: 139529 | BN8: 138994 | BO8: 145418 | BP8: 125303 | BQ8: 70673 | BR8: 62389 | BS8: 41667 | BT8: 62456 | BU8: 53866 | BV8: 33301 | BW8: 51542 | BX8: 67511 | BY8: 76484 | BZ8: 102169 | CA8: 118718 | CB8: 104895 | CC8: 125862 | CD8: 119268 | CE8: 172345 | CF8: 124146 | CG8: 98740 | CH8: 105790
A9: U.S.-chartered depository institutions; public corporate equities; liability | B9: Currency | C9: 1000000 | D9: USD | E9: Z1/Z1/LM763164113.A | F9: LM763164113.A | G9: 1811 | H9: 2333 | I9: 2890 | J9: 2444 | K9: 2599 | L9: 2077 | M9: 2184 | N9: 2155 | O9: 2723 | P9: 2600 | Q9: 2333 | R9: 2210 | S9: 2797 | T9: 2805 | U9: 2293 | V9: 2672 | W9: 3694 | X9: 3357 | Y9: 4302 | Z9: 4136 | AA9: 5165 | AB9: 5215 | AC9: 5190 | AD9: 4547 | AE9: 3511 | AF9: 4819 | AG9: 5250 | AH9: 5501 | AI9: 2928 | AJ9: 1597 | AK9: 1745 | AL9: 2722 | AM9: 2645 | AN9: 2977 | AO9: 3383 | AP9: 3380 | AQ9: 3870 | AR9: 3428 | AS9: 4395 | AT9: 3851 | AU9: 5739 | AV9: 9789 | AW9: 8185 | AX9: 12172 | AY9: 10651 | AZ9: 5826 | BA9: 10970 | BB9: 14827 | BC9: 22532 | BD9: 24924 | BE9: 36915 | BF9: 47450 | BG9: 65875 | BH9: 71612 | BI9: 78650 | BJ9: 110284 | BK9: 112201 | BL9: 112406 | BM9: 132823 | BN9: 131306 | BO9: 136836 | BP9: 115916 | BQ9: 64483 | BR9: 57063 | BS9: 38480 | BT9: 57438 | BU9: 49334 | BV9: 29258 | BW9: 45788 | BX9: 61821 | BY9: 70446 | BZ9: 93517 | CA9: 109215 | CB9: 97687 | CC9: 118774 | CD9: 111149 | CE9: 158744 | CF9: 114892 | CG9: 91473 | CH9: 97584
A10: U.S.-chartered depository institutions; closely held corporate equities; liability | B10: Currency | C10: 1000000 | D10: USD | E10: Z1/Z1/LM763164123.A | F10: LM763164123.A | G10: 0 | H10: 0 | I10: 0 | J10: 0 | K10: 0 | L10: 0 | M10: 0 | N10: 0 | O10: 0 | P10: 0 | Q10: 0 | R10: 0 | S10: 0 | T10: 0 | U10: 0 | V10: 0 | W10: 0 | X10: 0 | Y10: 0 | Z10: 0 | AA10: 0 | AB10: 0 | AC10: 0 | AD10: 0 | AE10: 0 | AF10: 0 | AG10: 0 | AH10: 0 | AI10: 0 | AJ10: 0 | AK10: 0 | AL10: 0 | AM10: 0 | AN10: 0 | AO10: 0 | AP10: 0 | AQ10: 0 | AR10: 0 | AS10: 0 | AT10: 0 | AU10: 0 | AV10: 0 | AW10: 0 | AX10: 0 | AY10: 0 | AZ10: 0 | BA10: 0 | BB10: 0 | BC10: 0 | BD10: 0 | BE10: 0 | BF10: 4724 | BG10: 9997 | BH10: 7115 | BI10: 4176 | BJ10: 6531 | BK10: 4889 | BL10: 5563 | BM10: 6706 | BN10: 7688 | BO10: 8582 | BP10: 9387 | BQ10: 6190 | BR10: 5326 | BS10: 3187 | BT10: 5018 | BU10: 4532 | BV10: 4043 | BW10: 5754 | BX10: 5690 | BY10: 6038 | BZ10: 8652 | CA10: 9503 | CB10: 7208 | CC10: 7088 | CD10: 8119 | CE10: 13601 | CF10: 9254 | CG10: 7267 | CH10: 8206
A11: Property-casualty insurance companies; corporate equities; liability | B11: Currency | C11: 1000000 | D11: USD | E11: Z1/Z1/LM513164105.A | F11: LM513164105.A | G11: 0 | H11: 0 | I11: 0 | J11: 0 | K11: 0 | L11: 0 | M11: 0 | N11: 0 | O11: 0 | P11: 0 | Q11: 0 | R11: 0 | S11: 0 | T11: 0 | U11: 0 | V11: 0 | W11: 0 | X11: 6599 | Y11: 6620 | Z11: 7574 | AA11: 9950 | AB11: 11647 | AC11: 8068 | AD11: 2726 | AE11: 3565 | AF11: 5168 | AG11: 5828 | AH11: 8255 | AI11: 5429 | AJ11: 3056 | AK11: 3543 | AL11: 4362 | AM11: 4486 | AN11: 7041 | AO11: 8798 | AP11: 9711 | AQ11: 12034 | AR11: 13786 | AS11: 16063 | AT11: 13827 | AU11: 23816 | AV11: 30532 | AW11: 26463 | AX11: 32871 | AY11: 46062 | AZ11: 40125 | BA11: 56247 | BB11: 73671 | BC11: 101382 | BD11: 103488 | BE11: 153585 | BF11: 183770 | BG11: 275189 | BH11: 366532 | BI11: 392953 | BJ11: 525478 | BK11: 474686 | BL11: 400734 | BM11: 476258 | BN11: 536968 | BO11: 576026 | BP11: 649672 | BQ11: 600298 | BR11: 314305 | BS11: 323607 | BT11: 421489 | BU11: 404925 | BV11: 401526 | BW11: 541279 | BX11: 638053 | BY11: 588241 | BZ11: 644748 | CA11: 835774 | CB11: 810396 | CC11: 896559 | CD11: 870738 | CE11: 1024210 | CF11: 1029895 | CG11: 1153411 | CH11: 1462384
A12: Property-casualty insurance companies; public corporate equities; liability | B12: Currency | C12: 1000000 | D12: USD | E12: Z1/Z1/LM513164113.A | F12: LM513164113.A | G12: 0 | H12: 0 | I12: 0 | J12: 0 | K12: 0 | L12: 0 | M12: 0 | N12: 0 | O12: 0 | P12: 0 | Q12: 0 | R12: 0 | S12: 0 | T12: 0 | U12: 0 | V12: 0 | W12: 0 | X12: 6599 | Y12: 6620 | Z12: 7574 | AA12: 9950 | AB12: 11647 | AC12: 8068 | AD12: 2726 | AE12: 3565 | AF12: 5168 | AG12: 5828 | AH12: 8255 | AI12: 5429 | AJ12: 3056 | AK12: 3543 | AL12: 4362 | AM12: 4486 | AN12: 7041 | AO12: 8798 | AP12: 9711 | AQ12: 12034 | AR12: 13786 | AS12: 16063 | AT12: 13827 | AU12: 23816 | AV12: 30532 | AW12: 26463 | AX12: 32871 | AY12: 46062 | AZ12: 40125 | BA12: 56247 | BB12: 73671 | BC12: 101382 | BD12: 103488 | BE12: 153585 | BF12: 181838 | BG12: 272325 | BH12: 362977 | BI12: 389390 | BJ12: 520945 | BK12: 470777 | BL12: 397366 | BM12: 473166 | BN12: 532629 | BO12: 571606 | BP12: 644674 | BQ12: 595533 | BR12: 311629 | BS12: 321327 | BT12: 419002 | BU12: 402742 | BV12: 399794 | BW12: 538003 | BX12: 634498 | BY12: 584756 | BZ12: 640883 | CA12: 831287 | CB12: 806357 | CC12: 891479 | CD12: 866169 | CE12: 1018274 | CF12: 1021245 | CG12: 1144650 | CH12: 1450846
A13: Property-casualty insurance companies; closely held corporate equities; liability | B13: Currency | C13: 1000000 | D13: USD | E13: Z1/Z1/LM513164123.A | F13: LM513164123.A | G13: 0 | H13: 0 | I13: 0 | J13: 0 | K13: 0 | L13: 0 | M13: 0 | N13: 0 | O13: 0 | P13: 0 | Q13: 0 | R13: 0 | S13: 0 | T13: 0 | U13: 0 | V13: 0 | W13: 0 | X13: 0 | Y13: 0 | Z13: 0 | AA13: 0 | AB13: 0 | AC13: 0 | AD13: 0 | AE13: 0 | AF13: 0 | AG13: 0 | AH13: 0 | AI13: 0 | AJ13: 0 | AK13: 0 | AL13: 0 | AM13: 0 | AN13: 0 | AO13: 0 | AP13: 0 | AQ13: 0 | AR13: 0 | AS13: 0 | AT13: 0 | AU13: 0 | AV13: 0 | AW13: 0 | AX13: 0 | AY13: 0 | AZ13: 0 | BA13: 0 | BB13: 0 | BC13: 0 | BD13: 0 | BE13: 0 | BF13: 1932 | BG13: 2864 | BH13: 3555 | BI13: 3563 | BJ13: 4533 | BK13: 3909 | BL13: 3368 | BM13: 3092 | BN13: 4339 | BO13: 4420 | BP13: 4998 | BQ13: 4765 | BR13: 2676 | BS13: 2280 | BT13: 2487 | BU13: 2183 | BV13: 1732 | BW13: 3276 | BX13: 3555 | BY13: 3485 | BZ13: 3865 | CA13: 4487 | CB13: 4039 | CC13: 5080 | CD13: 4569 | CE13: 5936 | CF13: 8650 | CG13: 8761 | CH13: 11538
A14: Life insurance companies, general accounts; corporate equities; liability | B14: Currency | C14: 1000000 | D14: USD | E14: Z1/Z1/LM543164175.A | F14: LM543164175.A | G14: 0 | H14: 0 | I14: 0 | J14: 0 | K14: 0 | L14: 0 | M14: 0 | N14: 0 | O14: 0 | P14: 0 | Q14: 0 | R14: 0 | S14: 0 | T14: 0 | U14: 0 | V14: 0 | W14: 0 | X14: 0 | Y14: 85 | Z14: 77 | AA14: 80 | AB14: 79 | AC14: 231 | AD14: 6285 | AE14: 8089 | AF14: 7360 | AG14: 9071 | AH14: 12927 | AI14: 9095 | AJ14: 4799 | AK14: 5391 | AL14: 6689 | AM14: 6887 | AN14: 5930 | AO14: 5853 | AP14: 4829 | AQ14: 5186 | AR14: 4893 | AS14: 6556 | AT14: 6974 | AU14: 10386 | AV14: 12505 | AW14: 10973 | AX14: 13334 | AY14: 20645 | AZ14: 16308 | BA14: 25827 | BB14: 40569 | BC14: 44977 | BD14: 38542 | BE14: 55442 | BF14: 67314 | BG14: 97662 | BH14: 102119 | BI14: 72458 | BJ14: 134168 | BK14: 98626 | BL14: 85723 | BM14: 108141 | BN14: 127873 | BO14: 159130 | BP14: 153064 | BQ14: 155956 | BR14: 80607 | BS14: 97122 | BT14: 123343 | BU14: 97440 | BV14: 125274 | BW14: 209736 | BX14: 210581 | BY14: 182189 | BZ14: 211936 | CA14: 230611 | CB14: 188467 | CC14: 211660 | CD14: 177370 | CE14: 239294 | CF14: 246953 | CG14: 255009 | CH14: 288740
... A55: All domestic sectors; closely held C corporation corporate equities; liability | B55: Currency | C55: 1000000 | D55: USD | E55: Z1/Z1/LM883164135.A | F55: LM883164135.A | G55: 0 | H55: 0 | I55: 0 | J55: 0 | K55: 0 | L55: 0 | M55: 0 | N55: 0 | O55: 0 | P55: 0 | Q55: 0 | R55: 0 | S55: 0 | T55: 0 | U55: 0 | V55: 0 | W55: 0 | X55: 0 | Y55: 0 | Z55: 0 | AA55: 0 | AB55: 0 | AC55: 0 | AD55: 0 | AE55: 0 | AF55: 0 | AG55: 0 | AH55: 0 | AI55: 0 | AJ55: 0 | AK55: 0 | AL55: 0 | AM55: 0 | AN55: 0 | AO55: 0 | AP55: 0 | AQ55: 0 | AR55: 0 | AS55: 0 | AT55: 0 | AU55: 0 | AV55: 0 | AW55: 0 | AX55: 0 | AY55: 0 | AZ55: 0 | BA55: 0 | BB55: 0 | BC55: 0 | BD55: 0 | BE55: 0 | BF55: 327923 | BG55: 450434 | BH55: 562397 | BI55: 401901 | BJ55: 348372 | BK55: 390243 | BL55: 343197 | BM55: 396442 | BN55: 566836 | BO55: 697589 | BP55: 953987 | BQ55: 1119493 | BR55: 967278 | BS55: 1021054 | BT55: 969234 | BU55: 885211 | BV55: 1022860 | BW55: 1616477 | BX55: 1864446 | BY55: 1722757 | BZ55: 1720803 | CA55: 1746947 | CB55: 1707254 | CC55: 1882260 | CD55: 2127540 | CE55: 2320868 | CF55: 1948356 | CG55: 2132967 | CH55: 2415675
A56: Interest rates and price indexes; Dow Jones U.S. Total Market Index | B56: Percent | C56: 1000000 | D56: USD | E56: Z1/Z1/PC073164013.A | F56: PC073164013.A | AG56: 14.331483 | AH56: 14.858943 | AI56: -20.96468 | AJ56: -31.493623 | AK56: 32.830233 | AL56: 21.683351 | AM56: -6.9787671 | AN56: 3.9635417 | AO56: 19.283245 | AP56: 27.607635 | AQ56: -8.4259464 | AR56: 12.855299 | AS56: 18.74014 | AT56: -1.2537566 | AU56: 27.184329 | AV56: 12.484929 | AW56: -0.73225323 | AX56: 13.292679 | AY56: 24.885153 | AZ56: -9.3137771 | BA56: 30.3009 | BB56: 6.1525327 | BC56: 8.5809596 | BD56: -2.5164079 | BE56: 33.400505 | BF56: 18.838376 | BG56: 29.172206 | BH56: 21.718205 | BI56: 22.046036 | BJ56: -11.849918 | BK56: -12.058266 | BL56: -22.082188 | BM56: 29.442455 | BN56: 10.665551 | BO56: 4.5660492 | BP56: 13.752223 | BQ56: 3.7831092 | BR56: -38.613913 | BS56: 25.70967 | BT56: 15.338982 | BU56: -0.85397903 | BV56: 13.945034 | BW56: 30.861658 | BX56: 10.361059 | BY56: -1.5106481 | BZ56: 10.311394 | CA56: 18.887791 | CB56: -7.0417614 | CC56: 28.419861 | CD56: 18.720051 | CE56: 24.005052 | CF56: -20.795422 | CG56: 24.05692 | CH56: 22.206198
A60: Ratio of Equity Market Cap to CRSP | G60: =G4+G7 -> 151910 | H60: =H4+H7 -> 145655 | I60: =I4+I7 -> 143857 | J60: =J4+J7 -> 143064 | K60: =K4+K7 -> 153076 | L60: =L4+L7 -> 176353
A61: CRSP | G61: ='CRSP Data'!U4 -> 64330622 | H61: ='CRSP Data'!V4 -> 59684384 | I61: ='CRSP Data'!W4 -> 59885361 | J61: ='CRSP Data'!X4 -> 58301258 | K61: ='CRSP Data'!Y4 -> 67344403 | L61: ='CRSP Data'!Z4 -> 84833974
G63: =G60/G61 -> 0.0023613949 | H63: =H60/H61 -> 0.0024404206 | I63: =I60/I61 -> 0.0024022065 | J63: =J60/J61 -> 0.002453875 | K63: =K60/K61 -> 0.0022730322 | L63: =L60/L61 -> 0.0020788016

Sheet S5
A1: Download Page | F1: Z.1 Statistical Release for Jan 09, 2026
A2: Descriptions: | B2: Unit: | C2: Multiplier: | D2: Currency: | E2: Unique Identifier: | F2: Series Name: | G2: 1945 | H2: 1946 | I2: 1947 | J2: 1948 | K2: 1949 | L2: 1950 | M2: 1951 | N2: 1952 | O2: 1953 | P2: 1954 | Q2: 1955 | R2: 1956 | S2: 1957 | T2: 1958 | U2: 1959 | V2: 1960 | W2: 1961 | X2: 1962 | Y2: 1963 | Z2: 1964 | AA2: 1965 | AB2: 1966 | AC2: 1967 | AD2: 1968 | AE2: 1969 | AF2: 1970 | AG2: 1971 | AH2: 1972 | AI2: 1973 | AJ2: 1974 | AK2: 1975 | AL2: 1976 | AM2: 1977 | AN2: 1978 | AO2: 1979 | AP2: 1980 | AQ2: 1981 | AR2: 1982 | AS2: 1983 | AT2: 1984 | AU2: 1985 | AV2: 1986 | AW2: 1987 | AX2: 1988 | AY2: 1989 | AZ2: 1990 | BA2: 1991 | BB2: 1992 | BC2: 1993 | BD2: 1994 | BE2: 1995 | BF2: 1996 | BG2: 1997 | BH2: 1998 | BI2: 1999 | BJ2: 2000 | BK2: 2001 | BL2: 2002 | BM2: 2003 | BN2: 2004 | BO2: 2005 | BP2: 2006 | BQ2: 2007 | BR2: 2008 | BS2: 2009 | BT2: 2010 | BU2: 2011 | BV2: 2012 | BW2: 2013 | BX2: 2014 | BY2: 2015 | BZ2: 2016 | CA2: 2017 | CB2: 2018 | CC2: 2019 | CD2: 2020 | CE2: 2021 | CF2: 2022 | CG2: 2023 | CH2: 2024
A3: Nonfinancial corporate business; gross value added | B3: Currency | C3: 1000000 | D3: USD | E3: Z1/Z1/FA106902501.A | F3: FA106902501.A | H3: 100771 | I3: 122211 | J3: 140041 | K3: 136291 | L3: 154866 | M3: 177643 | N3: 185882 | O3: 199045 | P3: 196163 | Q3: 221377 | R3: 237234 | S3: 247921 | T3: 242248 | U3: 271655 | V3: 282485 | W3: 290424 | X3: 316808 | Y3: 337829 | Z3: 364524 | AA3: 400741 | AB3: 440079 | AC3: 463192 | AD3: 510945 | AE3: 554625 | AF3: 572891 | AG3: 618096 | AH3: 685949 | AI3: 768838 | AJ3: 830041 | AK3: 898279 | AL3: 1014666 | AM3: 1147402 | AN3: 1303931 | AO3: 1450327 | AP3: 1574528 | AQ3: 1789068 | AR3: 1854861 | AS3: 1985899 | AT3: 2226002 | AU3: 2369167 | AV3: 2464907 | AW3: 2641902 | AX3: 2873908 | AY3: 3020213 | AZ3: 3160696 | BA3: 3231238 | BB3: 3376497 | BC3: 3534938 | BD3: 3816576 | BE3: 4041487 | BF3: 4296356 | BG3: 4609354 | BH3: 4875177 | BI3: 5168285 | BJ3: 5510788 | BK3: 5470157 | BL3: 5543552 | BM3: 5733743 | BN3: 6133642 | BO3: 6575529 | BP3: 7021572 | BQ3: 7257368 | BR3: 7327703 | BS3: 6904035 | BT3: 7287190 | BU3: 7661064 | BV3: 8110945 | BW3: 8417763 | BX3: 8851700 | BY3: 9222331 | BZ3: 9346389 | CA3: 9771450 | CB3: 10337805 | CC3: 10799812 | CD3: 10498662 | CE3: 12072724 | CF3: 13445428 | CG3: 14163359 | CH3: 14849198
A4: Nonfinancial corporate business; consumption of fixed capital, structures, equipment, and intellectual property products, including equity REIT residential structures (NIPA basis) | B4: Currency | C4: 1000000 | D4: USD | E4: Z1/Z1/FA106300003.A | F4: FA106300003.A | H4: 7752 | I4: 9476 | J4: 11120 | K4: 12008 | L4: 12848 | M4: 14636 | N4: 15581 | O4: 16729 | P4: 17724 | Q4: 18913 | R4: 21356 | S4: 23757 | T4: 25496 | U4: 26689 | V4: 27561 | W4: 28564 | X4: 29824 | Y4: 31340 | Z4: 33253 | AA4: 35829 | AB4: 39392 | AC4: 43452 | AD4: 48092 | AE4: 53485 | AF4: 59260 | AG4: 64733 | AH4: 70189 | AI4: 78181 | AJ4: 91385 | AK4: 107725 | AL4: 118273 | AM4: 132560 | AN4: 150153 | AO4: 172444 | AP4: 198860 | AQ4: 229084 | AR4: 253881 | AS4: 264616 | AT4: 278952 | AU4: 298976 | AV4: 317873 | AW4: 334692 | AX4: 358201 | AY4: 380160 | AZ4: 402625 | BA4: 423557 | BB4: 436253 | BC4: 455845 | BD4: 482344 | BE4: 520836 | BF4: 554165 | BG4: 594613 | BH4: 634096 | BI4: 679077 | BJ4: 737452 | BK4: 781461 | BL4: 805023 | BM4: 818192 | BN4: 851953 | BO4: 913611 | BP4: 984446 | BQ4: 1047220 | BR4: 1108750 | BS4: 1114627 | BT4: 1123496 | BU4: 1173464 | BV4: 1234809 | BW4: 1282796 | BX4: 1352680 | BY4: 1408264 | BZ4: 1441019 | CA4: 1509413 | CB4: 1582147 | CC4: 1664697 | CD4: 1728115 | CE4: 1815454 | CF4: 2010486 | CG4: 2154291 | CH4: 2274356
A5: Nonfinancial corporate business; net value added | B5: Currency | C5: 1000000 | D5: USD | E5: Z1/Z1/FA106902605.A | F5: FA106902605.A | H5: 93019 | I5: 112735 | J5: 128921 | K5: 124283 | L5: 142018 | M5: 163007 | N5: 170301 | O5: 182316 | P5: 178439 | Q5: 202464 | R5: 215878 | S5: 224164 | T5: 216752 | U5: 244966 | V5: 254924 | W5: 261860 | X5: 286984 | Y5: 306489 | Z5: 331271 | AA5: 364912 | AB5: 400687 | AC5: 419740 | AD5: 462853 | AE5: 501140 | AF5: 513631 | AG5: 553363 | AH5: 615760 | AI5: 690657 | AJ5: 738656 | AK5: 790554 | AL5: 896393 | AM5: 1014842 | AN5: 1153778 | AO5: 1277883 | AP5: 1375668 | AQ5: 1559984 | AR5: 1600980 | AS5: 1721283 | AT5: 1947050 | AU5: 2070191 | AV5: 2147034 | AW5: 2307210 | AX5: 2515707 | AY5: 2640053 | AZ5: 2758071 | BA5: 2807681 | BB5: 2940244 | BC5: 3079093 | BD5: 3334232 | BE5: 3520651 | BF5: 3742191 | BG5: 4014741 | BH5: 4241081 | BI5: 4489208 | BJ5: 4773336 | BK5: 4688696 | BL5: 4738529 | BM5: 4915551 | BN5: 5281689 | BO5: 5661918 | BP5: 6037126 | BQ5: 6210148 | BR5: 6218953 | BS5: 5789408 | BT5: 6163694 | BU5: 6487600 | BV5: 6876136 | BW5: 7134967 | BX5: 7499020 | BY5: 7814067 | BZ5: 7905370 | CA5: 8262037 | CB5: 8755658 | CC5: 9135115 | CD5: 8770547 | CE5: 10257270 | CF5: 11434942 | CG5: 12009069 | CH5: 12574842
A6: Nonfinancial corporate business; compensation of employees paid | B6: Currency | C6: 1000000 | D6: USD | E6: Z1/Z1/FA106025005.A | F6: FA106025005.A | H6: 66853 | I6: 78763 | J6: 87467 | K6: 84902 | L6: 94387 | M6: 109808 | N6: 117770 | O6: 128198 | P6: 125945 | Q6: 137886 | R6: 150770 | S6: 158411 | T6: 155209 | U6: 170794 | V6: 180409 | W6: 184516 | X6: 199256 | Y6: 210106 | Z6: 225657 | AA6: 245400 | AB6: 272851 | AC6: 291064 | AD6: 320870 | AE6: 356065 | AF6: 374486 | AG6: 396189 | AH6: 439925 | AI6: 495100 | AJ6: 542935 | AK6: 569020 | AL6: 640006 | AM6: 723328 | AN6: 829500 | AO6: 942401 | AP6: 1030693 | AQ6: 1139852 | AR6: 1183262 | AS6: 1250111 | AT6: 1388208 | AU6: 1490089 | AV6: 1578177 | AW6: 1685458 | AX6: 1825310 | AY6: 1934824 | AZ6: 2037524 | BA6: 2071122 | BB6: 2188675 | BC6: 2271016 | BD6: 2398673 | BE6: 2524558 | BF6: 2667704 | BG6: 2862553 | BH6: 3093834 | BI6: 3309976 | BJ6: 3597328 | BK6: 3582305 | BL6: 3540452 | BM6: 3594307 | BN6: 3761335 | BO6: 3928746 | BP6: 4127501 | BQ6: 4307102 | BR6: 4364267 | BS6: 4094886 | BT6: 4166599 | BU6: 4372726 | BV6: 4608339 | BW6: 4773790 | BX6: 5032918 | BY6: 5303854 | BZ6: 5448418 | CA6: 5727600 | CB6: 6047037 | CC6: 6344265 | CD6: 6350094 | CE6: 6998733 | CF6: 7593396 | CG6: 8015626 | CH6: 8451105
A7: Nonfinancial corporate business; wages and salaries paid | B7: Currency | C7: 1000000 | D7: USD | E7: Z1/Z1/FA106020001.A | F7: FA106020001.A | H7: 63608 | I7: 74759 | J7: 83441 | K7: 80689 | L7: 88948 | M7: 103053 | N7: 110547 | O7: 120353 | P7: 117730 | Q7: 128511 | R7: 140085 | S7: 146487 | T7: 143301 | U7: 156935 | V7: 165053 | W7: 168575 | X7: 181160 | Y7: 190566 | Z7: 204546 | AA7: 222158 | AB7: 245240 | AC7: 261618 | AD7: 288123 | AE7: 318845 | AF7: 334938 | AG7: 353484 | AH7: 389878 | AI7: 437318 | AJ7: 478534 | AK7: 495060 | AL7: 554587 | AM7: 621570 | AN7: 708962 | AO7: 802508 | AP7: 874675 | AQ7: 964258 | AR7: 994954 | AS7: 1044744 | AT7: 1160092 | AU7: 1243009 | AV7: 1307315 | AW7: 1397010 | AX7: 1514867 | AY7: 1600103 | AZ7: 1682877 | BA7: 1701727 | BB7: 1783873 | BC7: 1845450 | BD7: 1952818 | BE7: 2076882 | BF7: 2206890 | BG7: 2384240 | BH7: 2582624 | BI7: 2771099 | BJ7: 3008384 | BK7: 2991459 | BL7: 2937443 | BM7: 2960801 | BN7: 3098331 | BO7: 3236296 | BP7: 3418905 | BQ7: 3573381 | BR7: 3624655 | BS7: 3382810 | BT7: 3452257 | BU7: 3630646 | BV7: 3839250 | BW7: 3971082 | BX7: 4202500 | BY7: 4439668 | BZ7: 4574390 | CA7: 4804918 | CB7: 5068452 | CC7: 5323470 | CD7: 5351749 | CE7: 5919115 | CF7: 6451907 | CG7: 6796352 | CH7: 7152832
A8: Nonfinancial corporate business; employers' social contributions paid | B8: Currency | C8: 1000000 | D8: USD | E8: Z1/Z1/FA106401001.A | F8: FA106401001.A | H8: 3245 | I8: 4004 | J8: 4026 | K8: 4213 | L8: 5439 | M8: 6755 | N8: 7223 | O8: 7845 | P8: 8215 | Q8: 9375 | R8: 10685 | S8: 11924 | T8: 11908 | U8: 13859 | V8: 15356 | W8: 15941 | X8: 18096 | Y8: 19540 | Z8: 21111 | AA8: 23242 | AB8: 27611 | AC8: 29446 | AD8: 32747 | AE8: 37220 | AF8: 39548 | AG8: 42705 | AH8: 50047 | AI8: 57782 | AJ8: 64401 | AK8: 73960 | AL8: 85419 | AM8: 101758 | AN8: 120538 | AO8: 139893 | AP8: 156018 | AQ8: 175594 | AR8: 188308 | AS8: 205367 | AT8: 228116 | AU8: 247080 | AV8: 270862 | AW8: 288448 | AX8: 310443 | AY8: 334721 | AZ8: 354647 | BA8: 369395 | BB8: 404802 | BC8: 425566 | BD8: 445855 | BE8: 447676 | BF8: 460814 | BG8: 478313 | BH8: 511210 | BI8: 538877 | BJ8: 588944 | BK8: 590846 | BL8: 603009 | BM8: 633506 | BN8: 663004 | BO8: 692450 | BP8: 708596 | BQ8: 733721 | BR8: 739612 | BS8: 712076 | BT8: 714342 | BU8: 742080 | BV8: 769089 | BW8: 802708 | BX8: 830418 | BY8: 864186 | BZ8: 874028 | CA8: 922682 | CB8: 978585 | CC8: 1020795 | CD8: 998345 | CE8: 1079619 | CF8: 1141490 | CG8: 1219275 | CH8: 1298274
A9: Nonfinancial corporate business; taxes on production and imports less subsidies, payable | B9: Currency | C9: 1000000 | D9: USD | E9: Z1/Z1/FA106240101.A | F9: FA106240101.A | H9: 9525 | I9: 11192 | J9: 12378 | K9: 12955 | L9: 14363 | M9: 15365 | N9: 16797 | O9: 17885 | P9: 17317 | Q9: 19160 | R9: 20803 | S9: 22049 | T9: 22306 | U9: 24397 | V9: 26600 | W9: 27620 | X9: 29869 | Y9: 31667 | Z9: 33878 | AA9: 36022 | AB9: 36973 | AC9: 39311 | AD9: 45535 | AE9: 50181 | AF9: 54249 | AG9: 59516 | AH9: 63665 | AI9: 70075 | AJ9: 74430 | AK9: 80194 | AL9: 86668 | AM9: 94631 | AN9: 102726 | AO9: 108757 | AP9: 121536 | AQ9: 146651 | AR9: 152915 | AS9: 168018 | AT9: 185003 | AU9: 196579 | AV9: 204565 | AW9: 216840 | AX9: 233839 | AY9: 248156 | AZ9: 263528 | BA9: 285729 | BB9: 302501 | BC9: 319322 | BD9: 350748 | BE9: 358668 | BF9: 371682 | BG9: 388899 | BH9: 402904 | BI9: 424637 | BJ9: 449869 | BK9: 441508 | BL9: 467032 | BM9: 491121 | BN9: 531742 | BO9: 575663 | BP9: 611791 | BQ9: 631280 | BR9: 637442 | BS9: 608504 | BT9: 638215 | BU9: 670849 | BV9: 695083 | BW9: 726675 | BX9: 754669 | BY9: 771216 | BZ9: 785160 | CA9: 825907 | CB9: 873480 | CC9: 928991 | CD9: 507876 | CE9: 702594 | CF9: 1104840 | CG9: 1115707 | CH9: 1165975
A10: Nonfinancial corporate business; operating surplus, net | B10: Currency | C10: 1000000 | D10: USD | E10: Z1/Z1/FA106402101.A | F10: FA106402101.A | H10: 16641 | I10: 22780 | J10: 29076 | K10: 26426 | L10: 33268 | M10: 37834 | N10: 35736 | O10: 36232 | P10: 35177 | Q10: 45419 | R10: 44303 | S10: 43706 | T10: 39238 | U10: 49776 | V10: 47915 | W10: 49723 | X10: 57859 | Y10: 64717 | Z10: 71736 | AA10: 83492 | AB10: 90865 | AC10: 89366 | AD10: 96450 | AE10: 94896 | AF10: 84897 | AG10: 97659 | AH10: 112172 | AI10: 125483 | AJ10: 121293 | AK10: 141341 | AL10: 169722 | AM10: 196885 | AN10: 221555 | AO10: 226726 | AP10: 223441 | AQ10: 273482 | AR10: 264806 | AS10: 303156 | AT10: 373838 | AU10: 383523 | AV10: 364295 | AW10: 404914 | AX10: 456562 | AY10: 457077 | AZ10: 457023 | BA10: 450832 | BB10: 449070 | BC10: 488756 | BD10: 584812 | BE10: 637427 | BF10: 702809 | BG10: 763291 | BH10: 744345 | BI10: 754597 | BJ10: 726139 | BK10: 664886 | BL10: 731046 | BM10: 830127 | BN10: 988613 | BO10: 1157510 | BP10: 1297837 | BQ10: 1271769 | BR10: 1217246 | BS10: 1086020 | BT10: 1358883 | BU10: 1444028 | BV10: 1572717 | BW10: 1634506 | BX10: 1711434 | BY10: 1738998 | BZ10: 1671794 | CA10: 1708533 | CB10: 1835143 | CC10: 1861863 | CD10: 1912578 | CE10: 2555943 | CF10: 2736706 | CG10: 2877736 | CH10: 2957761
A11: Nonfinancial corporate business; net national income/balance of primary incomes, net | B11: Currency | C11: 1000000 | D11: USD | E11: Z1/Z1/FA106140005.A | F11: FA106140005.A | H11: 11691 | I11: 17178 | J11: 22790 | K11: 19666 | L11: 25268 | M11: 30255 | N11: 28124 | O11: 28127 | P11: 26579 | Q11: 36064 | R11: 34389 | S11: 33101 | T11: 28071 | U11: 37817 | V11: 35323 | W11: 36268 | X11: 42907 | Y11: 48847 | Z11: 53720 | AA11: 62726 | AB11: 68620 | AC11: 65110 | AD11: 69524 | AE11: 65045 | AF11: 51846 | AG11: 63700 | AH11: 77044 | AI11: 88821 | AJ11: 77041 | AK11: 92162 | AL11: 119258 | AM11: 140639 | AN11: 160201 | AO11: 163211 | AP11: 138611 | AQ11: 161725 | AR11: 142286 | AS11: 178382 | AT11: 235069 | AU11: 238455 | AV11: 203986 | AW11: 241352 | AX11: 261424 | AY11: 224411 | AZ11: 215473 | BA11: 216450 | BB11: 224043 | BC11: 271234 | BD11: 343279 | BE11: 384733 | BF11: 438728 | BG11: 471190 | BH11: 407932 | BI11: 442018 | BJ11: 381340 | BK11: 307053 | BL11: 371434 | BM11: 471072 | BN11: 573456 | BO11: 778298 | BP11: 780237 | BQ11: 692178 | BR11: 572400 | BS11: 603015 | BT11: 882410 | BU11: 889300 | BV11: 911927 | BW11: 1000160 | BX11: 981985 | BY11: 926527 | BZ11: 800094 | CA11: 833682 | CB11: 871002 | CC11: 865254 | CD11: 858010 | CE11: 1114471 | CF11: 1209740 | CG11: 1316676 | CH11: 1302951
A12: Nonfinancial corporate business; operating surplus, net | B12: Currency | C12: 1000000 | D12: USD | E12: Z1/Z1/FA106402101.A | F12: FA106402101.A | H12: 16641 | I12: 22780 | J12: 29076 | K12: 26426 | L12: 33268 | M12: 37834 | N12: 35736 | O12: 36232 | P12: 35177 | Q12: 45419 | R12: 44303 | S12: 43706 | T12: 39238 | U12: 49776 | V12: 47915 | W12: 49723 | X12: 57859 | Y12: 64717 | Z12: 71736 | AA12: 83492 | AB12: 90865 | AC12: 89366 | AD12: 96450 | AE12: 94896 | AF12: 84897 | AG12: 97659 | AH12: 112172 | AI12: 125483 | AJ12: 121293 | AK12: 141341 | AL12: 169722 | AM12: 196885 | AN12: 221555 | AO12: 226726 | AP12: 223441 | AQ12: 273482 | AR12: 264806 | AS12: 303156 | AT12: 373838 | AU12: 383523 | AV12: 364295 | AW12: 404914 | AX12: 456562 | AY12: 457077 | AZ12: 457023 | BA12: 450832 | BB12: 449070 | BC12: 488756 | BD12: 584812 | BE12: 637427 | BF12: 702809 | BG12: 763291 | BH12: 744345 | BI12: 754597 | BJ12: 726139 | BK12: 664886 | BL12: 731046 | BM12: 830127 | BN12: 988613 | BO12: 1157510 | BP12: 1297837 | BQ12: 1271769 | BR12: 1217246 | BS12: 1086020 | BT12: 1358883 | BU12: 1444028 | BV12: 1572717 | BW12: 1634506 | BX12: 1711434 | BY12: 1738998 | BZ12: 1671794 | CA12: 1708533 | CB12: 1835143 | CC12: 1861863 | CD12: 1912578 | CE12: 2555943 | CF12: 2736706 | CG12: 2877736 | CH12: 2957761
A13: Nonfinancial corporate business; property income (received) | B13: Currency | C13: 1000000 | D13: USD | E13: Z1/Z1/FA106150105.A | F13: FA106150105.A | H13: 3029 | I13: 3302 | J13: 3773 | K13: 3705 | L13: 4240 | M13: 4728 | N13: 5002 | O13: 5062 | P13: 5010 | Q13: 5890 | R13: 6540 | S13: 7002 | T13: 6608 | U13: 7312 | V13: 8140 | W13: 8557 | X13: 9256 | Y13: 10170 | Z13: 10840 | AA13: 11301 | AB13: 12026 | AC13: 13110 | AD13: 15463 | AE13: 18898 | AF13: 21655 | AG13: 23483 | AH13: 27344 | AI13: 39185 | AJ13: 51529 | AK13: 47922 | AL13: 54265 | AM13: 61536 | AN13: 72774 | AO13: 100173 | AP13: 116351 | AQ13: 132530 | AR13: 141224 | AS13: 146984 | AT13: 165334 | AU13: 174018 | AV13: 181637 | AW13: 191899 | AX13: 220401 | AY13: 245480 | AZ13: 255378 | BA13: 247085 | BB13: 234416 | BC13: 233650 | BD13: 248463 | BE13: 298604 | BF13: 329942 | BG13: 364127 | BH13: 340182 | BI13: 373621 | BJ13: 448050 | BK13: 405929 | BL13: 392816 | BM13: 414664 | BN13: 476352 | BO13: 609840 | BP13: 646915 | BQ13: 676494 | BR13: 613293 | BS13: 556944 | BT13: 573129 | BU13: 545374 | BV13: 528000 | BW13: 536967 | BX13: 536996 | BY13: 543695 | BZ13: 520569 | CA13: 595782 | CB13: 913329 | CC13: 767967 | CD13: 538199 | CE13: 486986 | CF13: 551239 | CG13: 668119 | CH13: 778827
A14: Nonfinancial corporate business; interest received | B14: Currency | C14: 1000000 | D14: USD | E14: Z1/Z1/FA106130101.A | F14: FA106130101.A | H14: 1020 | I14: 994 | J14: 1060 | K14: 1122 | L14: 1279 | M14: 1422 | N14: 1580 | O14: 1684 | P14: 1672 | Q14: 1948 | R14: 2232 | S14: 2488 | T14: 2432 | U14: 2852 | V14: 3264 | W14: 3324 | X14: 3608 | Y14: 4080 | Z14: 4436 | AA14: 4644 | AB14: 5316 | AC14: 5996 | AD14: 7308 | AE14: 9856 | AF14: 11872 | AG14: 12580 | AH14: 13912 | AI14: 18112 | AJ14: 23792 | AK14: 27656 | AL14: 28292 | AM14: 31872 | AN14: 39200 | AO14: 51740 | AP14: 67212 | AQ14: 89624 | AR14: 97616 | AS14: 98088 | AT14: 110776 | AU14: 122984 | AV14: 131756 | AW14: 133772 | AX14: 150720 | AY14: 178412 | AZ14: 182452 | BA14: 179912 | BB14: 164308 | BC14: 155000 | BD14: 169404 | BE14: 193012 | BF14: 215488 | BG14: 235788 | BH14: 226228 | BI14: 240360 | BJ14: 284136 | BK14: 267764 | BL14: 244236 | BM14: 231876 | BN14: 249964 | BO14: 300012 | BP14: 368216 | BQ14: 373644 | BR14: 293484 | BS14: 206916 | BT14: 172316 | BU14: 172844 | BV14: 159028 | BW14: 147172 | BX14: 147532 | BY14: 150800 | BZ14: 151404 | CA14: 166436 | CB14: 188788 | CC14: 240244 | CD14: 172351 | CE14: 158354 | CF14: 243274 | CG14: 426073 | CH14: 471894
... A24: Nonfinancial corporate business; other current transfers paid | B24: Currency | C24: 1000000 | D24: USD | E24: Z1/Z1/FA106403001.A | F24: FA106403001.A | H24: 475 | I24: 572 | J24: 605 | K24: 588 | L24: 601 | M24: 727 | N24: 824 | O24: 959 | P24: 852 | Q24: 980 | R24: 1036 | S24: 1098 | T24: 1173 | U24: 1255 | V24: 1267 | W24: 1421 | X24: 1580 | Y24: 1595 | Z24: 1871 | AA24: 2103 | AB24: 2618 | AC24: 2703 | AD24: 2937 | AE24: 3047 | AF24: 3183 | AG24: 3593 | AH24: 3885 | AI24: 4504 | AJ24: 3739 | AK24: 4717 | AL24: 6701 | AM24: 8707 | AN24: 9203 | AO24: 9027 | AP24: 9636 | AQ24: 10659 | AR24: 8119 | AS24: 9953 | AT24: 10934 | AU24: 15363 | AV24: 26919 | AW24: 29656 | AX24: 27037 | AY24: 23481 | AZ24: 24867 | BA24: 26093 | BB24: 30693 | BC24: 29521 | BD24: 34651 | BE24: 30164 | BF24: 37318 | BG24: 38488 | BH24: 34106 | BI24: 45602 | BJ24: 45440 | BK24: 55201 | BL24: 51994 | BM24: 61635 | BN24: 62539 | BO24: 79314 | BP24: 68525 | BQ24: 59077 | BR24: 46320 | BS24: 60531 | BT24: 71809 | BU24: 79885 | BV24: 82372 | BW24: 84166 | BX24: 82241 | BY24: 99763 | BZ24: 73340 | CA24: 92900 | CB24: 97765 | CC24: 89471 | CD24: 90877 | CE24: 122876 | CF24: 119058 | CG24: 97823 | CH24: 111445
A25: Nonfinancial corporate business; disposable income, net; net saving (IMA) | B25: Currency | C25: 1000000 | D25: USD | E25: Z1/Z1/FA106012095.A | F25: FA106012095.A | H25: 2643 | I25: 5829 | J25: 10504 | K25: 9816 | L25: 7903 | M25: 8424 | N25: 9623 | O25: 8799 | P25: 10199 | Q25: 14969 | R25: 13434 | S25: 13022 | T25: 10834 | U25: 15880 | V25: 14914 | W25: 15428 | X25: 20736 | Y25: 24498 | Z25: 27961 | AA25: 33486 | AB25: 36510 | AC25: 34579 | AD25: 33053 | AE25: 28654 | AF25: 21377 | AG25: 30112 | AH25: 39364 | AI25: 43908 | AJ25: 30453 | AK25: 45537 | AL25: 59062 | AM25: 71354 | AN25: 83442 | AO25: 83565 | AP25: 60772 | AQ25: 85072 | AR25: 85404 | AS25: 106708 | AT25: 148195 | AU25: 152009 | AV25: 100829 | AW25: 117466 | AX25: 130434 | AY25: 99722 | AZ25: 92152 | BA25: 101759 | BB25: 98920 | BC25: 133672 | BD25: 176272 | BE25: 214246 | BF25: 248481 | BG25: 271342 | BH25: 215158 | BI25: 229952 | BJ25: 170814 | BK25: 145642 | BL25: 228365 | BM25: 282945 | BN25: 331683 | BO25: 436442 | BP25: 415631 | BQ25: 355481 | BR25: 318875 | BS25: 381048 | BT25: 606817 | BU25: 600196 | BV25: 583751 | BW25: 652038 | BX25: 609116 | BY25: 542816 | BZ25: 464695 | CA25: 526967 | CB25: 560292 | CC25: 578994 | CD25: 555134 | CE25: 647812 | CF25: 618860 | CG25: 731994 | CH25: 651303 | CJ25: 2643 | CK25: 5829 | CL25: 10504 | CM25: 9816 | CN25: 7903 | CO25: 8424 | CP25: 9623 | CQ25: 8799 | CR25: 10199 | CS25: 14969 | CT25: 13434 | CU25: 13022 | CV25: 10834 | CW25: 15880 | CX25: 14914 | CY25: 15428 | CZ25: 20736 | DA25: 24498 | DB25: 27961 | DC25: 33486 | DD25: 36510 | DE25: 34579 | DF25: 33053 | DG25: 28654 | DH25: 21377 | DI25: 30112 | DJ25: 39364 | DK25: 43908 | DL25: 30453 | DM25: 45537 | DN25: 59062 | DO25: 71354 | DP25: 83442 | DQ25: 83565 | DR25: 60772 | DS25: 85072 | DT25: 85404 | DU25: 106708 | DV25: 148195 | DW25: 152009 | DX25: 100829 | DY25: 117466 | DZ25: 130434 | EA25: 99722 | EB25: 92152 | EC25: 101759 | ED25: 98920 | EE25: 133672 | EF25: 176272 | EG25: 214246 | EH25: 248481 | EI25: 271342 | EJ25: 215158 | EK25: 229952 | EL25: 170814 | EM25: 145642 | EN25: 228365 | EO25: 282945 | EP25: 331683 | EQ25: 436442 | ER25: 415631 | ES25: 355481 | ET25: 318875 | EU25: 381048 | EV25: 606817 | EW25: 600196 | EX25: 583751 | EY25: 652038 | EZ25: 609116 | FA25: 542816 | FB25: 464695 | FC25: 526967 | FD25: 560292 | FE25: 578994 | FF25: 555134 | FG25: 647812 | FH25: 618860 | FI25: 731994 | FJ25: 651303
A26: Nonfinancial corporate business; net saving excluding foreign earnings retained abroad less net capital transfers paid | B26: Currency | C26: 1000000 | D26: USD | E26: Z1/Z1/FA106006385.A | F26: FA106006385.A | H26: 2643 | I26: 5829 | J26: 10504 | K26: 9816 | L26: 7903 | M26: 8424 | N26: 9623 | O26: 8799 | P26: 10199 | Q26: 14977 | R26: 13454 | S26: 13046 | T26: 10862 | U26: 15929 | V26: 15007 | W26: 15551 | X26: 20862 | Y26: 24586 | Z26: 28042 | AA26: 33567 | AB26: 36593 | AC26: 34664 | AD26: 33165 | AE26: 28731 | AF26: 21502 | AG26: 30251 | AH26: 39558 | AI26: 44065 | AJ26: 30676 | AK26: 45778 | AL26: 59260 | AM26: 71515 | AN26: 83606 | AO26: 83808 | AP26: 61048 | AQ26: 85274 | AR26: 85603 | AS26: 106746 | AT26: 148203 | AU26: 152013 | AV26: 100829 | AW26: 117466 | AX26: 130434 | AY26: 100906 | AZ26: 92152 | BA26: 101759 | BB26: 105875 | BC26: 134275 | BD26: 179530 | BE26: 214690 | BF26: 248481 | BG26: 271342 | BH26: 215158 | BI26: 230830 | BJ26: 170814 | BK26: 158174 | BL26: 228365 | BM26: 283036 | BN26: 338341 | BO26: 451959 | BP26: 415659 | BQ26: 355515 | BR26: 322561 | BS26: 342750 | BT26: 585901 | BU26: 606625 | BV26: 600749 | BW26: 657750 | BX26: 615792 | BY26: 546058 | BZ26: 462062 | CA26: 326143 | CB26: 566488 | CC26: 591425 | CD26: 541501 | CE26: 663188 | CF26: 588607 | CG26: 732776 | CH26: 668053
A27: Nonfinancial corporate business; disposable income, net; net saving (IMA) | B27: Currency | C27: 1000000 | D27: USD | E27: Z1/Z1/FA106012095.A | F27: FA106012095.A | H27: 2643 | I27: 5829 | J27: 10504 | K27: 9816 | L27: 7903 | M27: 8424 | N27: 9623 | O27: 8799 | P27: 10199 | Q27: 14969 | R27: 13434 | S27: 13022 | T27: 10834 | U27: 15880 | V27: 14914 | W27: 15428 | X27: 20736 | Y27: 24498 | Z27: 27961 | AA27: 33486 | AB27: 36510 | AC27: 34579 | AD27: 33053 | AE27: 28654 | AF27: 21377 | AG27: 30112 | AH27: 39364 | AI27: 43908 | AJ27: 30453 | AK27: 45537 | AL27: 59062 | AM27: 71354 | AN27: 83442 | AO27: 83565 | AP27: 60772 | AQ27: 85072 | AR27: 85404 | AS27: 106708 | AT27: 148195 | AU27: 152009 | AV27: 100829 | AW27: 117466 | AX27: 130434 | AY27: 99722 | AZ27: 92152 | BA27: 101759 | BB27: 98920 | BC27: 133672 | BD27: 176272 | BE27: 214246 | BF27: 248481 | BG27: 271342 | BH27: 215158 | BI27: 229952 | BJ27: 170814 | BK27: 145642 | BL27: 228365 | BM27: 282945 | BN27: 331683 | BO27: 436442 | BP27: 415631 | BQ27: 355481 | BR27: 318875 | BS27: 381048 | BT27: 606817 | BU27: 600196 | BV27: 583751 | BW27: 652038 | BX27: 609116 | BY27: 542816 | BZ27: 464695 | CA27: 526967 | CB27: 560292 | CC27: 578994 | CD27: 555134 | CE27: 647812 | CF27: 618860 | CG27: 731994 | CH27: 651303
A28: Nonfinancial corporate business; net capital transfers paid | B28: Currency | C28: 1000000 | D28: USD | E28: Z1/Z1/FA105440005.A | F28: FA105440005.A | H28: 0 | I28: 0 | J28: 0 | K28: 0 | L28: 0 | M28: 0 | N28: 0 | O28: 0 | P28: 0 | Q28: -8 | R28: -20 | S28: -24 | T28: -28 | U28: -49 | V28: -93 | W28: -123 | X28: -126 | Y28: -88 | Z28: -81 | AA28: -81 | AB28: -83 | AC28: -85 | AD28: -112 | AE28: -77 | AF28: -125 | AG28: -139 | AH28: -194 | AI28: -157 | AJ28: -223 | AK28: -241 | AL28: -198 | AM28: -161 | AN28: -164 | AO28: -243 | AP28: -276 | AQ28: -202 | AR28: -199 | AS28: -38 | AT28: -8 | AU28: -4 | AV28: 0 | AW28: 0 | AX28: 0 | AY28: -1184 | AZ28: 0 | BA28: 0 | BB28: -6955 | BC28: -603 | BD28: -3258 | BE28: -444 | BF28: 0 | BG28: 0 | BH28: 0 | BI28: -878 | BJ28: 0 | BK28: -12532 | BL28: 0 | BM28: -91 | BN28: -6658 | BO28: -15517 | BP28: -28 | BQ28: -34 | BR28: -3686 | BS28: 38298 | BT28: 20916 | BU28: -6429 | BV28: -16998 | BW28: -5712 | BX28: -6676 | BY28: -3242 | BZ28: 2633 | CA28: 200824 | CB28: -6196 | CC28: -12431 | CD28: 13633 | CE28: -15375 | CF28: 30253 | CG28: -782 | CH28: -16750
A29: Nonfinancial corporate business; capital formation, net (includes equity REIT residential structures) (IMA) | B29: Currency | C29: 1000000 | D29: USD | E29: Z1/Z1/FA105050985.A | F29: FA105050985.A | H29: 11430 | I29: 8871 | J29: 10765 | K29: 3066 | L29: 11404 | M29: 16357 | N29: 10608 | O29: 11031 | P29: 6545 | Q29: 15135 | R29: 18291 | S29: 14768 | T29: 5285 | U29: 14656 | V29: 14266 | W29: 12792 | X29: 17213 | Y29: 18340 | Z29: 22359 | AA29: 31812 | AB29: 43590 | AC29: 38108 | AD29: 39541 | AE29: 43415 | AF29: 35517 | AG29: 36514 | AH29: 45585 | AI29: 62896 | AJ29: 70037 | AK29: 28093 | AL29: 61466 | AM29: 77722 | AN29: 105439 | AO29: 117665 | AP29: 104056 | AQ29: 138889 | AR29: 80079 | AS29: 96372 | AT29: 187898 | AU29: 149005 | AV29: 118798 | AW29: 118463 | AX29: 119533 | AY29: 135528 | AZ29: 133374 | BA29: 98342 | BB29: 115591 | BC29: 150363 | BD29: 202817 | BE29: 242656 | BF29: 250539 | BG29: 333886 | BH29: 343001 | BI29: 371922 | BJ29: 413094 | BK29: 248786 | BL29: 168669 | BM29: 168493 | BN29: 226709 | BO29: 294555 | BP29: 380557 | BQ29: 367343 | BR29: 305952 | BS29: -36722 | BT29: 180914 | BU29: 257974 | BV29: 382030 | BW29: 393380 | BX29: 491179 | BY29: 542713 | BZ29: 429641 | CA29: 441899 | CB29: 550016 | CC29: 533899 | CD29: 303455 | CE29: 452090 | CF29: 804087 | CG29: 697075 | CH29: 681699
A30: Nonfinancial corporate business; gross fixed capital formation with equity REIT residential structures (IMA) | B30: Currency | C30: 1000000 | D30: USD | E30: Z1/Z1/FA105019085.A | F30: FA105019085.A | H30: 13361 | I30: 17296 | J30: 19102 | K30: 17269 | L30: 18961 | M30: 22779 | N30: 24384 | O30: 26910 | P30: 26662 | Q30: 29403 | R30: 35688 | S30: 38576 | T30: 33721 | U30: 37278 | V30: 40431 | W30: 40444 | X30: 43578 | Y30: 46438 | Z30: 51851 | AA30: 61704 | AB30: 71952 | AC30: 73874 | AD30: 80346 | AE30: 89281 | AF30: 92336 | AG30: 95421 | AH30: 107865 | AI30: 125804 | AJ30: 141538 | AK30: 144183 | AL30: 161805 | AM30: 193035 | AN30: 233472 | AO30: 274491 | AP30: 299969 | AQ30: 343054 | AR30: 349908 | AS30: 348271 | AT30: 405891 | AU30: 431584 | AV30: 426903 | AW30: 422235 | AX30: 450558 | AY30: 489804 | AZ30: 524972 | BA30: 522908 | BB30: 543625 | BC30: 582993 | BD30: 636979 | BE30: 719057 | BF30: 779768 | BG30: 858482 | BH30: 915633 | BI30: 994652 | BJ30: 1101403 | BK30: 1065402 | BL30: 956646 | BM30: 976342 | BN30: 1029817 | BO30: 1156258 | BP30: 1287718 | BQ30: 1384599 | BR30: 1422603 | BS30: 1201475 | BT30: 1251054 | BU30: 1390984 | BV30: 1543068 | BW30: 1590872 | BX30: 1767580 | BY30: 1801861 | BZ30: 1826792 | CA30: 1919803 | CB30: 2080197 | CC30: 2127035 | CD30: 2051296 | CE30: 2236870 | CF30: 2548806 | CG30: 2810202 | CH30: 2914282
A31: Nonfinancial corporate business; consumption of fixed capital, structures, equipment, and intellectual property products, including equity REIT residential structures (NIPA basis) | B31: Currency | C31: 1000000 | D31: USD | E31: Z1/Z1/FA106300003.A | F31: FA106300003.A | H31: 7752 | I31: 9476 | J31: 11120 | K31: 12008 | L31: 12848 | M31: 14636 | N31: 15581 | O31: 16729 | P31: 17724 | Q31: 18913 | R31: 21356 | S31: 23757 | T31: 25496 | U31: 26689 | V31: 27561 | W31: 28564 | X31: 29824 | Y31: 31340 | Z31: 33253 | AA31: 35829 | AB31: 39392 | AC31: 43452 | AD31: 48092 | AE31: 53485 | AF31: 59260 | AG31: 64733 | AH31: 70189 | AI31: 78181 | AJ31: 91385 | AK31: 107725 | AL31: 118273 | AM31: 132560 | AN31: 150153 | AO31: 172444 | AP31: 198860 | AQ31: 229084 | AR31: 253881 | AS31: 264616 | AT31: 278952 | AU31: 298976 | AV31: 317873 | AW31: 334692 | AX31: 358201 | AY31: 380160 | AZ31: 402625 | BA31: 423557 | BB31: 436253 | BC31: 455845 | BD31: 482344 | BE31: 520836 | BF31: 554165 | BG31: 594613 | BH31: 634096 | BI31: 679077 | BJ31: 737452 | BK31: 781461 | BL31: 805023 | BM31: 818192 | BN31: 851953 | BO31: 913611 | BP31: 984446 | BQ31: 1047220 | BR31: 1108750 | BS31: 1114627 | BT31: 1123496 | BU31: 1173464 | BV31: 1234809 | BW31: 1282796 | BX31: 1352680 | BY31: 1408264 | BZ31: 1441019 | CA31: 1509413 | CB31: 1582147 | CC31: 1664697 | CD31: 1728115 | CE31: 1815454 | CF31: 2010486 | CG31: 2154291 | CH31: 2274356
A32: Nonfinancial corporate business; acquisition of nonproduced nonfinancial assets (net) (IMA) | B32: Currency | C32: 1000000 | D32: USD | E32: Z1/Z1/FA105420095.A | F32: FA105420095.A | H32: -70 | I32: -90 | J32: -116 | K32: -199 | L32: -269 | M32: -272 | N32: -252 | O32: -329 | P32: -366 | Q32: -616 | R32: -683 | S32: -704 | T32: -776 | U32: -1089 | V32: -654 | W32: -727 | X32: -841 | Y32: -795 | Z32: -920 | AA32: -773 | AB32: -962 | AC32: -91 | AD32: 587 | AE32: -332 | AF32: 16 | AG32: 62 | AH32: 330 | AI32: 2805 | AJ32: 5238 | AK32: -17 | AL32: 1981 | AM32: 1061 | AN32: 206 | AO32: 2385 | AP32: 3578 | AQ32: 5042 | AR32: 3345 | AS32: 4702 | AT32: 3573 | AU32: 685 | AV32: 2242 | AW32: -484 | AX32: -770 | AY32: -343 | AZ32: -653 | BA32: -1736 | BB32: -1745 | BC32: -1700 | BD32: -1711 | BE32: 5936 | BF32: 3417 | BG32: 7861 | BH32: 4316 | BI32: -847 | BJ32: -1171 | BK32: -886 | BL32: -2641 | BM32: -2190 | BN32: -2012 | BO32: 785 | BP32: 13256 | BQ32: 163 | BR32: 17901 | BS32: 6610 | BT32: -1080 | BU32: -1014 | BV32: 246 | BW32: 1378 | BX32: 1586 | BY32: 29473 | BZ32: 7265 | CA32: 166 | CB32: -1022 | CC32: -656 | CD32: 59 | CE32: 6644 | CF32: 105434 | CG32: -2728 | CH32: -3220
A33: Nonfinancial corporate business; inventories including IVA | B33: Currency | C33: 1000000 | D33: USD | E33: Z1/Z1/FA105020005.A | F33: FA105020005.A | H33: 5891 | I33: 1141 | J33: 2899 | K33: -1996 | L33: 5560 | M33: 8486 | N33: 2057 | O33: 1179 | P33: -2027 | Q33: 5261 | R33: 4642 | S33: 653 | T33: -2164 | U33: 5156 | V33: 2050 | W33: 1639 | X33: 4300 | Y33: 4037 | Z33: 4681 | AA33: 6710 | AB33: 11992 | AC33: 7777 | AD33: 6700 | AE33: 7951 | AF33: 2425 | AG33: 5764 | AH33: 7579 | AI33: 12468 | AJ33: 14646 | AK33: -8348 | AL33: 15953 | AM33: 16186 | AN33: 21914 | AO33: 13233 | AP33: -631 | AQ33: 19877 | AR33: -19293 | AS33: 8015 | AT33: 57386 | AU33: 15712 | AV33: 7526 | AW33: 31404 | AX33: 27946 | AY33: 26227 | AZ33: 11680 | BA33: 727 | BB33: 9964 | BC33: 24915 | BD33: 49893 | BE33: 38499 | BF33: 21519 | BG33: 62156 | BH33: 57148 | BI33: 57194 | BJ33: 50314 | BK33: -34269 | BL33: 19687 | BM33: 12533 | BN33: 50857 | BO33: 51123 | BP33: 64029 | BQ33: 29801 | BR33: -25802 | BS33: -130180 | BT33: 54436 | BU33: 41468 | BV33: 73525 | BW33: 83926 | BX33: 74693 | BY33: 119643 | BZ33: 36603 | CA33: 31343 | CB33: 52988 | CC33: 72217 | CD33: -19785 | CE33: 24031 | CF33: 160332 | CG33: 43891 | CH33: 44993
A34: Nonfinancial corporate business; net lending (+) or borrowing (-) (capital account), includes statistical discrepancy | B34: Currency | C34: 1000000 | D34: USD | E34: Z1/Z1/FA105000905.A | F34: FA105000905.A | H34: -8787 | I34: -3042 | J34: -261 | K34: 6750 | L34: -3501 | M34: -7933 | N34: -985 | O34: -2232 | P34: 3654 | Q34: -158 | R34: -4837 | S34: -1723 | T34: 5577 | U34: 1273 | V34: 741 | W34: 2759 | X34: 3649 | Y34: 6246 | Z34: 5683 | AA34: 1755 | AB34: -6997 | AC34: -3445 | AD34: -6376 | AE34: -14685 | AF34: -14015 | AG34: -6263 | AH34: -6028 | AI34: -18831 | AJ34: -39361 | AK34: 17685 | AL34: -2206 | AM34: -6207 | AN34: -21833 | AO34: -33857 | AP34: -43009 | AQ34: -53615 | AR34: 5524 | AS34: 10374 | AT34: -39695 | AU34: 3008 | AV34: -17969 | AW34: -997 | AX34: 10901 | AY34: -34622 | AZ34: -41222 | BA34: 3417 | BB34: -9716 | BC34: -16088 | BD34: -23287 | BE34: -27966 | BF34: -2058 | BG34: -62544 | BH34: -127843 | BI34: -141093 | BJ34: -242280 | BK34: -90612 | BL34: 59696 | BM34: 114543 | BN34: 111632 | BO34: 157404 | BP34: 35102 | BQ34: -11829 | BR34: 16609 | BS34: 379472 | BT34: 404987 | BU34: 348651 | BV34: 218719 | BW34: 264370 | BX34: 124613 | BY34: 3345 | BZ34: 32421 | CA34: -115756 | CB34: 16472 | CC34: 57527 | CD34: 238046 | CE34: 211097 | CF34: -215480 | CG34: 35701 | CH34: -13646 | CJ34: -8787 | CK34: -3042 | CL34: -261 | CM34: 6750 | CN34: -3501 | CO34: -7933 | CP34: -985 | CQ34: -2232 | CR34: 3654 | CS34: -158 | CT34: -4837 | CU34: -1723 | CV34: 5577 | CW34: 1273 | CX34: 741 | CY34: 2759 | CZ34: 3649 | DA34: 6246 | DB34: 5683 | DC34: 1755 | DD34: -6997 | DE34: -3445 | DF34: -6376 | DG34: -14685 | DH34: -14015 | DI34: -6263 | DJ34: -6028 | DK34: -18831 | DL34: -39361 | DM34: 17685 | DN34: -2206 | DO34: -6207 | DP34: -21833 | DQ34: -33857 | DR34: -43009 | DS34: -53615 | DT34: 5524 | DU34: 10374 | DV34: -39695 | DW34: 3008 | DX34: -17969 | DY34: -997 | DZ34: 10901 | EA34: -34622 | EB34: -41222 | EC34: 3417 | ED34: -9716 | EE34: -16088 | EF34: -23287 | EG34: -27966 | EH34: -2058 | EI34: -62544 | EJ34: -127843 | EK34: -141093 | EL34: -242280 | EM34: -90612 | EN34: 59696 | EO34: 114543 | EP34: 111632 | EQ34: 157404 | ER34: 35102 | ES34: -11829 | ET34: 16609 | EU34: 379472 | EV34: 404987 | EW34: 348651 | EX34: 218719 | EY34: 264370 | EZ34: 124613 | FA34: 3345 | FB34: 32421 | FC34: -115756 | FD34: 16472 | FE34: 57527 | FF34: 238046 | FG34: 211097 | FH34: -215480 | FI34: 35701 | FJ34: -13646
A35: Nonfinancial corporate business; total financial assets | B35: Currency | C35: 1000000 | D35: USD | E35: Z1/Z1/FA104090005.A | F35: FA104090005.A | H35: -1605 | I35: 8725 | J35: 5477 | K35: 3902 | L35: 16784 | M35: 8027 | N35: 5418 | O35: 3037 | P35: 5498 | Q35: 17382 | R35: 5031 | S35: 4561 | T35: 11530 | U35: 15097 | V35: 2841 | W35: 13351 | X35: 11969 | Y35: 12015 | Z35: 12874 | AA35: 26110 | AB35: 16496 | AC35: 14314 | AD35: 32126 | AE35: 38478 | AF35: 22925 | AG35: 40171 | AH35: 67549 | AI35: 90570 | AJ35: 66905 | AK35: 20395 | AL35: 75626 | AM35: 108248 | AN35: 133781 | AO35: 169745 | AP35: 144214 | AQ35: 204946 | AR35: 93855 | AS35: 155170 | AT35: 275376 | AU35: 227567 | AV35: 140261 | AW35: 233904 | AX35: 351330 | AY35: 165957 | AZ35: 126405 | BA35: 51885 | BB35: 147943 | BC35: 324708 | BD35: 277954 | BE35: 347402 | BF35: 392895 | BG35: 157919 | BH35: 743475 | BI35: 958452 | BJ35: 1484056 | BK35: 368570 | BL35: 377680 | BM35: -73678 | BN35: 721478 | BO35: 934913 | BP35: 623577 | BQ35: 1050993 | BR35: -331186 | BS35: 237406 | BT35: 554561 | BU35: 376701 | BV35: 321406 | BW35: 727804 | BX35: 686147 | BY35: 1143273 | BZ35: 960331 | CA35: 578845 | CB35: 855074 | CC35: 2406351 | CD35: 436586 | CE35: 1343073 | CF35: 2683038 | CG35: 1457871 | CH35: 329417
A36: Nonfinancial corporate business; total currency and deposits; asset | B36: Currency | C36: 1000000 | D36: USD | E36: Z1/Z1/FA104000005.A | F36: FA104000005.A | H36: 578 | I36: 1915 | J36: 386 | K36: 1042 | L36: 1366 | M36: 1671 | N36: 766 | O36: -52 | P36: 2023 | Q36: 824 | R36: -283 | S36: 27 | T36: 1977 | U36: -1304 | V36: 563 | W36: 4271 | X36: 4345 | Y36: -509 | Z36: 661 | AA36: 2321 | AB36: -968 | AC36: 3695 | AD36: 2620 | AE36: -227 | AF36: 2257 | AG36: 3120 | AH36: 5676 | AI36: 7267 | AJ36: 4792 | AK36: 14637 | AL36: 10165 | AM36: 12670 | AN36: 11655 | AO36: 10053 | AP36: 3811 | AQ36: -8347 | AR36: 16624 | AS36: 32285 | AT36: 11166 | AU36: 25932 | AV36: 17691 | AW36: 7127 | AX36: 13376 | AY36: 8 | AZ36: -792 | BA36: 10063 | BB36: -8058 | BC36: 34049 | BD36: 13046 | BE36: 7622 | BF36: 42009 | BG36: 19112 | BH36: 20035 | BI36: 74805 | BJ36: 62941 | BK36: -52873 | BL36: 2284 | BM36: 131895 | BN36: 54306 | BO36: 120420 | BP36: -81173 | BQ36: -75742 | BR36: -267239 | BS36: 268383 | BT36: 145313 | BU36: 41780 | BV36: 58708 | BW36: 152072 | BX36: 22850 | BY36: 38992 | BZ36: 178164 | CA36: 66840 | CB36: 146548 | CC36: 179582 | CD36: 525126 | CE36: 302308 | CF36: -2575 | CG36: 98151 | CH36: 231895
A37: Nonfinancial corporate business; checkable deposits and currency; asset | B37: Currency | C37: 1000000 | D37: USD | E37: Z1/Z1/FA103020005.A | F37: FA103020005.A | H37: 543 | I37: 1932 | J37: 427 | K37: 1042 | L37: 1319 | M37: 1637 | N37: 782 | O37: -91 | P37: 1779 | Q37: 953 | R37: -292 | S37: 34 | T37: 1059 | U37: -887 | V37: -940 | W37: 3083 | X37: 3570 | Y37: -987 | Z37: -426 | AA37: 311 | AB37: -682 | AC37: 2532 | AD37: 2714 | AE37: 5591 | AF37: 937 | AG37: -1478 | AH37: 2357 | AI37: 1377 | AJ37: 1151 | AK37: 10500 | AL37: 4695 | AM37: 3750 | AN37: 6298 | AO37: 6058 | AP37: -413 | AQ37: -20986 | AR37: 10345 | AS37: 21554 | AT37: 13125 | AU37: 23016 | AV37: -1716 | AW37: 9653 | AX37: 11754 | AY37: 8520 | AZ37: 5242 | BA37: 5328 | BB37: -5824 | BC37: 19347 | BD37: 7497 | BE37: 2564 | BF37: 1222 | BG37: -10523 | BH37: -15558 | BI37: 29574 | BJ37: 34906 | BK37: -53138 | BL37: -12967 | BM37: 42860 | BN37: 31068 | BO37: 100650 | BP37: -73570 | BQ37: 49001 | BR37: -132246 | BS37: 184646 | BT37: 125671 | BU37: 93132 | BV37: 43884 | BW37: 44367 | BX37: 119720 | BY37: 47098 | BZ37: 156970 | CA37: -44397 | CB37: 250966 | CC37: 140590 | CD37: 444416 | CE37: 265443 | CF37: -54575 | CG37: -79611 | CH37: 280166
A38: Nonfinancial corporate business; total time and savings deposits; asset | B38: Currency | C38: 1000000 | D38: USD | E38: Z1/Z1/FA103030003.A | F38: FA103030003.A | H38: 0 | I38: 0 | J38: 0 | K38: 0 | L38: 0 | M38: 0 | N38: 0 | O38: 0 | P38: 200 | Q38: -100 | R38: 0 | S38: 0 | T38: 900 | U38: -400 | V38: 1500 | W38: 1100 | X38: 900 | Y38: 687 | Z38: 984 | AA38: 2322 | AB38: -390 | AC38: 1079 | AD38: -626 | AE38: -5404 | AF38: 1695 | AG38: 4162 | AH38: 2381 | AI38: 4733 | AJ38: 3841 | AK38: 3666 | AL38: 4653 | AM38: 6673 | AN38: 2726 | AO38: 2232 | AP38: 4608 | AQ38: 9949 | AR38: 8602 | AS38: 6401 | AT38: -850 | AU38: 177 | AV38: 16229 | AW38: 413 | AX38: -3670 | AY38: -1663 | AZ38: -6046 | BA38: 3017 | BB38: -1590 | BC38: 15991 | BD38: 4387 | BE38: 3319 | BF38: 29982 | BG38: 34704 | BH38: 28214 | BI38: 44289 | BJ38: 35466 | BK38: 8777 | BL38: 10181 | BM38: 71477 | BN38: 7678 | BO38: 9904 | BP38: 6632 | BQ38: -125657 | BR38: -109447 | BS38: 76913 | BT38: 6439 | BU38: -39889 | BV38: 13731 | BW38: 39155 | BX38: -87561 | BY38: 10899 | BZ38: 17464 | CA38: -7726 | CB38: 5842 | CC38: 14299 | CD38: 76681 | CE38: 5582 | CF38: 17289 | CG38: 132992 | CH38: -15523
A39: Nonfinancial corporate business; private foreign deposits; asset | B39: Currency | C39: 1000000 | D39: USD | E39: Z1/Z1/FA103091003.A | F39: FA103091003.A | H39: 35 | I39: -17 | J39: -41 | K39: 0 | L39: 47 | M39: 34 | N39: -16 | O39: 39 | P39: 44 | Q39: -29 | R39: 9 | S39: -7 | T39: 18 | U39: -17 | V39: 3 | W39: 88 | X39: -125 | Y39: -209 | Z39: 103 | AA39: -312 | AB39: 104 | AC39: 84 | AD39: 532 | AE39: -414 | AF39: -375 | AG39: 436 | AH39: 938 | AI39: 1157 | AJ39: -200 | AK39: 471 | AL39: 817 | AM39: 2247 | AN39: 2631 | AO39: 1763 | AP39: -384 | AQ39: 2690 | AR39: -2323 | AS39: 4330 | AT39: -1109 | AU39: 2739 | AV39: 3178 | AW39: -2939 | AX39: 5292 | AY39: -6849 | AZ39: 12 | BA39: 1718 | BB39: -644 | BC39: -1289 | BD39: 1162 | BE39: 1739 | BF39: 10805 | BG39: -5069 | BH39: 7379 | BI39: 942 | BJ39: -7431 | BK39: -8512 | BL39: 5070 | BM39: 17558 | BN39: 15560 | BO39: 9866 | BP39: -14235 | BQ39: 914 | BR39: -25546 | BS39: 6824 | BT39: 13203 | BU39: -11463 | BV39: 1093 | BW39: 68550 | BX39: -9309 | BY39: -19005 | BZ39: 3730 | CA39: 118963 | CB39: -110260 | CC39: 24693 | CD39: 4029 | CE39: 31283 | CF39: 34711 | CG39: 44770 | CH39: -32748
A40: Nonfinancial corporate business; debt securities; asset | B40: Currency | C40: 1000000 | D40: USD | E40: Z1/Z1/FA104022005.A | F40: FA104022005.A | H40: -5636 | I40: -354 | J40: 715 | K40: 1962 | L40: 3218 | M40: 922 | N40: -932 | O40: 1794 | P40: -1663 | Q40: 4231 | R40: -4252 | S40: -462 | T40: 557 | U40: 6497 | V40: -5319 | W40: -1210 | X40: -1245 | Y40: 3909 | Z40: -637 | AA40: -1099 | AB40: -1184 | AC40: -1701 | AD40: 2403 | AE40: -1524 | AF40: 1306 | AG40: 5362 | AH40: 1909 | AI40: -2896 | AJ40: 7011 | AK40: 9666 | AL40: 8409 | AM40: -6166 | AN40: -1022 | AO40: -2650 | AP40: 5080 | AQ40: 8840 | AR40: 1223 | AS40: 20328 | AT40: 9224 | AU40: 7158 | AV40: -3256 | AW40: -9145 | AX40: -4371 | AY40: 42847 | AZ40: -27803 | BA40: 28610 | BB40: 24123 | BC40: 10003 | BD40: 4366 | BE40: -8710 | BF40: 896 | BG40: -39513 | BH40: 992 | BI40: 5287 | BJ40: 19180 | BK40: 157 | BL40: 21003 | BM40: 11119 | BN40: 16549 | BO40: 41557 | BP40: -1153 | BQ40: -61393 | BR40: -25205 | BS40: 17690 | BT40: -5264 | BU40: -13931 | BV40: -16164 | BW40: -3485 | BX40: 26055 | BY40: 3617 | BZ40: -3759 | CA40: 30815 | CB40: 22283 | CC40: 69353 | CD40: 37120 | CE40: 38008 | CF40: -5424 | CG40: 12745 | CH40: 11085
A41: Nonfinancial corporate business; commercial paper; asset | B41: Currency | C41: 1000000 | D41: USD | E41: Z1/Z1/FA103069100.A | F41: FA103069100.A | H41: 32 | I41: 97 | J41: 51 | K41: 85 | L41: -122 | M41: -53 | N41: 105 | O41: 9 | P41: 87 | Q41: -74 | R41: 88 | S41: 130 | T41: -225 | U41: 532 | V41: 46 | W41: 301 | X41: 215 | Y41: -335 | Z41: 725 | AA41: -324 | AB41: 1482 | AC41: 1100 | AD41: 1147 | AE41: 2529 | AF41: 1761 | AG41: 1886 | AH41: 2960 | AI41: 641 | AJ41: 4126 | AK41: 3784 | AL41: 2140 | AM41: -1121 | AN41: 122 | AO41: 74 | AP41: -454 | AQ41: -933 | AR41: -251 | AS41: 4240 | AT41: -2446 | AU41: 736 | AV41: -305 | AW41: 4793 | AX41: -1318 | AY41: 643 | AZ41: -455 | BA41: 859 | BB41: 2349 | BC41: 2367 | BD41: -585 | BE41: 1316 | BF41: 11392 | BG41: 4611 | BH41: 3288 | BI41: 8171 | BJ41: 10161 | BK41: 2404 | BL41: 4620 | BM41: 10890 | BN41: 19344 | BO41: 15951 | BP41: 11695 | BQ41: -53207 | BR41: -12176 | BS41: -1299 | BT41: -12476 | BU41: 93 | BV41: -11472 | BW41: -5628 | BX41: 25085 | BY41: 7807 | BZ41: -6866 | CA41: -8803 | CB41: 38399 | CC41: 55442 | CD41: 33285 | CE41: 5399 | CF41: -39380 | CG41: -7038 | CH41: -3276
A42: Nonfinancial corporate business; Treasury securities; asset | B42: Currency | C42: 1000000 | D42: USD | E42: Z1/Z1/FA103061103.A | F42: FA103061103.A | H42: -5729 | I42: -488 | J42: 562 | K42: 1844 | L42: 3173 | M42: 783 | N42: -1006 | O42: 1593 | P42: -1717 | Q42: 3758 | R42: -4563 | S42: -1129 | T42: 503 | U42: 5529 | V42: -5869 | W42: -1656 | X42: -1789 | Y42: 2821 | Z42: -647 | AA42: -1933 | AB42: -1494 | AC42: -2440 | AD42: 345 | AE42: -3313 | AF42: 637 | AG42: 2774 | AH42: -2176 | AI42: -4399 | AJ42: 1351 | AK42: 7413 | AL42: 7283 | AM42: -4991 | AN42: -1486 | AO42: -1598 | AP42: 225 | AQ42: 4955 | AR42: 2359 | AS42: 9133 | AT42: 6323 | AU42: 4635 | AV42: -777 | AW42: -8535 | AX42: -3857 | AY42: 23499 | AZ42: -13783 | BA42: 5777 | BB42: 17163 | BC42: -11750 | BD42: 1981 | BE42: 6278 | BF42: -10003 | BG42: -20249 | BH42: -3231 | BI42: -4195 | BJ42: -1315 | BK42: -1253 | BL42: 14502 | BM42: 2336 | BN42: 324 | BO42: 18103 | BP42: -6654 | BQ42: -7144 | BR42: -7864 | BS42: 12509 | BT42: 6867 | BU42: -7801 | BV42: -2799 | BW42: 1674 | BX42: 1579 | BY42: -3770 | BZ42: 4155 | CA42: 30135 | CB42: -15591 | CC42: 6709 | CD42: 7423 | CE42: 10660 | CF42: 21203 | CG42: 19883 | CH42: 12917
A43: Nonfinancial corporate business; agency- and GSE-backed securities; asset | B43: Currency | C43: 1000000 | D43: USD | E43: Z1/Z1/FA103061703.A | F43: FA103061703.A | H43: 0 | I43: 0 | J43: 0 | K43: 0 | L43: 0 | M43: 0 | N43: 0 | O43: 0 | P43: 0 | Q43: 300 | R43: 100 | S43: 400 | T43: -200 | U43: 600 | V43: -84 | W43: 132 | X43: 27 | Y43: 333 | Z43: -608 | AA43: 238 | AB43: -211 | AC43: -22 | AD43: 429 | AE43: 242 | AF43: -467 | AG43: -298 | AH43: 125 | AI43: 999 | AJ43: 918 | AK43: -538 | AL43: -396 | AM43: -196 | AN43: 101 | AO43: -973 | AP43: 405 | AQ43: 3574 | AR43: -2457 | AS43: 865 | AT43: 1132 | AU43: -1302 | AV43: -1657 | AW43: 288 | AX43: 3374 | AY43: 3148 | AZ43: -5885 | BA43: 1827 | BB43: 3473 | BC43: 10474 | BD43: 816 | BE43: 3546 | BF43: 5059 | BG43: -20509 | BH43: 2638 | BI43: 1807 | BJ43: 3007 | BK43: 2116 | BL43: -656 | BM43: -5653 | BN43: 108 | BO43: 6034 | BP43: -2218 | BQ43: -2381 | BR43: -2621 | BS43: 4169 | BT43: 1974 | BU43: -2161 | BV43: -1334 | BW43: 277 | BX43: 638 | BY43: -1303 | BZ43: 1295 | CA43: 9987 | CB43: -5455 | CC43: 2380 | CD43: 3637 | CE43: 2886 | CF43: 5750 | CG43: 6633 | CH43: 3497
A44: Nonfinancial corporate business; municipal securities; asset | B44: Currency | C44: 1000000 | D44: USD | E44: Z1/Z1/FA103062003.A | F44: FA103062003.A | H44: 61 | I44: 37 | J44: 102 | K44: 33 | L44: 167 | M44: 192 | N44: -31 | O44: 192 | P44: -33 | Q44: 247 | R44: 123 | S44: 137 | T44: 479 | U44: -164 | V44: 588 | W44: 13 | X44: 302 | Y44: 1090 | Z44: -107 | AA44: 920 | AB44: -961 | AC44: -339 | AD44: 482 | AE44: -982 | AF44: -625 | AG44: 1000 | AH44: 1000 | AI44: -137 | AJ44: 616 | AK44: -993 | AL44: -618 | AM44: 142 | AN44: 241 | AO44: -153 | AP44: 4904 | AQ44: 1244 | AR44: 1572 | AS44: 6090 | AT44: 4215 | AU44: 3089 | AV44: -517 | AW44: -5691 | AX44: -2570 | AY44: 15557 | AZ44: -7680 | BA44: 20147 | BB44: 995 | BC44: 8895 | BD44: 1998 | BE44: -19919 | BF44: -5770 | BG44: -3637 | BH44: -1632 | BI44: -746 | BJ44: 6936 | BK44: -2607 | BL44: 2800 | BM44: 3273 | BN44: -3591 | BO44: 300 | BP44: -3982 | BQ44: 1057 | BR44: -3024 | BS44: 937 | BT44: -1866 | BU44: -3410 | BV44: -175 | BW44: -222 | BX44: -1629 | BY44: 1003 | BZ44: -2696 | CA44: -2480 | CB44: 1734 | CC44: 4790 | CD44: -8444 | CE44: 11372 | CF44: 4255 | CG44: -4096 | CH44: 1143
A45: Equity real estate investment trusts; corporate and foreign bonds; asset | B45: Currency | C45: 1000000 | D45: USD | E45: Z1/Z1/FA123063003.A | F45: FA123063003.A | H45: 0 | I45: 0 | J45: 0 | K45: 0 | L45: 0 | M45: 0 | N45: 0 | O45: 0 | P45: 0 | Q45: 0 | R45: 0 | S45: 0 | T45: 0 | U45: 0 | V45: 0 | W45: 0 | X45: 0 | Y45: 0 | Z45: 0 | AA45: 0 | AB45: 0 | AC45: 0 | AD45: 0 | AE45: 0 | AF45: 0 | AG45: 0 | AH45: 0 | AI45: 0 | AJ45: 0 | AK45: 0 | AL45: 0 | AM45: 0 | AN45: 0 | AO45: 0 | AP45: 0 | AQ45: 0 | AR45: 0 | AS45: 0 | AT45: 0 | AU45: 0 | AV45: 0 | AW45: 0 | AX45: 0 | AY45: 0 | AZ45: 0 | BA45: 0 | BB45: 143 | BC45: 17 | BD45: 156 | BE45: 69 | BF45: 218 | BG45: 271 | BH45: -71 | BI45: 250 | BJ45: 391 | BK45: -503 | BL45: -263 | BM45: 273 | BN45: 364 | BO45: 1169 | BP45: 6 | BQ45: 282 | BR45: 480 | BS45: 1374 | BT45: 237 | BU45: -652 | BV45: -384 | BW45: 414 | BX45: 382 | BY45: -120 | BZ45: 353 | CA45: 1976 | CB45: 3196 | CC45: 32 | CD45: 1219 | CE45: 7691 | CF45: 2748 | CG45: -2637 | CH45: -3196
A46: Nonfinancial corporate business; total loans including security repurchase agreements; asset | B46: Currency | C46: 1000000 | D46: USD | E46: Z1/Z1/FA104035005.A | F46: FA104035005.A | H46: 548 | I46: 820 | J46: 810 | K46: 580 | L46: 1119 | M46: 625 | N46: -129 | O46: 286 | P46: 370 | Q46: 727 | R46: 506 | S46: 132 | T46: 205 | U46: 1281 | V46: -383 | W46: 102 | X46: 899 | Y46: 1089 | Z46: 1408 | AA46: 1429 | AB46: 700 | AC46: 235 | AD46: 1233 | AE46: 3298 | AF46: -1436 | AG46: 4754 | AH46: 4203 | AI46: 10185 | AJ46: -3749 | AK46: -2437 | AL46: 2586 | AM46: 4490 | AN46: 4590 | AO46: 8172 | AP46: 14790 | AQ46: 13382 | AR46: 4458 | AS46: 2096 | AT46: 13085 | AU46: 7125 | AV46: 2588 | AW46: 9685 | AX46: 29556 | AY46: -1862 | AZ46: -2719 | BA46: -562 | BB46: 13493 | BC46: 14340 | BD46: 29371 | BE46: 4058 | BF46: -1935 | BG46: 40173 | BH46: 5649 | BI46: 28844 | BJ46: -6532 | BK46: 3886 | BL46: 26835 | BM46: -21377 | BN46: 31526 | BO46: -2765 | BP46: -31155 | BQ46: -39875 | BR46: -36178 | BS46: 33634 | BT46: -37525 | BU46: 21925 | BV46: 9659 | BW46: -727 | BX46: 24590 | BY46: 26523 | BZ46: -14094 | CA46: -70644 | CB46: 53241 | CC46: -93437 | CD46: 5385 | CE46: -34296 | CF46: -43621 | CG46: 55259 | CH46: 10976
... A108: Nonfinancial corporate business; net worth (IMA) | B108: Currency | C108: 1000000 | D108: USD | E108: Z1/Z1/FC102090095.A | F108: FC102090095.A | H108: 19885 | I108: 37941 | J108: 23621 | K108: -1479 | L108: -498 | M108: -7395 | N108: 22545 | O108: 20496 | P108: -90231 | Q108: -63005 | R108: -2538 | S108: 70586 | T108: -140858 | U108: -50781 | V108: 412 | W108: -121554 | X108: 32555 | Y108: -18682 | Z108: -46612 | AA108: -26268 | AB108: 118521 | AC108: -106405 | AD108: -64685 | AE108: 208163 | AF108: 75942 | AG108: -10826 | AH108: -63223 | AI108: 370685 | AJ108: 610428 | AK108: -150052 | AL108: 78315 | AM108: 324705 | AN108: 287481 | AO108: 254469 | AP108: 93720 | AQ108: 462113 | AR108: 108282 | AS108: -46056 | AT108: 245187 | AU108: -64838 | AV108: -138845 | AW108: 111852 | AX108: 899 | AY108: -362636 | AZ108: 20706 | BA108: -1129590 | BB108: -784011 | BC108: -109775 | BD108: 474871 | BE108: -1082653 | BF108: -367120 | BG108: -966533 | BH108: -1881662 | BI108: -2625864 | BJ108: 3037605 | BK108: 755168 | BL108: 2914631 | BM108: -1741530 | BN108: 277540 | BO108: 1035615 | BP108: 131374 | BQ108: 321811 | BR108: 2064395 | BS108: -3971424 | BT108: -2450514 | BU108: -53412 | BV108: -1422740 | BW108: -3911624 | BX108: -2290457 | BY108: 892719 | BZ108: -1038978 | CA108: -2422919 | CB108: 1620042 | CC108: -5647466 | CD108: -7742418 | CE108: -7471917 | CF108: 12533340 | CG108: -10672645 | CH108: -12113459
A109: Nonfinancial corporate business; total assets | B109: Currency | C109: 1000000 | D109: USD | E109: Z1/Z1/FL102000005.A | F109: FL102000005.A | G109: 286179 | H109: 311970 | I109: 362918 | J109: 396726 | K109: 406603 | L109: 453833 | M109: 502990 | N109: 527493 | O109: 549516 | P109: 564737 | Q109: 621122 | R109: 679244 | S109: 716339 | T109: 741003 | U109: 781943 | V109: 798485 | W109: 828196 | X109: 862704 | Y109: 901521 | Z109: 953006 | AA109: 1037843 | AB109: 1121957 | AC109: 1207164 | AD109: 1325556 | AE109: 1467873 | AF109: 1593964 | AG109: 1749129 | AH109: 1956675 | AI109: 2241079 | AJ109: 2631821 | AK109: 2970197 | AL109: 3340677 | AM109: 3716619 | AN109: 4234674 | AO109: 4900531 | AP109: 5585840 | AQ109: 6268214 | AR109: 6617846 | AS109: 6982066 | AT109: 7543455 | AU109: 8139533 | AV109: 8601193 | AW109: 9148874 | AX109: 9978103 | AY109: 10591414 | AZ109: 10734094 | BA109: 10752502 | BB109: 10687109 | BC109: 11315592 | BD109: 11998538 | BE109: 12998304 | BF109: 14077602 | BG109: 15616014 | BH109: 17458922 | BI109: 19609197 | BJ109: 21979140 | BK109: 21597229 | BL109: 21770725 | BM109: 22718470 | BN109: 25298918 | BO109: 27887456 | BP109: 30787001 | BQ109: 33410897 | BR109: 29748301 | BS109: 28237960 | BT109: 28279497 | BU109: 28985790 | BV109: 30534672 | BW109: 33694144 | BX109: 35544744 | BY109: 37114967 | BZ109: 39293411 | CA109: 42338006 | CB109: 43034940 | CC109: 48688431 | CD109: 50650703 | CE109: 57099697 | CF109: 58477437 | CG109: 61190830 | CH109: 63034404
A110: Nonfinancial corporate business; nonfinancial assets | B110: Currency | C110: 1000000 | D110: USD | E110: Z1/Z1/LM102010005.A | F110: LM102010005.A | G110: 217410 | H110: 245036 | I110: 286870 | J110: 314663 | K110: 320222 | L110: 350202 | M110: 390649 | N110: 408849 | O110: 427039 | P110: 436061 | Q110: 474122 | R110: 526053 | S110: 558139 | T110: 570439 | U110: 595235 | V110: 609837 | W110: 626707 | X110: 649543 | Y110: 673043 | Z110: 710023 | AA110: 761547 | AB110: 833092 | AC110: 898793 | AD110: 980642 | AE110: 1084257 | AF110: 1183462 | AG110: 1289214 | AH110: 1404127 | AI110: 1597325 | AJ110: 1944114 | AK110: 2132839 | AL110: 2355292 | AM110: 2619194 | AN110: 2979763 | AO110: 3440780 | AP110: 3926581 | AQ110: 4405193 | AR110: 4640163 | AS110: 4794609 | AT110: 5097458 | AU110: 5331604 | AV110: 5513361 | AW110: 5804924 | AX110: 6180698 | AY110: 6493857 | AZ110: 6649557 | BA110: 6493751 | BB110: 6343985 | BC110: 6481667 | BD110: 6891748 | BE110: 7271083 | BF110: 7715873 | BG110: 8735258 | BH110: 9355956 | BI110: 9920662 | BJ110: 10883270 | BK110: 10832685 | BL110: 11364937 | BM110: 11671434 | BN110: 13172128 | BO110: 14582533 | BP110: 16214190 | BQ110: 17433190 | BR110: 16642693 | BS110: 13964445 | BT110: 15074104 | BU110: 15979377 | BV110: 16756344 | BW110: 18252815 | BX110: 19485228 | BY110: 20378838 | BZ110: 21417556 | CA110: 22566406 | CB110: 23316387 | CC110: 24637844 | CD110: 25437294 | CE110: 28859727 | CF110: 29971263 | CG110: 29754124 | CH110: 30336892
A111: Nonfinancial corporate business; real estate at market value | B111: Currency | C111: 1000000 | D111: USD | E111: Z1/Z1/LM105035005.A | F111: LM105035005.A | G111: 142811 | H111: 159407 | I111: 187736 | J111: 199450 | K111: 203936 | L111: 220715 | M111: 240645 | N111: 251382 | O111: 259102 | P111: 265003 | Q111: 285179 | R111: 313564 | S111: 330035 | T111: 337847 | U111: 348117 | V111: 352721 | W111: 362550 | X111: 371962 | Y111: 381280 | Z111: 399403 | AA111: 423994 | AB111: 454030 | AC111: 483207 | AD111: 524866 | AE111: 580412 | AF111: 638015 | AG111: 707036 | AH111: 775700 | AI111: 883295 | AJ111: 1062857 | AK111: 1170930 | AL111: 1292062 | AM111: 1430747 | AN111: 1620823 | AO111: 1860176 | AP111: 2112581 | AQ111: 2397012 | AR111: 2546254 | AS111: 2616850 | AT111: 2755196 | AU111: 2872856 | AV111: 2956923 | AW111: 3096102 | AX111: 3297032 | AY111: 3446477 | AZ111: 3436638 | BA111: 3209584 | BB111: 2955054 | BC111: 2947188 | BD111: 3127498 | BE111: 3249692 | BF111: 3495199 | BG111: 4290930 | BH111: 4708587 | BI111: 4952489 | BJ111: 5564554 | BK111: 5461783 | BL111: 5914019 | BM111: 6101611 | BN111: 7270675 | BO111: 8336004 | BP111: 9558104 | BQ111: 10384792 | BR111: 9379546 | BS111: 6827264 | BT111: 7628727 | BU111: 8123907 | BV111: 8550079 | BW111: 9712711 | BX111: 10611914 | BY111: 11308154 | BZ111: 12000937 | CA111: 12696848 | CB111: 12907929 | CC111: 13843112 | CD111: 14258331 | CE111: 16516891 | CF111: 16525554 | CG111: 15770666 | CH111: 15740766
A112: Nonfinancial corporate business; equipment, current cost basis | B112: Currency | C112: 1000000 | D112: USD | E112: Z1/Z1/LM105015205.A | F112: LM105015205.A | G112: 32465 | H112: 39279 | I112: 47266 | J112: 57163 | K112: 59285 | L112: 68488 | M112: 75392 | N112: 79753 | O112: 86913 | P112: 90164 | Q112: 99783 | R112: 114101 | S112: 125736 | T112: 129748 | U112: 136600 | V112: 142048 | W112: 145294 | X112: 151692 | Y112: 158637 | Z112: 168605 | AA112: 182462 | AB112: 204456 | AC112: 225542 | AD112: 250075 | AE112: 276657 | AF112: 303944 | AG112: 325368 | AH112: 350690 | AI112: 389100 | AJ112: 479746 | AK112: 551086 | AL112: 609268 | AM112: 687076 | AN112: 783664 | AO112: 906981 | AP112: 1054348 | AQ112: 1171874 | AR112: 1240519 | AS112: 1277332 | AT112: 1343028 | AU112: 1418255 | AV112: 1493379 | AW112: 1555118 | AX112: 1637331 | AY112: 1721471 | AZ112: 1816047 | BA112: 1864110 | BB112: 1918294 | BC112: 1997112 | BD112: 2109169 | BE112: 2251824 | BF112: 2371476 | BG112: 2480420 | BH112: 2586099 | BI112: 2724829 | BJ112: 2893562 | BK112: 2967393 | BL112: 2973703 | BM112: 2980244 | BN112: 3129204 | BO112: 3262634 | BP112: 3486061 | BQ112: 3640080 | BR112: 3825487 | BS112: 3765496 | BT112: 3844060 | BU112: 4023175 | BV112: 4199753 | BW112: 4321474 | BX112: 4497223 | BY112: 4615911 | BZ112: 4734456 | CA112: 4921584 | CB112: 5167558 | CC112: 5319014 | CD112: 5399722 | CE112: 5828680 | CF112: 6272429 | CG112: 6539779 | CH112: 6779301
A113: Nonfinancial corporate business; nonresidential intellectual property products, current cost basis | B113: Currency | C113: 1000000 | D113: USD | E113: Z1/Z1/LM105013765.A | F113: LM105013765.A | G113: 5846 | H113: 6662 | I113: 7773 | J113: 8356 | K113: 8555 | L113: 9455 | M113: 10128 | N113: 11026 | O113: 12393 | P113: 13648 | Q113: 15241 | R113: 17473 | S113: 19457 | T113: 21159 | U113: 23283 | V113: 25168 | W113: 27234 | X113: 29096 | Y113: 31624 | Z113: 34152 | AA113: 37500 | AB113: 41644 | AC113: 46791 | AD113: 52548 | AE113: 59291 | AF113: 65365 | AG113: 69750 | AH113: 75345 | AI113: 84044 | AJ113: 95674 | AK113: 103649 | AL113: 113360 | AM113: 124876 | AN113: 139760 | AO113: 159871 | AP113: 182934 | AQ113: 209699 | AR113: 234876 | AS113: 260874 | AT113: 290589 | AU113: 319916 | AV113: 348148 | AW113: 382179 | AX113: 413067 | AY113: 449106 | AZ113: 487059 | BA113: 525147 | BB113: 560211 | BC113: 594465 | BD113: 638916 | BE113: 690603 | BF113: 744688 | BG113: 816120 | BH113: 886940 | BI113: 984814 | BJ113: 1085157 | BK113: 1130541 | BL113: 1164513 | BM113: 1225681 | BN113: 1278650 | BO113: 1365208 | BP113: 1449999 | BQ113: 1552430 | BR113: 1631698 | BS113: 1669582 | BT113: 1740922 | BU113: 1831473 | BV113: 1907266 | BW113: 2013748 | BX113: 2116253 | BY113: 2184292 | BZ113: 2324950 | CA113: 2496496 | CB113: 2661389 | CC113: 2825994 | CD113: 3104396 | CE113: 3337568 | CF113: 3655765 | CG113: 3947802 | CH113: 4242631
A114: Nonfinancial corporate business; inventories excluding IVA, current cost basis | B114: Currency | C114: 1000000 | D114: USD | E114: Z1/Z1/LM105020015.A | F114: LM105020015.A | G114: 36288 | H114: 39688 | I114: 44095 | J114: 49694 | K114: 48446 | L114: 51544 | M114: 64484 | N114: 66688 | O114: 68631 | P114: 67246 | Q114: 73919 | R114: 80915 | S114: 82911 | T114: 81685 | U114: 87235 | V114: 89900 | W114: 91629 | X114: 96793 | Y114: 101502 | Z114: 107863 | AA114: 117591 | AB114: 132962 | AC114: 143253 | AD114: 153153 | AE114: 167897 | AF114: 176138 | AG114: 187060 | AH114: 202392 | AI114: 240886 | AJ114: 305837 | AK114: 307174 | AL114: 340602 | AM114: 376495 | AN114: 435516 | AO114: 513752 | AP114: 576718 | AQ114: 626608 | AR114: 618514 | AS114: 639553 | AT114: 708645 | AU114: 720577 | AV114: 714911 | AW114: 771525 | AX114: 833268 | AY114: 876803 | AZ114: 909813 | BA114: 894910 | BB114: 910426 | BC114: 942902 | BD114: 1016165 | BE114: 1078964 | BF114: 1104510 | BG114: 1147788 | BH114: 1174330 | BI114: 1258530 | BJ114: 1339997 | BK114: 1272968 | BL114: 1312702 | BM114: 1363898 | BN114: 1493599 | BO114: 1618687 | BP114: 1720026 | BQ114: 1855888 | BR114: 1805962 | BS114: 1702103 | BT114: 1860395 | BU114: 2000822 | BV114: 2099246 | BW114: 2204882 | BX114: 2259838 | BY114: 2270481 | BZ114: 2357213 | CA114: 2451478 | CB114: 2579511 | CC114: 2649724 | CD114: 2674845 | CE114: 3176588 | CF114: 3517515 | CG114: 3495877 | CH114: 3574194
A115: Nonfinancial corporate business; total financial assets | B115: Currency | C115: 1000000 | D115: USD | E115: Z1/Z1/FL104090005.A | F115: FL104090005.A | G115: 68769 | H115: 66934 | I115: 76048 | J115: 82063 | K115: 86381 | L115: 103631 | M115: 112341 | N115: 118644 | O115: 122477 | P115: 128676 | Q115: 147000 | R115: 153191 | S115: 158200 | T115: 170564 | U115: 186708 | V115: 188648 | W115: 201489 | X115: 213161 | Y115: 228478 | Z115: 242983 | AA115: 276296 | AB115: 288865 | AC115: 308371 | AD115: 344914 | AE115: 383616 | AF115: 410502 | AG115: 459915 | AH115: 552548 | AI115: 643754 | AJ115: 687707 | AK115: 837358 | AL115: 985385 | AM115: 1097425 | AN115: 1254911 | AO115: 1459751 | AP115: 1659259 | AQ115: 1863021 | AR115: 1977683 | AS115: 2187457 | AT115: 2445997 | AU115: 2807929 | AV115: 3087832 | AW115: 3343950 | AX115: 3797405 | AY115: 4097557 | AZ115: 4084537 | BA115: 4258751 | BB115: 4343124 | BC115: 4833925 | BD115: 5106790 | BE115: 5727221 | BF115: 6361729 | BG115: 6880756 | BH115: 8102966 | BI115: 9688535 | BJ115: 11095870 | BK115: 10764544 | BL115: 10405788 | BM115: 11047036 | BN115: 12126790 | BO115: 13304923 | BP115: 14572811 | BQ115: 15977707 | BR115: 13105608 | BS115: 14273515 | BT115: 13205393 | BU115: 13006413 | BV115: 13778328 | BW115: 15441329 | BX115: 16059516 | BY115: 16736129 | BZ115: 17875855 | CA115: 19771600 | CB115: 19718553 | CC115: 24050587 | CD115: 25213409 | CE115: 28239970 | CF115: 28506174 | CG115: 31436706 | CH115: 32697512
A116: Nonfinancial corporate business; total currency and deposits; asset | B116: Currency | C116: 1000000 | D116: USD | E116: Z1/Z1/FL104000005.A | F116: FL104000005.A | G116: 19892 | H116: 20470 | I116: 22385 | J116: 22771 | K116: 23813 | L116: 25179 | M116: 26850 | N116: 27616 | O116: 27564 | P116: 29587 | Q116: 30411 | R116: 30128 | S116: 30155 | T116: 32132 | U116: 30828 | V116: 31391 | W116: 36009 | X116: 40354 | Y116: 39845 | Z116: 40506 | AA116: 42827 | AB116: 41859 | AC116: 45554 | AD116: 48174 | AE116: 47947 | AF116: 50204 | AG116: 53324 | AH116: 59000 | AI116: 66267 | AJ116: 73182 | AK116: 85024 | AL116: 95189 | AM116: 107859 | AN116: 119514 | AO116: 129567 | AP116: 133378 | AQ116: 125031 | AR116: 141655 | AS116: 173940 | AT116: 185106 | AU116: 211038 | AV116: 228729 | AW116: 235856 | AX116: 249232 | AY116: 249240 | AZ116: 248448 | BA116: 258511 | BB116: 250453 | BC116: 284502 | BD116: 297548 | BE116: 305170 | BF116: 347179 | BG116: 366291 | BH116: 386326 | BI116: 461131 | BJ116: 524072 | BK116: 471199 | BL116: 473483 | BM116: 605378 | BN116: 659684 | BO116: 780104 | BP116: 698931 | BQ116: 623189 | BR116: 355950 | BS116: 624333 | BT116: 788906 | BU116: 830686 | BV116: 889394 | BW116: 1041466 | BX116: 1064316 | BY116: 1103308 | BZ116: 1281472 | CA116: 1348312 | CB116: 1494860 | CC116: 1674442 | CD116: 2199568 | CE116: 2501459 | CF116: 2498884 | CG116: 2597035 | CH116: 2828842
A117: Nonfinancial corporate business; checkable deposits and currency; asset | B117: Currency | C117: 1000000 | D117: USD | E117: Z1/Z1/FL103020005.A | F117: FL103020005.A | G117: 18959 | H117: 19502 | I117: 21434 | J117: 21861 | K117: 22903 | L117: 24222 | M117: 25859 | N117: 26641 | O117: 26550 | P117: 28329 | Q117: 29282 | R117: 28990 | S117: 29024 | T117: 30083 | U117: 29196 | V117: 28243 | W117: 31673 | X117: 34564 | Y117: 33427 | Z117: 32738 | AA117: 33053 | AB117: 32371 | AC117: 34817 | AD117: 37531 | AE117: 43122 | AF117: 44059 | AG117: 42581 | AH117: 44938 | AI117: 46315 | AJ117: 47772 | AK117: 58272 | AL117: 62967 | AM117: 66717 | AN117: 73015 | AO117: 79073 | AP117: 78660 | AQ117: 57674 | AR117: 68019 | AS117: 89573 | AT117: 102698 | AU117: 125714 | AV117: 123998 | AW117: 133651 | AX117: 145405 | AY117: 153925 | AZ117: 159167 | BA117: 164495 | BB117: 158671 | BC117: 178018 | BD117: 185515 | BE117: 188079 | BF117: 189301 | BG117: 178778 | BH117: 163220 | BI117: 192794 | BJ117: 227700 | BK117: 174562 | BL117: 161595 | BM117: 204455 | BN117: 235523 | BO117: 336173 | BP117: 262603 | BQ117: 311604 | BR117: 179358 | BS117: 364004 | BT117: 489675 | BU117: 582807 | BV117: 626691 | BW117: 671058 | BX117: 790778 | BY117: 837876 | BZ117: 994846 | CA117: 950449 | CB117: 1201415 | CC117: 1342005 | CD117: 1786421 | CE117: 2051447 | CF117: 1996872 | CG117: 1917261 | CH117: 2197339
A118: Nonfinancial corporate business; total time and savings deposits; asset | B118: Currency | C118: 1000000 | D118: USD | E118: Z1/Z1/FL103030003.A | F118: FL103030003.A | G118: 900 | H118: 900 | I118: 900 | J118: 900 | K118: 900 | L118: 900 | M118: 900 | N118: 900 | O118: 900 | P118: 1100 | Q118: 1000 | R118: 1000 | S118: 1000 | T118: 1900 | U118: 1500 | V118: 3000 | W118: 4100 | X118: 5000 | Y118: 5687 | Z118: 6671 | AA118: 8993 | AB118: 8603 | AC118: 9682 | AD118: 9056 | AE118: 3652 | AF118: 5347 | AG118: 9509 | AH118: 11890 | AI118: 16623 | AJ118: 20464 | AK118: 24130 | AL118: 28783 | AM118: 35456 | AN118: 38182 | AO118: 40414 | AP118: 45022 | AQ118: 54971 | AR118: 63573 | AS118: 69974 | AT118: 69124 | AU118: 69301 | AV118: 85530 | AW118: 85943 | AX118: 82273 | AY118: 80610 | AZ118: 74564 | BA118: 77581 | BB118: 75991 | BC118: 91982 | BD118: 96369 | BE118: 99688 | BF118: 129670 | BG118: 164374 | BH118: 192588 | BI118: 236877 | BJ118: 272343 | BK118: 281120 | BL118: 291301 | BM118: 362778 | BN118: 370456 | BO118: 380360 | BP118: 386992 | BQ118: 261335 | BR118: 151888 | BS118: 228801 | BT118: 235240 | BU118: 195351 | BV118: 209082 | BW118: 248237 | BX118: 160676 | BY118: 171575 | BZ118: 189039 | CA118: 181313 | CB118: 187155 | CC118: 201454 | CD118: 278135 | CE118: 283717 | CF118: 301006 | CG118: 433998 | CH118: 418475
A119: Nonfinancial corporate business; private foreign deposits; asset | B119: Currency | C119: 1000000 | D119: USD | E119: Z1/Z1/FL103091003.A | F119: FL103091003.A | G119: 33 | H119: 68 | I119: 51 | J119: 10 | K119: 10 | L119: 57 | M119: 91 | N119: 75 | O119: 114 | P119: 158 | Q119: 129 | R119: 138 | S119: 131 | T119: 149 | U119: 132 | V119: 148 | W119: 236 | X119: 790 | Y119: 731 | Z119: 1097 | AA119: 781 | AB119: 885 | AC119: 1055 | AD119: 1587 | AE119: 1173 | AF119: 798 | AG119: 1234 | AH119: 2172 | AI119: 3329 | AJ119: 4946 | AK119: 2622 | AL119: 3439 | AM119: 5686 | AN119: 8317 | AO119: 10080 | AP119: 9696 | AQ119: 12386 | AR119: 10063 | AS119: 14393 | AT119: 13284 | AU119: 16023 | AV119: 19201 | AW119: 16262 | AX119: 21554 | AY119: 14705 | AZ119: 14717 | BA119: 16435 | BB119: 15791 | BC119: 14502 | BD119: 15664 | BE119: 17403 | BF119: 28208 | BG119: 23139 | BH119: 30518 | BI119: 31460 | BJ119: 24029 | BK119: 15517 | BL119: 20587 | BM119: 38145 | BN119: 53705 | BO119: 63571 | BP119: 49336 | BQ119: 50250 | BR119: 24704 | BS119: 31528 | BT119: 63991 | BU119: 52528 | BV119: 53621 | BW119: 122171 | BX119: 112862 | BY119: 93857 | BZ119: 97587 | CA119: 216550 | CB119: 106290 | CC119: 130983 | CD119: 135012 | CE119: 166295 | CF119: 201006 | CG119: 245776 | CH119: 213028
A120: Nonfinancial corporate business; debt securities; asset | B120: Currency | C120: 1000000 | D120: USD | E120: Z1/Z1/LM104022005.A | F120: LM104022005.A | G120: 18760 | H120: 13124 | I120: 12770 | J120: 13485 | K120: 15447 | L120: 18665 | M120: 19587 | N120: 18655 | O120: 20449 | P120: 18786 | Q120: 23017 | R120: 18765 | S120: 18303 | T120: 18860 | U120: 25357 | V120: 20038 | W120: 18828 | X120: 17583 | Y120: 21492 | Z120: 20855 | AA120: 19756 | AB120: 18572 | AC120: 16871 | AD120: 19274 | AE120: 17750 | AF120: 19056 | AG120: 24418 | AH120: 26327 | AI120: 23431 | AJ120: 26740 | AK120: 30745 | AL120: 39154 | AM120: 32988 | AN120: 31966 | AO120: 29316 | AP120: 34396 | AQ120: 43236 | AR120: 44459 | AS120: 64787 | AT120: 74011 | AU120: 81169 | AV120: 77913 | AW120: 68768 | AX120: 64397 | AY120: 107244 | AZ120: 79441 | BA120: 108051 | BB120: 132173 | BC120: 142181 | BD120: 146524 | BE120: 137852 | BF120: 138732 | BG120: 99247 | BH120: 100255 | BI120: 105469 | BJ120: 124661 | BK120: 124868 | BL120: 145920 | BM120: 157048 | BN120: 173582 | BO120: 215089 | BP120: 213883 | BQ120: 152455 | BR120: 126993 | BS120: 145413 | BT120: 216876 | BU120: 207993 | BV120: 192241 | BW120: 184184 | BX120: 213614 | BY120: 216373 | BZ120: 211927 | CA120: 243351 | CB120: 263220 | CC120: 337625 | CD120: 377229 | CE120: 409561 | CF120: 382168 | CG120: 400061 | CH120: 408501
... A168: Nonfinancial corporate business; net worth (IMA) | B168: Currency | C168: 1000000 | D168: USD | E168: Z1/Z1/FL102090095.A | F168: FL102090095.A | G168: 94234 | H168: 114119 | I168: 152060 | J168: 175681 | K168: 174202 | L168: 173704 | M168: 166309 | N168: 188854 | O168: 209350 | P168: 119119 | Q168: 56114 | R168: 53576 | S168: 124162 | T168: -16696 | U168: -67477 | V168: -67065 | W168: -188619 | X168: -156064 | Y168: -174746 | Z168: -221358 | AA168: -247626 | AB168: -129105 | AC168: -235510 | AD168: -300195 | AE168: -92032 | AF168: -16090 | AG168: -26916 | AH168: -90139 | AI168: 280546 | AJ168: 890974 | AK168: 740922 | AL168: 819237 | AM168: 1143942 | AN168: 1431423 | AO168: 1685892 | AP168: 1779612 | AQ168: 2241725 | AR168: 2350007 | AS168: 2303951 | AT168: 2549138 | AU168: 2484300 | AV168: 2345455 | AW168: 2457307 | AX168: 2458206 | AY168: 2095570 | AZ168: 2116276 | BA168: 986686 | BB168: 202675 | BC168: 92900 | BD168: 567771 | BE168: -514882 | BF168: -882002 | BG168: -1848535 | BH168: -3730197 | BI168: -6356062 | BJ168: -3318456 | BK168: -2563288 | BL168: 351343 | BM168: -1390187 | BN168: -1112647 | BO168: -77032 | BP168: 54342 | BQ168: 376153 | BR168: 2440548 | BS168: -1530876 | BT168: -3981391 | BU168: -4034802 | BV168: -5457543 | BW168: -9369167 | BX168: -11659624 | BY168: -10766905 | BZ168: -11805883 | CA168: -14228802 | CB168: -12608760 | CC168: -18256226 | CD168: -25998644 | CE168: -33470561 | CF168: -20937221 | CG168: -31609866 | CH168: -43723326
A172: Net Property Payments over V | H172: =(H17-H13)/'B1'!H16 -> 0.037810216 | I172: =(I17-I13)/'B1'!I16 -> 0.041554781 | J172: =(J17-J13)/'B1'!J16 -> 0.045228879 | K172: =(K17-K13)/'B1'!K16 -> 0.046295028 | L172: =(L17-L13)/'B1'!L16 -> 0.045326293 | M172: =(M17-M13)/'B1'!M16 -> 0.033783543 | N172: =(N17-N13)/'B1'!N16 -> 0.034600786 | O172: =(O17-O13)/'B1'!O16 -> 0.037232014 | ... CH172: =(CH17-CH13)/'B1'!CH16 -> 0.022344115
A173: Net Lending over V | H173: =H34/'B1'!H16 -> -0.067118862 | I173: =I34/'B1'!I16 -> -0.022565092 | J173: =J34/'B1'!J16 -> -0.001877941 | K173: =K34/'B1'!K16 -> 0.046226544 | L173: =L34/'B1'!L16 -> -0.019835919 | M173: =M34/'B1'!M16 -> -0.035361505 | N173: =N34/'B1'!N16 -> -0.0044773745 | O173: =O34/'B1'!O16 -> -0.010253159 | ... CH173: =CH34/'B1'!CH16 -> -0.00018425547
A174: FCF over V | H174: =(H3-H6-H9-H23--H24-H30)/'B1'!H16 -> 0.022411146 | I174: =(I3-I6-I9-I23--I24-I30)/'B1'!I16 -> 0.035271864 | J174: =(J3-J6-J9-J23--J24-J30)/'B1'!J16 -> 0.072081277 | K174: =(K3-K6-K9-K23--K24-K30)/'B1'!K16 -> 0.085543076 | L174: =(L3-L6-L9-L23--L24-L30)/'B1'!L16 -> 0.062278326 | M174: =(M3-M6-M9-M23--M24-M30)/'B1'!M16 -> 0.04151734 | N174: =(N3-N6-N9-N23--N24-N30)/'B1'!N16 -> 0.045810132 | O174: =(O3-O6-O9-O23--O24-O30)/'B1'!O16 -> 0.039698836 | ... CH174: =(CH3-CH6-CH9-CH23--CH24-CH30)/'B1'!CH16 -> 0.025507325
A175: FCFless inventories over V | H175: =H174-(H32+H33)/'B1'!H16 -> -0.02205214 | I175: =I174-(I32+I33)/'B1'!I16 -> 0.027475707 | J175: =J174-(J32+J33)/'B1'!J16 -> 0.052057101 | K175: =K174-(K32+K33)/'B1'!K16 -> 0.10057526 | L175: =L174-(L32+L33)/'B1'!L16 -> 0.032300649 | M175: =M174-(M32+M33)/'B1'!M16 -> 0.0049032718 | N175: =N174-(N32+N33)/'B1'!N16 -> 0.0376054 | O175: =O174-(O32+O33)/'B1'!O16 -> 0.035794183 | ... CH175: =CH174-(CH32+CH33)/'B1'!CH16 -> 0.024943284

Sheet S6
A1: Download Page | F1: Z.1 Statistical Release for Jan 09, 2026
A2: Descriptions: | B2: Unit: | C2: Multiplier: | D2: Currency: | E2: Unique Identifier: | F2: Series Name: | G2: 1945 | H2: 1946 | I2: 1947 | J2: 1948 | K2: 1949 | L2: 1950 | M2: 1951 | N2: 1952 | O2: 1953 | P2: 1954 | Q2: 1955 | R2: 1956 | S2: 1957 | T2: 1958 | U2: 1959 | V2: 1960 | W2: 1961 | X2: 1962 | Y2: 1963 | Z2: 1964 | AA2: 1965 | AB2: 1966 | AC2: 1967 | AD2: 1968 | AE2: 1969 | AF2: 1970 | AG2: 1971 | AH2: 1972 | AI2: 1973 | AJ2: 1974 | AK2: 1975 | AL2: 1976 | AM2: 1977 | AN2: 1978 | AO2: 1979 | AP2: 1980 | AQ2: 1981 | AR2: 1982 | AS2: 1983 | AT2: 1984 | AU2: 1985 | AV2: 1986 | AW2: 1987 | AX2: 1988 | AY2: 1989 | AZ2: 1990 | BA2: 1991 | BB2: 1992 | BC2: 1993 | BD2: 1994 | BE2: 1995 | BF2: 1996 | BG2: 1997 | BH2: 1998 | BI2: 1999 | BJ2: 2000 | BK2: 2001 | BL2: 2002 | BM2: 2003 | BN2: 2004 | BO2: 2005 | BP2: 2006 | BQ2: 2007 | BR2: 2008 | BS2: 2009 | BT2: 2010 | BU2: 2011 | BV2: 2012 | BW2: 2013 | BX2: 2014 | BY2: 2015 | BZ2: 2016 | CA2: 2017 | CB2: 2018 | CC2: 2019 | CD2: 2020 | CE2: 2021 | CF2: 2022 | CG2: 2023 | CH2: 2024
A3: Domestic financial sectors; gross value added (IMA) | B3: Currency | C3: 1000000 | D3: USD | E3: Z1/Z1/FA796902505.A | F3: FA796902505.A | U3: 18992 | V3: 20513 | W3: 21674 | X3: 22384 | Y3: 23120 | Z3: 25403 | AA3: 27525 | AB3: 29945 | AC3: 33430 | AD3: 37392 | AE3: 42121 | AF3: 45285 | AG3: 49765 | AH3: 54292 | AI3: 58065 | AJ3: 66368 | AK3: 74926 | AL3: 81285 | AM3: 96377 | AN3: 114461 | AO3: 125379 | AP3: 139760 | AQ3: 163524 | AR3: 178402 | AS3: 205080 | AT3: 229391 | AU3: 253174 | AV3: 264363 | AW3: 285535 | AX3: 304210 | AY3: 340606 | AZ3: 345364 | BA3: 361647 | BB3: 402768 | BC3: 428910 | BD3: 445203 | BE3: 490858 | BF3: 547671 | BG3: 618996 | BH3: 694961 | BI3: 731353 | BJ3: 812578 | BK3: 823920 | BL3: 822452 | BM3: 855064 | BN3: 886637 | BO3: 989750 | BP3: 1095145 | BQ3: 1024841 | BR3: 800955 | BS3: 972163 | BT3: 1010133 | BU3: 1009309 | BV3: 1139927 | BW3: 1104669 | BX3: 1242979 | BY3: 1317243 | BZ3: 1412177 | CA3: 1456489 | CB3: 1516413 | CC3: 1600582 | CD3: 1658068 | CE3: 1822313 | CF3: 1931478 | CG3: 1996581 | CH3: 2135222
A4: Domestic financial sectors; consumption of fixed capital, nonresidential structures, equipment, and intellectual property products, including noncorporate financial, current cost basis (IMA) | B4: Currency | C4: 1000000 | D4: USD | E4: Z1/Z1/FA796330081.A | F4: FA796330081.A | H4: 298 | I4: 384 | J4: 442 | K4: 485 | L4: 528 | M4: 600 | N4: 645 | O4: 687 | P4: 740 | Q4: 778 | R4: 878 | S4: 970 | T4: 1080 | U4: 1184 | V4: 1145 | W4: 1182 | X4: 1235 | Y4: 1302 | Z4: 1392 | AA4: 1561 | AB4: 1735 | AC4: 1930 | AD4: 2211 | AE4: 2570 | AF4: 2940 | AG4: 3341 | AH4: 3756 | AI4: 4370 | AJ4: 5300 | AK4: 6511 | AL4: 7518 | AM4: 8717 | AN4: 10007 | AO4: 11922 | AP4: 14449 | AQ4: 17262 | AR4: 20359 | AS4: 23156 | AT4: 26248 | AU4: 30060 | AV4: 34300 | AW4: 39184 | AX4: 44502 | AY4: 49994 | AZ4: 55143 | BA4: 59174 | BB4: 61104 | BC4: 64383 | BD4: 68449 | BE4: 73008 | BF4: 75730 | BG4: 79216 | BH4: 85037 | BI4: 95258 | BJ4: 106474 | BK4: 112757 | BL4: 115315 | BM4: 120244 | BN4: 127299 | BO4: 135160 | BP4: 142043 | BQ4: 149569 | BR4: 156506 | BS4: 157958 | BT4: 156443 | BU4: 160953 | BV4: 167837 | BW4: 176478 | BX4: 184121 | BY4: 192444 | BZ4: 203220 | CA4: 214439 | CB4: 226122 | CC4: 242836 | CD4: 257539 | CE4: 274459 | CF4: 302232 | CG4: 324065 | CH4: 344821
A5: Domestic financial sectors; net value added (IMA) | B5: Currency | C5: 1000000 | D5: USD | E5: Z1/Z1/FA796902605.A | F5: FA796902605.A | U5: 17808 | V5: 19368 | W5: 20492 | X5: 21149 | Y5: 21818 | Z5: 24011 | AA5: 25964 | AB5: 28210 | AC5: 31500 | AD5: 35181 | AE5: 39551 | AF5: 42345 | AG5: 46424 | AH5: 50536 | AI5: 53695 | AJ5: 61068 | AK5: 68415 | AL5: 73767 | AM5: 87660 | AN5: 104454 | AO5: 113457 | AP5: 125311 | AQ5: 146262 | AR5: 158043 | AS5: 181924 | AT5: 203143 | AU5: 223114 | AV5: 230063 | AW5: 246351 | AX5: 259708 | AY5: 290612 | AZ5: 290221 | BA5: 302473 | BB5: 341664 | BC5: 364527 | BD5: 376754 | BE5: 417850 | BF5: 471941 | BG5: 539780 | BH5: 609924 | BI5: 636095 | BJ5: 706104 | BK5: 711163 | BL5: 707137 | BM5: 734820 | BN5: 759338 | BO5: 854590 | BP5: 953102 | BQ5: 875272 | BR5: 644449 | BS5: 814205 | BT5: 853690 | BU5: 848356 | BV5: 972090 | BW5: 928191 | BX5: 1058858 | BY5: 1124799 | BZ5: 1208957 | CA5: 1242050 | CB5: 1290291 | CC5: 1357746 | CD5: 1400529 | CE5: 1547854 | CF5: 1629246 | CG5: 1672516 | CH5: 1790402
A6: Domestic financial sectors; compensation of employees paid (IMA) | B6: Currency | C6: 1000000 | D6: USD | E6: Z1/Z1/FA796025005.A | F6: FA796025005.A | J6: 4009 | K6: 4298 | L6: 4751 | M6: 5281 | N6: 5810 | O6: 6397 | P6: 6980 | Q6: 7553 | R6: 8271 | S6: 8991 | T6: 9764 | U6: 10620 | V6: 11396 | W6: 12295 | X6: 12986 | Y6: 13831 | Z6: 14899 | AA6: 15978 | AB6: 17382 | AC6: 19274 | AD6: 21665 | AE6: 23822 | AF6: 25845 | AG6: 28072 | AH6: 30967 | AI6: 33737 | AJ6: 37269 | AK6: 42179 | AL6: 46683 | AM6: 52163 | AN6: 59304 | AO6: 67454 | AP6: 77815 | AQ6: 87540 | AR6: 98796 | AS6: 110836 | AT6: 121405 | AU6: 135507 | AV6: 155589 | AW6: 174491 | AX6: 189347 | AY6: 196363 | AZ6: 209429 | BA6: 219212 | BB6: 246247 | BC6: 259964 | BD6: 265856 | BE6: 279886 | BF6: 304074 | BG6: 333746 | BH6: 375328 | BI6: 399180 | BJ6: 440636 | BK6: 445265 | BL6: 443298 | BM6: 459762 | BN6: 497689 | BO6: 534590 | BP6: 579181 | BQ6: 617429 | BR6: 612139 | BS6: 547984 | BT6: 573340 | BU6: 606487 | BV6: 630088 | BW6: 641324 | BX6: 681085 | BY6: 715705 | BZ6: 734148 | CA6: 787648 | CB6: 819121 | CC6: 851646 | CD6: 912345 | CE6: 990616 | CF6: 1020695 | CG6: 1059695 | CH6: 1115373
A7: Domestic financial sectors; wages and salaries paid (IMA) | B7: Currency | C7: 1000000 | D7: USD | E7: Z1/Z1/FA796020001.A | F7: FA796020001.A | J7: 3826 | K7: 4088 | L7: 4503 | M7: 4994 | N7: 5484 | O7: 6031 | P7: 6550 | Q7: 7083 | R7: 7744 | S7: 8396 | T7: 9034 | U7: 9763 | V7: 10448 | W7: 11285 | X7: 11819 | Y7: 12522 | Z7: 13478 | AA7: 14395 | AB7: 15562 | AC7: 17208 | AD7: 19423 | AE7: 21422 | AF7: 23166 | AG7: 25078 | AH7: 27369 | AI7: 29785 | AJ7: 32988 | AK7: 36355 | AL7: 40003 | AM7: 44421 | AN7: 50946 | AO7: 57991 | AP7: 66788 | AQ7: 75282 | AR7: 84318 | AS7: 94984 | AT7: 104290 | AU7: 116918 | AV7: 134137 | AW7: 150499 | AX7: 162160 | AY7: 166828 | AZ7: 176956 | BA7: 184416 | BB7: 206469 | BC7: 216681 | BD7: 220895 | BE7: 233583 | BF7: 257183 | BG7: 284022 | BH7: 319715 | BI7: 341678 | BJ7: 378780 | BK7: 374725 | BL7: 370684 | BM7: 390160 | BN7: 422462 | BO7: 448884 | BP7: 490232 | BQ7: 526363 | BR7: 517209 | BS7: 465308 | BT7: 485459 | BU7: 513242 | BV7: 536780 | BW7: 545423 | BX7: 582076 | BY7: 611170 | BZ7: 625472 | CA7: 668515 | CB7: 693117 | CC7: 727179 | CD7: 787383 | CE7: 860093 | CF7: 885582 | CG7: 911657 | CH7: 956949
A8: Domestic financial sectors; employers' social contributions paid (IMA) | B8: Currency | C8: 1000000 | D8: USD | E8: Z1/Z1/FA796401001.A | F8: FA796401001.A | J8: 183 | K8: 210 | L8: 248 | M8: 287 | N8: 326 | O8: 366 | P8: 430 | Q8: 470 | R8: 527 | S8: 595 | T8: 730 | U8: 857 | V8: 948 | W8: 1010 | X8: 1167 | Y8: 1309 | Z8: 1421 | AA8: 1583 | AB8: 1820 | AC8: 2066 | AD8: 2242 | AE8: 2400 | AF8: 2679 | AG8: 2994 | AH8: 3598 | AI8: 3952 | AJ8: 4281 | AK8: 5824 | AL8: 6680 | AM8: 7742 | AN8: 8358 | AO8: 9463 | AP8: 11027 | AQ8: 12258 | AR8: 14478 | AS8: 15852 | AT8: 17115 | AU8: 18589 | AV8: 21452 | AW8: 23992 | AX8: 27187 | AY8: 29535 | AZ8: 32473 | BA8: 34796 | BB8: 39778 | BC8: 43283 | BD8: 44961 | BE8: 46303 | BF8: 46891 | BG8: 49724 | BH8: 55613 | BI8: 57502 | BJ8: 61856 | BK8: 70540 | BL8: 72614 | BM8: 69602 | BN8: 75227 | BO8: 85706 | BP8: 88949 | BQ8: 91066 | BR8: 94930 | BS8: 82676 | BT8: 87881 | BU8: 93245 | BV8: 93308 | BW8: 95901 | BX8: 99009 | BY8: 104535 | BZ8: 108676 | CA8: 119133 | CB8: 126004 | CC8: 124467 | CD8: 124962 | CE8: 130523 | CF8: 135113 | CG8: 148038 | CH8: 158424
A9: Domestic financial sectors; taxes on production and imports less subsidies, payable (IMA) | B9: Currency | C9: 1000000 | D9: USD | E9: Z1/Z1/FA796240101.A | F9: FA796240101.A | U9: 1434 | V9: 1537 | W9: 1632 | X9: 1669 | Y9: 1841 | Z9: 2080 | AA9: 2191 | AB9: 2324 | AC9: 2542 | AD9: 2813 | AE9: 3194 | AF9: 3239 | AG9: 3932 | AH9: 4259 | AI9: 4552 | AJ9: 4787 | AK9: 4965 | AL9: 5434 | AM9: 6365 | AN9: 6853 | AO9: 6987 | AP9: 7855 | AQ9: 9238 | AR9: 9110 | AS9: 10302 | AT9: 11675 | AU9: 13528 | AV9: 16049 | AW9: 18055 | AX9: 20127 | AY9: 21503 | AZ9: 23430 | BA9: 24767 | BB9: 25373 | BC9: 26451 | BD9: 27544 | BE9: 29390 | BF9: 30969 | BG9: 33171 | BH9: 33616 | BI9: 35812 | BJ9: 36797 | BK9: 34692 | BL9: 37370 | BM9: 39563 | BN9: 43912 | BO9: 47071 | BP9: 49777 | BQ9: 51421 | BR9: 51041 | BS9: 58375 | BT9: 58714 | BU9: 54872 | BV9: 56701 | BW9: 56388 | BX9: 60728 | BY9: 64970 | BZ9: 72693 | CA9: 66493 | CB9: 79315 | CC9: 69290 | CD9: 71556 | CE9: 65044 | CF9: 83739 | CG9: 88987 | CH9: 96114
A10: Domestic financial sectors; operating surplus, net (IMA) | B10: Currency | C10: 1000000 | D10: USD | E10: Z1/Z1/FA796402101.A | F10: FA796402101.A | U10: 5754 | V10: 6435 | W10: 6565 | X10: 6494 | Y10: 6146 | Z10: 7032 | AA10: 7795 | AB10: 8504 | AC10: 9684 | AD10: 10703 | AE10: 12535 | AF10: 13261 | AG10: 14420 | AH10: 15310 | AI10: 15406 | AJ10: 19012 | AK10: 21271 | AL10: 21650 | AM10: 29132 | AN10: 38297 | AO10: 39016 | AP10: 39641 | AQ10: 49484 | AR10: 50137 | AS10: 60786 | AT10: 70063 | AU10: 74079 | AV10: 58425 | AW10: 53805 | AX10: 50234 | AY10: 72746 | AZ10: 57362 | BA10: 58494 | BB10: 70044 | BC10: 78112 | BD10: 83354 | BE10: 108574 | BF10: 136898 | BG10: 172863 | BH10: 200980 | BI10: 201103 | BJ10: 228671 | BK10: 231206 | BL10: 226469 | BM10: 235495 | BN10: 217737 | BO10: 272929 | BP10: 324144 | BQ10: 206422 | BR10: -18731 | BS10: 207846 | BT10: 221636 | BU10: 186997 | BV10: 285301 | BW10: 230479 | BX10: 317045 | BY10: 344124 | BZ10: 402116 | CA10: 387909 | CB10: 391855 | CC10: 436810 | CD10: 416628 | CE10: 492194 | CF10: 524813 | CG10: 523834 | CH10: 578915
A11: Domestic financial sectors; net national income/balance of primary incomes, net (IMA) | B11: Currency | C11: 1000000 | D11: USD | E11: Z1/Z1/FA796140005.A | F11: FA796140005.A | U11: 5627 | V11: 6606 | W11: 6751 | X11: 7175 | Y11: 6847 | Z11: 6970 | AA11: 8215 | AB11: 8076 | AC11: 8499 | AD11: 9958 | AE11: 10420 | AF11: 10367 | AG11: 12001 | AH11: 14023 | AI11: 15145 | AJ11: 16193 | AK11: 16631 | AL11: 17819 | AM11: 20510 | AN11: 28545 | AO11: 29863 | AP11: 20621 | AQ11: 14663 | AR11: 13694 | AS11: 22708 | AT11: 27159 | AU11: 33876 | AV11: 27984 | AW11: 34857 | AX11: 35978 | AY11: 48915 | AZ11: 44603 | BA11: 64107 | BB11: 84955 | BC11: 69793 | BD11: 64707 | BE11: 85645 | BF11: 85342 | BG11: 93845 | BH11: 94047 | BI11: 104136 | BJ11: 105322 | BK11: 163045 | BL11: 193992 | BM11: 202382 | BN11: 222849 | BO11: 229076 | BP11: 247574 | BQ11: 154448 | BR11: 26987 | BS11: 286118 | BT11: 356478 | BU11: 293161 | BV11: 255250 | BW11: 149771 | BX11: 268314 | BY11: 239291 | BZ11: 342520 | CA11: 250196 | CB11: 302065 | CC11: 325975 | CD11: 187629 | CE11: 249854 | CF11: 322938 | CG11: 358274 | CH11: 525479
A12: Domestic financial sectors; operating surplus, net (IMA) | B12: Currency | C12: 1000000 | D12: USD | E12: Z1/Z1/FA796402101.A | F12: FA796402101.A | U12: 5754 | V12: 6435 | W12: 6565 | X12: 6494 | Y12: 6146 | Z12: 7032 | AA12: 7795 | AB12: 8504 | AC12: 9684 | AD12: 10703 | AE12: 12535 | AF12: 13261 | AG12: 14420 | AH12: 15310 | AI12: 15406 | AJ12: 19012 | AK12: 21271 | AL12: 21650 | AM12: 29132 | AN12: 38297 | AO12: 39016 | AP12: 39641 | AQ12: 49484 | AR12: 50137 | AS12: 60786 | AT12: 70063 | AU12: 74079 | AV12: 58425 | AW12: 53805 | AX12: 50234 | AY12: 72746 | AZ12: 57362 | BA12: 58494 | BB12: 70044 | BC12: 78112 | BD12: 83354 | BE12: 108574 | BF12: 136898 | BG12: 172863 | BH12: 200980 | BI12: 201103 | BJ12: 228671 | BK12: 231206 | BL12: 226469 | BM12: 235495 | BN12: 217737 | BO12: 272929 | BP12: 324144 | BQ12: 206422 | BR12: -18731 | BS12: 207846 | BT12: 221636 | BU12: 186997 | BV12: 285301 | BW12: 230479 | BX12: 317045 | BY12: 344124 | BZ12: 402116 | CA12: 387909 | CB12: 391855 | CC12: 436810 | CD12: 416628 | CE12: 492194 | CF12: 524813 | CG12: 523834 | CH12: 578915
A13: Domestic financial sectors; property income (received) (IMA) | B13: Currency | C13: 1000000 | D13: USD | E13: Z1/Z1/FA796150105.A | F13: FA796150105.A | U13: 28248 | V13: 31736 | W13: 33849 | X13: 37981 | Y13: 41716 | Z13: 46298 | AA13: 50936 | AB13: 55924 | AC13: 61358 | AD13: 71578 | AE13: 84545 | AF13: 101462 | AG13: 112088 | AH13: 125941 | AI13: 152966 | AJ13: 186693 | AK13: 207444 | AL13: 215464 | AM13: 238114 | AN13: 279972 | AO13: 339825 | AP13: 418734 | AQ13: 539909 | AR13: 623732 | AS13: 647186 | AT13: 706015 | AU13: 773030 | AV13: 810046 | AW13: 876319 | AX13: 991098 | AY13: 1150750 | AZ13: 1174075 | BA13: 1124742 | BB13: 1040698 | BC13: 1030223 | BD13: 1117850 | BE13: 1303859 | BF13: 1342292 | BG13: 1455932 | BH13: 1560271 | BI13: 1652864 | BJ13: 1922919 | BK13: 1881669 | BL13: 1625183 | BM13: 1560192 | BN13: 1796030 | BO13: 2210049 | BP13: 2804479 | BQ13: 3275813 | BR13: 2916509 | BS13: 2283106 | BT13: 2191411 | BU13: 2164433 | BV13: 2104833 | BW13: 2059758 | BX13: 2089803 | BY13: 2107536 | BZ13: 2193942 | CA13: 2413624 | CB13: 2714006 | CC13: 2816597 | CD13: 2334708 | CE13: 2338032 | CF13: 2965436 | CG13: 4128773 | CH13: 4569056
A14: Domestic financial sectors; interest received (IMA) | B14: Currency | C14: 1000000 | D14: USD | E14: Z1/Z1/FA796130101.A | F14: FA796130101.A | U14: 26518 | V14: 29881 | W14: 31935 | X14: 35672 | Y14: 39510 | Z14: 43509 | AA14: 47509 | AB14: 52906 | AC14: 58325 | AD14: 66438 | AE14: 78779 | AF14: 95414 | AG14: 105540 | AH14: 118729 | AI14: 144194 | AJ14: 176829 | AK14: 196857 | AL14: 204180 | AM14: 224668 | AN14: 264012 | AO14: 320043 | AP14: 395941 | AQ14: 515748 | AR14: 599418 | AS14: 619693 | AT14: 675015 | AU14: 739295 | AV14: 775246 | AW14: 839767 | AX14: 945785 | AY14: 1098684 | AZ14: 1117313 | BA14: 1065798 | BB14: 975705 | BC14: 956534 | BD14: 1034859 | BE14: 1208808 | BF14: 1231691 | BG14: 1332357 | BH14: 1430355 | BI14: 1513270 | BJ14: 1779653 | BK14: 1742644 | BL14: 1480800 | BM14: 1397855 | BN14: 1588298 | BO14: 1979593 | BP14: 2506423 | BQ14: 2911261 | BR14: 2532092 | BS14: 1958575 | BT14: 1816988 | BU14: 1780702 | BV14: 1690450 | BW14: 1586375 | BX14: 1588116 | BY14: 1593962 | BZ14: 1680538 | CA14: 1830870 | CB14: 2071815 | CC14: 2227435 | CD14: 1755711 | CE14: 1671466 | CF14: 2268753 | CG14: 3400169 | CH14: 3789272
A15: Domestic financial sectors; dividends received (IMA) | B15: Currency | C15: 1000000 | D15: USD | E15: Z1/Z1/FA796121101.A | F15: FA796121101.A | T15: 1615 | U15: 1691 | V15: 1805 | W15: 1870 | X15: 2257 | Y15: 2139 | Z15: 2723 | AA15: 3357 | AB15: 2941 | AC15: 2952 | AD15: 5030 | AE15: 5639 | AF15: 5904 | AG15: 6392 | AH15: 6982 | AI15: 8337 | AJ15: 9417 | AK15: 10077 | AL15: 10762 | AM15: 12961 | AN15: 15207 | AO15: 18598 | AP15: 21611 | AQ15: 23196 | AR15: 23491 | AS15: 25887 | AT15: 28842 | AU15: 31568 | AV15: 33007 | AW15: 33819 | AX15: 42770 | AY15: 48986 | AZ15: 52180 | BA15: 54809 | BB15: 60793 | BC15: 66741 | BD15: 76368 | BE15: 86470 | BF15: 102075 | BG15: 114076 | BH15: 122114 | BI15: 129135 | BJ15: 129902 | BK15: 127966 | BL15: 130593 | BM15: 142209 | BN15: 179433 | BO15: 229008 | BP15: 261581 | BQ15: 322669 | BR15: 338678 | BS15: 275723 | BT15: 308855 | BU15: 318938 | BV15: 359141 | BW15: 414307 | BX15: 450241 | BY15: 462935 | BZ15: 467414 | CA15: 526407 | CB15: 681009 | CC15: 559955 | CD15: 543224 | CE15: 616763 | CF15: 652178 | CG15: 689836 | CH15: 726462
A16: Domestic financial sectors; reinvested earnings on U.S. direct investment abroad; received (IMA) | B16: Currency | C16: 1000000 | D16: USD | E16: Z1/Z1/FA793092281.A | F16: FA793092281.A | H16: 18 | I16: 17 | J16: 18 | K16: 14 | L16: 15 | M16: 24 | N16: 28 | O16: 26 | P16: 23 | Q16: 33 | R16: 41 | S16: 46 | T16: 33 | U16: 39 | V16: 50 | W16: 44 | X16: 52 | Y16: 67 | Z16: 66 | AA16: 70 | AB16: 77 | AC16: 81 | AD16: 110 | AE16: 127 | AF16: 144 | AG16: 156 | AH16: 230 | AI16: 436 | AJ16: 447 | AK16: 510 | AL16: 523 | AM16: 484 | AN16: 753 | AO16: 1184 | AP16: 1182 | AQ16: 964 | AR16: 823 | AS16: 1606 | AT16: 2158 | AU16: 2167 | AV16: 1793 | AW16: 2733 | AX16: 2542 | AY16: 3080 | AZ16: 4582 | BA16: 4135 | BB16: 4201 | BC16: 6948 | BD16: 6623 | BE16: 8581 | BF16: 8526 | BG16: 9499 | BH16: 7802 | BI16: 10459 | BJ16: 13363 | BK16: 11059 | BL16: 13790 | BM16: 20128 | BN16: 28299 | BO16: 1447 | BP16: 36475 | BQ16: 41883 | BR16: 45739 | BS16: 48808 | BT16: 65568 | BU16: 64793 | BV16: 55242 | BW16: 59076 | BX16: 51446 | BY16: 50639 | BZ16: 45990 | CA16: 56347 | CB16: -38818 | CC16: 29206 | CD16: 35773 | CE16: 49803 | CF16: 44505 | CG16: 38768 | CH16: 53322
A17: Domestic financial sectors; uses of property income (paid) (IMA) | B17: Currency | C17: 1000000 | D17: USD | E17: Z1/Z1/FA796150005.A | F17: FA796150005.A | U17: 28375 | V17: 31565 | W17: 33664 | X17: 37300 | Y17: 41015 | Z17: 46360 | AA17: 50517 | AB17: 56352 | AC17: 62543 | AD17: 72323 | AE17: 86660 | AF17: 104356 | AG17: 114507 | AH17: 127228 | AI17: 153228 | AJ17: 189512 | AK17: 212084 | AL17: 219295 | AM17: 246736 | AN17: 289724 | AO17: 348978 | AP17: 437754 | AQ17: 574729 | AR17: 660175 | AS17: 685265 | AT17: 748920 | AU17: 813234 | AV17: 840487 | AW17: 895267 | AX17: 1005353 | AY17: 1174580 | AZ17: 1186834 | BA17: 1119129 | BB17: 1025787 | BC17: 1038542 | BD17: 1136497 | BE17: 1326789 | BF17: 1393849 | BG17: 1534950 | BH17: 1667204 | BI17: 1749831 | BJ17: 2046268 | BK17: 1949830 | BL17: 1657661 | BM17: 1593305 | BN17: 1790919 | BO17: 2253902 | BP17: 2881049 | BQ17: 3327787 | BR17: 2870792 | BS17: 2204834 | BT17: 2056568 | BU17: 2058269 | BV17: 2134884 | BW17: 2140466 | BX17: 2138534 | BY17: 2212369 | BZ17: 2253538 | CA17: 2551337 | CB17: 2803797 | CC17: 2927432 | CD17: 2563707 | CE17: 2580372 | CF17: 3167311 | CG17: 4294333 | CH17: 4622493
A18: Domestic financial sectors; interest paid (IMA) | B18: Currency | C18: 1000000 | D18: USD | E18: Z1/Z1/FA796130001.A | F18: FA796130001.A | U18: 23162 | V18: 26225 | W18: 28252 | X18: 31611 | Y18: 34834 | Z18: 38778 | AA18: 42609 | AB18: 47993 | AC18: 53654 | AD18: 60389 | AE18: 73497 | AF18: 89774 | AG18: 98929 | AH18: 110584 | AI18: 134752 | AJ18: 169257 | AK18: 191067 | AL18: 196291 | AM18: 218871 | AN18: 257445 | AO18: 311606 | AP18: 396208 | AQ18: 526856 | AR18: 613666 | AS18: 630741 | AT18: 688114 | AU18: 744588 | AV18: 767628 | AW18: 818536 | AX18: 911688 | AY18: 1064643 | AZ18: 1064147 | BA18: 992443 | BB18: 905313 | BC18: 900519 | BD18: 978939 | BE18: 1138356 | BF18: 1167614 | BG18: 1280859 | BH18: 1395785 | BI18: 1453932 | BJ18: 1722963 | BK18: 1652030 | BL18: 1347666 | BM18: 1269714 | BN18: 1404125 | BO18: 1826613 | BP18: 2391502 | BQ18: 2759876 | BR18: 2332160 | BS18: 1701673 | BT18: 1517441 | BU18: 1495439 | BV18: 1463847 | BW18: 1350935 | BX18: 1381931 | BY18: 1443837 | BZ18: 1506495 | CA18: 1684645 | CB18: 1938914 | CC18: 2047300 | CD18: 1607947 | CE18: 1480243 | CF18: 2052186 | CG18: 3160238 | CH18: 3458572
A19: Domestic financial sectors; distributed income of corporations, paid (IMA) | B19: Currency | C19: 1000000 | D19: USD | E19: Z1/Z1/FA796120005.A | F19: FA796120005.A | U19: 5159 | V19: 5299 | W19: 5355 | X19: 5637 | Y19: 6127 | Z19: 7507 | AA19: 7825 | AB19: 8285 | AC19: 8802 | AD19: 11841 | AE19: 13086 | AF19: 14517 | AG19: 15498 | AH19: 16551 | AI19: 18336 | AJ19: 20114 | AK19: 20863 | AL19: 22813 | AM19: 27727 | AN19: 32071 | AO19: 37030 | AP19: 41206 | AQ19: 47584 | AR19: 46833 | AS19: 54656 | AT19: 60569 | AU19: 68695 | AV19: 72920 | AW19: 76723 | AX19: 93635 | AY19: 109992 | AZ19: 122598 | BA19: 126765 | BB19: 120689 | BC19: 138171 | BD19: 157366 | BE19: 188290 | BF19: 225897 | BG19: 253227 | BH19: 271230 | BI19: 295107 | BJ19: 323440 | BK19: 302963 | BL19: 309456 | BM19: 320314 | BN19: 377178 | BO19: 419014 | BP19: 476720 | BQ19: 557858 | BR19: 530668 | BS19: 498720 | BT19: 528385 | BU19: 547929 | BV19: 654411 | BW19: 773964 | BX19: 741041 | BY19: 754833 | BZ19: 733827 | CA19: 852530 | CB19: 847844 | CC19: 862378 | CD19: 943267 | CE19: 1067456 | CF19: 1089082 | CG19: 1113015 | CH19: 1139976
A20: Domestic financial sectors; dividends paid (IMA) | B20: Currency | C20: 1000000 | D20: USD | E20: Z1/Z1/FA796121001.A | F20: FA796121001.A | H20: 1188 | I20: 1349 | J20: 1532 | K20: 1572 | L20: 1885 | M20: 1842 | N20: 1844 | O20: 1911 | P20: 1937 | Q20: 2184 | R20: 2337 | S20: 2427 | T20: 2856 | U20: 3494 | V20: 3657 | W20: 3487 | X20: 3822 | Y20: 4137 | Z20: 5300 | AA20: 5333 | AB20: 5667 | AC20: 5916 | AD20: 8623 | AE20: 10035 | AF20: 11474 | AG20: 11941 | AH20: 12483 | AI20: 15035 | AJ20: 16889 | AK20: 17292 | AL20: 18912 | AM20: 21677 | AN20: 25896 | AO20: 31937 | AP20: 36211 | AQ20: 39132 | AR20: 41532 | AS20: 46884 | AT20: 51374 | AU20: 59471 | AV20: 63344 | AW20: 60731 | AX20: 74221 | AY20: 91333 | AZ20: 102471 | BA20: 107119 | BB20: 105000 | BC20: 118670 | BD20: 138783 | BE20: 159219 | BF20: 187987 | BG20: 210856 | BH20: 225441 | BI20: 238137 | BJ20: 262227 | BK20: 244608 | BL20: 255317 | BM20: 270282 | BN20: 329897 | BO20: 371405 | BP20: 426730 | BQ20: 517212 | BR20: 508361 | BS20: 424512 | BT20: 441235 | BU20: 491191 | BV20: 584644 | BW20: 723103 | BX20: 722143 | BY20: 745204 | BZ20: 691619 | CA20: 800321 | CB20: 817558 | CC20: 829936 | CD20: 882395 | CE20: 1003280 | CF20: 1028036 | CG20: 1045349 | CH20: 1066883
A21: Domestic financial sectors; withdrawals from income of quasi-corporations, paid (IMA) | B21: Currency | C21: 1000000 | D21: USD | E21: Z1/Z1/FA796122001.A | F21: FA796122001.A | U21: 1665 | V21: 1642 | W21: 1868 | X21: 1815 | Y21: 1990 | Z21: 2207 | AA21: 2492 | AB21: 2618 | AC21: 2886 | AD21: 3218 | AE21: 3051 | AF21: 3043 | AG21: 3557 | AH21: 4068 | AI21: 3301 | AJ21: 3225 | AK21: 3571 | AL21: 3901 | AM21: 6050 | AN21: 6175 | AO21: 5093 | AP21: 4995 | AQ21: 8452 | AR21: 5301 | AS21: 7772 | AT21: 9195 | AU21: 9224 | AV21: 9576 | AW21: 15992 | AX21: 19414 | AY21: 18659 | AZ21: 20127 | BA21: 19646 | BB21: 15689 | BC21: 19501 | BD21: 18583 | BE21: 29071 | BF21: 37910 | BG21: 42371 | BH21: 45789 | BI21: 56970 | BJ21: 61213 | BK21: 58355 | BL21: 54139 | BM21: 50032 | BN21: 47281 | BO21: 47609 | BP21: 49990 | BQ21: 40646 | BR21: 22307 | BS21: 74208 | BT21: 87150 | BU21: 56738 | BV21: 69767 | BW21: 50861 | BX21: 18898 | BY21: 9629 | BZ21: 42208 | CA21: 52209 | CB21: 30286 | CC21: 32442 | CD21: 60872 | CE21: 64176 | CF21: 61046 | CG21: 67666 | CH21: 73093
A22: Domestic financial sectors; reinvested earnings on foreign direct investment in U.S.; paid (IMA) | B22: Currency | C22: 1000000 | D22: USD | E22: Z1/Z1/FA793192281.A | F22: FA793192281.A | H22: 39 | I22: 37 | J22: 55 | K22: 48 | L22: 56 | M22: 46 | N22: 36 | O22: 43 | P22: 41 | Q22: 49 | R22: 43 | S22: 39 | T22: 37 | U22: 54 | V22: 41 | W22: 57 | X22: 52 | Y22: 54 | Z22: 75 | AA22: 83 | AB22: 74 | AC22: 87 | AD22: 93 | AE22: 77 | AF22: 65 | AG22: 80 | AH22: 93 | AI22: 140 | AJ22: 141 | AK22: 154 | AL22: 191 | AM22: 138 | AN22: 208 | AO22: 342 | AP22: 340 | AQ22: 289 | AR22: -324 | AS22: -133 | AT22: 237 | AU22: -50 | AV22: -61 | AW22: 8 | AX22: 30 | AY22: -55 | AZ22: 89 | BA22: -79 | BB22: -215 | BC22: -149 | BD22: 192 | BE22: 143 | BF22: 338 | BG22: 864 | BH22: 189 | BI22: 792 | BJ22: -136 | BK22: -5163 | BL22: 539 | BM22: 3277 | BN22: 9616 | BO22: 8275 | BP22: 12827 | BQ22: 10053 | BR22: 7964 | BS22: 4441 | BT22: 10742 | BU22: 14901 | BV22: 16626 | BW22: 15567 | BX22: 15562 | BY22: 13699 | BZ22: 13216 | CA22: 14162 | CB22: 17039 | CC22: 17754 | CD22: 12493 | CE22: 32673 | CF22: 26043 | CG22: 21080 | CH22: 23945
A23: Domestic financial sectors; rents on land and natural resources paid (IMA) | B23: Currency | C23: 1000000 | D23: USD | E23: Z1/Z1/FA796112001.A | F23: FA796112001.A | U23: 0 | V23: 0 | W23: 0 | X23: 0 | Y23: 0 | Z23: 0 | AA23: 0 | AB23: 0 | AC23: 0 | AD23: 0 | AE23: 0 | AF23: 0 | AG23: 0 | AH23: 0 | AI23: 0 | AJ23: 0 | AK23: 0 | AL23: 0 | AM23: 0 | AN23: 0 | AO23: 0 | AP23: 0 | AQ23: 0 | AR23: 0 | AS23: 0 | AT23: 0 | AU23: 0 | AV23: 0 | AW23: 0 | AX23: 0 | AY23: 0 | AZ23: 0 | BA23: 0 | BB23: 0 | BC23: 0 | BD23: 0 | BE23: 0 | BF23: 0 | BG23: 0 | BH23: 0 | BI23: 0 | BJ23: 0 | BK23: 0 | BL23: 0 | BM23: 0 | BN23: 0 | BO23: 0 | BP23: 0 | BQ23: 0 | BR23: 0 | BS23: 0 | BT23: 0 | BU23: 0 | BV23: 0 | BW23: 0 | BX23: 0 | BY23: 0 | BZ23: 0 | CA23: 0 | CB23: 0 | CC23: 0 | CD23: 0 | CE23: 0 | CF23: 0 | CG23: 0 | CH23: 0
A24: Domestic financial sectors; net national income/balance of primary incomes, net (IMA) | B24: Currency | C24: 1000000 | D24: USD | E24: Z1/Z1/FA796140005.A | F24: FA796140005.A | U24: 5627 | V24: 6606 | W24: 6751 | X24: 7175 | Y24: 6847 | Z24: 6970 | AA24: 8215 | AB24: 8076 | AC24: 8499 | AD24: 9958 | AE24: 10420 | AF24: 10367 | AG24: 12001 | AH24: 14023 | AI24: 15145 | AJ24: 16193 | AK24: 16631 | AL24: 17819 | AM24: 20510 | AN24: 28545 | AO24: 29863 | AP24: 20621 | AQ24: 14663 | AR24: 13694 | AS24: 22708 | AT24: 27159 | AU24: 33876 | AV24: 27984 | AW24: 34857 | AX24: 35978 | AY24: 48915 | AZ24: 44603 | BA24: 64107 | BB24: 84955 | BC24: 69793 | BD24: 64707 | BE24: 85645 | BF24: 85342 | BG24: 93845 | BH24: 94047 | BI24: 104136 | BJ24: 105322 | BK24: 163045 | BL24: 193992 | BM24: 202382 | BN24: 222849 | BO24: 229076 | BP24: 247574 | BQ24: 154448 | BR24: 26987 | BS24: 286118 | BT24: 356478 | BU24: 293161 | BV24: 255250 | BW24: 149771 | BX24: 268314 | BY24: 239291 | BZ24: 342520 | CA24: 250196 | CB24: 302065 | CC24: 325975 | CD24: 187629 | CE24: 249854 | CF24: 322938 | CG24: 358274 | CH24: 525479
A25: Domestic financial sectors; current taxes on income, wealth, etc. paid (IMA) | B25: Currency | C25: 1000000 | D25: USD | E25: Z1/Z1/FA796220001.A | F25: FA796220001.A | U25: 3044 | V25: 2743 | W25: 2784 | X25: 2705 | Y25: 2737 | Z25: 2685 | AA25: 2631 | AB25: 2740 | AC25: 3164 | AD25: 3630 | AE25: 3614 | AF25: 3977 | AG25: 4813 | AH25: 5315 | AI25: 5223 | AJ25: 4386 | AK25: 4356 | AL25: 5923 | AM25: 7926 | AN25: 10296 | AO25: 10118 | AP25: 7281 | AQ25: 4321 | AR25: 2531 | AS25: 4698 | AT25: 5537 | AU25: 10527 | AV25: 15633 | AW25: 18474 | AX25: 20315 | AY25: 23215 | AZ25: 23364 | BA25: 29215 | BB25: 37485 | BC25: 47007 | BD25: 40316 | BE25: 54127 | BF25: 58459 | BG25: 63403 | BH25: 63137 | BI25: 60922 | BJ25: 68363 | BK25: 63938 | BL25: 69599 | BM25: 87272 | BN25: 99279 | BO25: 117208 | BP25: 134066 | BQ25: 114163 | BR25: 48713 | BS25: 42497 | BT25: 68484 | BU25: 71546 | BV25: 88785 | BW25: 98462 | BX25: 116261 | BY25: 112178 | BZ25: 113976 | CA25: 83341 | CB25: 84480 | CC25: 100408 | CD25: 99062 | CE25: 125094 | CF25: 128747 | CG25: 126152 | CH25: 140140
A26: Domestic financial sectors; other current transfers paid (IMA) | B26: Currency | C26: 1000000 | D26: USD | E26: Z1/Z1/FA796403005.A | F26: FA796403005.A | U26: 129 | V26: 244 | W26: 238 | X26: 284 | Y26: 702 | Z26: 890 | AA26: 1053 | AB26: 275 | AC26: 453 | AD26: 798 | AE26: 1262 | AF26: 586 | AG26: -154 | AH26: 34 | AI26: 323 | AJ26: 2566 | AK26: 3561 | AL26: 921 | AM26: -2639 | AN26: -1229 | AO26: 1850 | AP26: 2469 | AQ26: 3717 | AR26: 8587 | AS26: 9619 | AT26: 16057 | AU26: 15632 | AV26: 2558 | AW26: -4396 | AX26: -371 | AY26: 10430 | AZ26: 9435 | BA26: 7855 | BB26: 3517 | BC26: 2476 | BD26: -2207 | BE26: 7077 | BF26: 7024 | BG26: -3395 | BH26: 19328 | BI26: 9135 | BJ26: 27864 | BK26: 30625 | BL26: 10583 | BM26: -10204 | BN26: -6943 | BO26: -22738 | BP26: -20978 | BQ26: 10037 | BR26: 48812 | BS26: 37667 | BT26: 28570 | BU26: 28142 | BV26: -27616 | BW26: -18060 | BX26: 15122 | BY26: 21635 | BZ26: 64384 | CA26: 19585 | CB26: 30065 | CC26: 47275 | CD26: 35571 | CE26: 30449 | CF26: 78919 | CG26: 114261 | CH26: 140931
